Workbook

Sheet Judging
A1: display_id | B1: query_id | C1: question | D1: reference_answer | E1: chunk_id | F1: source_document_title | G1: candidate_chunk | H1: relevance_grade | I1: rationale | J1: batch | K1: status
A2: v2q-001-candidate-19 | B2: v2q-001 | C2: What is the minimum house size specified under PMAY-G? | D2: The minimum house size is 25 square metres, including a dedicated hygienic cooking area. | E2: pilot-v2-doc-pm-gkay-0000-c29b96f46a80 | F2: Pradhan Mantri Garib Kalyan Anna Yojana | G2: Pradhan Mantri Garib Kalyan Anna Yojana. Ministry Of Finance. Department Of Economic Affairs. The scheme "Pradhan Mantri Garib Kalyan Anna Yojana (PMGKAY)" has been launched by the Department of Food and Public Distribution, Ministry of Consumer Affairs, Food and Public Distribution, Government of India, and aims to ensure food security for the poor and vulnerable sections of the country by providing free food foodgrains. It was announced on 26 March 2020 during the COVID-19 pandemic and is operated by the Department of Food and Public Distribution under the Ministry of Consumer Affairs, Food and Public Distribution. Through this scheme, free foodgrains (rice or wheat, depending on the State) are provided to eligible ration card holders covered under the National Food Security Act, 2013, namely Antyodaya Anna Yojana (AAY) households and Priority Households (PHH). From 1 January 2023, the scheme was integrated into the food security framework, and foodgrains earlier given at the highly subsidised rates of ₹1, ₹2, and ₹3 per kilogram for coarse cereals, wheat, and rice, respectively, are now provided free of cost. The scheme has been extended by the Union Cabinet for 5 years starting from 1 January 2024 and is approved for continuation till 31 December 2028, with a total financial outlay of ₹11.80 lakh crore (₹11,80,000 crore). The scheme is implemented through the Targeted Public Distribution System (TPDS) by the state governments and Union Territory Administrations, with foodgrain allocation by the Government of India.. The scheme aims to ensure food security for the poor. Through this scheme, free foodgrains are provided to eligible ration card holders under the National Food Security Act, 2013.. Antyodaya Anna Yojana (AAY) families receive 35 kilograms of foodgrains per family per month. Priority Household (PHH) beneficiaries receive 5 kilograms of foodgrains per person per month. The foodgrains are provided as | H2: 0 | J2: =INT((ROW()-2)/50)+1 -> 1 | K2: =IF(H2="","Pending",IF(OR(H2="0",H2="1",H2="2",H2="U"),"Complete","Invalid")) -> Complete
A3: v2q-004-candidate-10 | B3: v2q-004 | C3: What is the maximum micro-loan amount stated for PMMY? | D3: PMMY facilitates micro-credit loans up to ₹20 lakh for eligible income-generating micro-enterprises. | E3: pilot-v2-doc-pmegp-0002-f67d4c730011 | F3: Prime Minister's Employment Generation Programme | G3: under the Business/Service sector is ₹20,00,000. The balance amount (excluding the own contribution)of the total project cost will be provided by Banks. If the total project cost exceeds ₹50,00,000 or ₹20,00,000 for Manufacturing and Service/Business sector respectively, the balance amount may be provided by Banks without any Government subsidy. 2. 2nd Loan for Upgradation of Existing PMEGP / REGP / MUDRA Units a) Categories of beneficiaries under PMEGP (for upgradation of existing units): All Categories b) Beneficiary's contribution (of project cost): 10% c) Rate of Subsidy (of project cost): 15% (20% in NER and Hill States). Note: The maximum cost of the project/unit admissible for Margin Money subsidy under the Manufacturing sector for upgradation is ₹10,00,00,000. The maximum subsidy would be ₹15,00,000 (₹20,00,000 for NER and Hill States). The maximum cost of the project/unit admissible for Margin Money subsidy under the Business/Service sector for upgradation is ₹25,00,000. The maximum subsidy would be ₹3,75,000 (₹5,00,000 for NER and Hill States). The balance amount (excluding the own contribution)of the total project cost will be provided by Banks. If the total project cost exceeds ₹10,00,00,000 or ₹25,00,000 for Manufacturing and Service/Business sector respectively, the balance amount may be provided by banks without any Government subsidy.. For PMEGP new enterprises (Units) Any individual, above 18 years of age. There will be no income ceiling for assistance in setting up projects under PMEGP. For setting up of project costing above Rs.10 lakh in the Manufacturing sector and above ₹ 5,00,000 in the Business /Service sector, the beneficiaries should possess at least VIII standard pass educational qualification. Assistance under the scheme is available only for new projects sanctioned specifically under the PMEGP. Existing Units (under PMRY, REGP, or any other scheme of the Government of India or State Government) and the units that have already availed | H3: 0 | J3: =INT((ROW()-2)/50)+1 -> 1 | K3: =IF(H3="","Pending",IF(OR(H3="0",H3="1",H3="2",H3="U"),"Complete","Invalid")) -> Complete
A4: v2q-005-candidate-12 | B4: v2q-005 | C4: How many days of wage employment does MGNREGA guarantee a rural household in a financial year? | D4: MGNREGA guarantees at least 100 days of wage employment per financial year to a rural household whose adult members volunteer for unskilled work. | E4: pilot-v2-doc-pm-kmy-guidelines-0006-2652020c834e | F4: Pradhan Mantri Kisan Maan Dhan Yojana Operational Guidelines | G4: same day every month as enrolment date. The beneficiaries may also chose an option to pay their contributions on quarterly, 4-monthly or half-yearly basis. Such contributions will fall due on the same day of such period as the date of enrollment; 4 (x) The amount of the monthly contribution shall range between Rs.55 to Rs.200 per month depending upon the age of entry of the farmers into the Scheme, as per the following contribution chart: Superannuation Member's Government’s Total contribution Entry Age Age contribution (Rs.) contribution (Rs.) (Rs.) (1) (2) (3) (4) (5) 18 60 55 55 110 19 60 58 58 116 20 60 61 61 122 21 60 64 64 128 22 60 68 68 136 23 60 72 72 144 24 60 76 76 152 25 60 80 80 160 26 60 85 85 170 27 60 90 90 180 28 60 95 95 190 29 60 100 100 200 30 60 105 105 210 31 60 110 110 220 32 60 120 120 240 33 60 130 130 260 34 60 140 140 280 35 60 150 150 300 36 60 160 160 320 37 60 170 170 340 38 60 180 180 360 39 60 190 190 380 40 60 200 200 400 (xi) In case of death of subscriber before vesting date, the spouse of subscriber shall have an option of continuing the scheme by payment of remaining contributions under the scheme, provided she/he is not already an SMF beneficiary of the Scheme. The rate of contribution and vesting date shall remain the same. Pension accruals will be calculated as if subscriber were to be alive on the vesting date. However, the same pension would be payable to the spouse. Upon death of spouse after vesting date, pension corpus would be transferred back to | H4: 0 | J4: =INT((ROW()-2)/50)+1 -> 1 | K4: =IF(H4="","Pending",IF(OR(H4="0",H4="1",H4="2",H4="U"),"Complete","Invalid")) -> Complete
A5: v2q-027-candidate-14 | B5: v2q-027 | C5: What livelihood mechanism does PM SVANidhi offer street vendors, and which other programme from its ministry addresses housing shortages for eligible urban households? | D5: PM SVANidhi offers street vendors collateral-free working-capital loans, interest subsidy, and digital-payment incentives. PMAY-U, under the same Ministry of Housing and Urban Affairs, provides housing support for eligible urban households. | E5: pilot-v2-doc-pm-kisan-guidelines-0000-bbe94f08550e | F5: PM-KISAN Operational Guidelines | G5: PRADHAN MANTRI KISAN SAMMAN NIDHI SCHEME (PM-KISAN SCHEME) OPERATIONAL GUIDELINES (REVISED AS ON 29.03.2020) MINISTRY OF AGRICULTURE & FARMERS’ WELFARE DEPARTMENT OF AGRICULTURE, COOPERATION & FARMERS’ WELFARE (DAC&FW) 1 PRADHAN MANTRI KISAN SAMMAN NIDHI (PM-KISAN) SCHEME OPERATIONAL GUIDELINES 1. Scheme With a view to provide income support to all landholding farmers’ families in the country, having cultivable land, the Central Government has implemented a Central Sector Scheme, namely, “Pradhan Mantri Kisan Samman Nidhi (PM-KISAN)”. 2. Objective and Benefits The scheme aims to supplement the financial needs of all landholding farmers’ families in procuring various inputs to ensure proper crop health and appropriate yields, commensurate with the anticipated farm income as well as for domestic needs. Under the Scheme an amount of Rs.6000/- per year is released by the Central Government online directly into the bank accounts of the eligible farmers under Direct Benefit Transfer mode, subject to certain exclusions. 3. Definition of farmer’s family A landholder farmer’s family is defined as “a family comprising of husband, wife and minor children who owns cultivable land as per land records of the concerned State/UT”. The existing land-ownership system will be used for identification of beneficiaries for calculation of benefit. 4 Exclusions 4.1 The following categories of beneficiaries of higher economic status shall not be eligible for benefit under the scheme: (a) All Institutional Land holders; and (b) Farmer families in which one or more of its members belong to following categories : i) Former and present holders of constitutional posts ii) Former and present Ministers / State Ministers and former / present Members of Lok Sabha / Rajya Sabha / State Legislative Assemblies / State Legislative Councils, former and present Mayors of Municipal Corporations, former and present Chairpersons of District Panchayats. iii) All serving or retired officers and employees of Central / | H5: 0 | J5: =INT((ROW()-2)/50)+1 -> 1 | K5: =IF(H5="","Pending",IF(OR(H5="0",H5="1",H5="2",H5="U"),"Complete","Invalid")) -> Complete
A6: v2q-029-candidate-19 | B6: v2q-029 | C6: What migrant-focused facility distinguishes Ujjwala 2.0, and what clean-cooking transition was established by its predecessor programme? | D6: Ujjwala 2.0 added 1.6 crore LPG connections with a special facility for migrant households. Its predecessor, Pradhan Mantri Ujjwala Yojana, sought to replace traditional cooking fuels with LPG access for rural and deprived households. | E6: pilot-v2-doc-pm-gkay-0000-c29b96f46a80 | F6: Pradhan Mantri Garib Kalyan Anna Yojana | G6: Pradhan Mantri Garib Kalyan Anna Yojana. Ministry Of Finance. Department Of Economic Affairs. The scheme "Pradhan Mantri Garib Kalyan Anna Yojana (PMGKAY)" has been launched by the Department of Food and Public Distribution, Ministry of Consumer Affairs, Food and Public Distribution, Government of India, and aims to ensure food security for the poor and vulnerable sections of the country by providing free food foodgrains. It was announced on 26 March 2020 during the COVID-19 pandemic and is operated by the Department of Food and Public Distribution under the Ministry of Consumer Affairs, Food and Public Distribution. Through this scheme, free foodgrains (rice or wheat, depending on the State) are provided to eligible ration card holders covered under the National Food Security Act, 2013, namely Antyodaya Anna Yojana (AAY) households and Priority Households (PHH). From 1 January 2023, the scheme was integrated into the food security framework, and foodgrains earlier given at the highly subsidised rates of ₹1, ₹2, and ₹3 per kilogram for coarse cereals, wheat, and rice, respectively, are now provided free of cost. The scheme has been extended by the Union Cabinet for 5 years starting from 1 January 2024 and is approved for continuation till 31 December 2028, with a total financial outlay of ₹11.80 lakh crore (₹11,80,000 crore). The scheme is implemented through the Targeted Public Distribution System (TPDS) by the state governments and Union Territory Administrations, with foodgrain allocation by the Government of India.. The scheme aims to ensure food security for the poor. Through this scheme, free foodgrains are provided to eligible ration card holders under the National Food Security Act, 2013.. Antyodaya Anna Yojana (AAY) families receive 35 kilograms of foodgrains per family per month. Priority Household (PHH) beneficiaries receive 5 kilograms of foodgrains per person per month. The foodgrains are provided as | H6: 0 | J6: =INT((ROW()-2)/50)+1 -> 1 | K6: =IF(H6="","Pending",IF(OR(H6="0",H6="1",H6="2",H6="U"),"Complete","Invalid")) -> Complete
A7: v2q-034-candidate-08 | B7: v2q-034 | C7: How do three programmes meet distinct household needs for rural housing, clean cooking, and food security? | D7: PMAY-G supports pucca rural housing with basic amenities; PMUY provides LPG access to deprived households replacing traditional cooking fuels; PMGKAY provides free foodgrains to eligible AAY and PHH ration-card holders. | E7: pilot-v2-doc-pmegp-0003-43256e8e6645 | F7: Prime Minister's Employment Generation Programme | G7: sector and above ₹ 5,00,000 in the Business /Service sector, the beneficiaries should possess at least VIII standard pass educational qualification. Assistance under the scheme is available only for new projects sanctioned specifically under the PMEGP. Existing Units (under PMRY, REGP, or any other scheme of the Government of India or State Government) and the units that have already availed of Government Subsidy under any other scheme of the Government of India or State Government are not eligible. For up-gradation of existing PMEGP / REGP / MUDRA units Margin Money(subsidy)claimed under PMEGP has to be successfully adjusted on the completion of the lock-in period of 3 years. The first loan under PMEGP/REGP/MUDRA has to be successfully repaid in the stipulated time. The unit is profit-making with good turnover and has the potential for further growth in turnover and profit with modernization/upgrading of the technology. Reservation / Preference / Priority Priority will be given to the persons affected by natural calamities/disasters in the areas which are declared as affected by "disaster" as defined under Section 2(d) of the Disaster Management Act, 2005 by the Ministry of Home Affairs.. For PMEGP new enterprises (Units): Existing Units (under PMRY, REGP, or any other scheme of the Government of India or State Government) and the units that have already availed of Government Subsidy under any other scheme of the Government of India or State Government are not eligible. Only one person from one family is eligible for obtaining financial assistance for setting up of projects under PMEGP. The 'family’ includes self and spouse. Negative List of Activities: The following list of activities will not be permitted under PMEGP for setting up of micro enterprises/ projects/units:- Any Industry/ Business connected with Meat(slaughtered), i.e., processing, canning and/or serving items made of it as food, production/Manufacturing or | H7: 0 | J7: =INT((ROW()-2)/50)+1 -> 1 | K7: =IF(H7="","Pending",IF(OR(H7="0",H7="1",H7="2",H7="U"),"Complete","Invalid")) -> Complete
A8: v2q-019-candidate-22 | B8: v2q-019 | C8: What role does the Ministry of Petroleum and Natural Gas have in Ujjwala 2.0? | D8: The ministry introduced Ujjwala 2.0 to provide LPG connections and promote clean cooking fuel among poor, rural, and deprived households. | E8: pilot-v2-doc-apy-0000-c43dd88d7899 | F8: Atal Pension Yojana | G8: Atal Pension Yojana. Ministry Of Finance. Department of Financial Service. Banks. Atal Pension Yojana (APY) is an old age income security scheme for a savings account holder in the age group of 18-40 years who is not an income tax-payee. The scheme helps in addressing the longevity risks among the workers in the unorganized sector and encourages the workers to voluntarily save for their retirement. Focus of APY The scheme is mainly targeted at the poor, the under-privileged and workers in the unorganized sector. APY Subscriber Contribution Chart - https://www.npscra.nsdl.co.in/nsdl/scheme-details/APYSubscribersContributionChart1.pdf Charges and fees and overdue interest under APY: The charges and fees and the overdue interest for non-payment or delayed payment of prescribed contribution amount shall be levied on the subscribers of APY. These charges and their method of application shall be prescribed by PFRDA from time to time, in consultation with the Central Government. Raising Grievance Under APY A subscriber can raise grievance anytime free of cost from anywhere by visiting: www.npscra.nsdl.co.in &gt;&gt;Home &gt;&gt; select: NPS-Lite or through CGMS Subscriber raising the grievance will be allotted a token number against the grievance raised. Subscriber may check the status of the grievance under “Check the status of Grievance / Enquiry already registered”.. Atal Pension Yojana (APY) is an old age income security scheme for a savings account holder in the age group of 18-40 years, who is not an income tax-payee. It helps to address longevity risks among workers in unorganized sector and encourages the workers to voluntarily save for retirement.. Upon exit on attaining 60 years The subscriber shall receive the following three benefits on attaining the age of 60: (i) Guaranteed minimum pension amount: Each subscriber under APY shall receive a guaranteed minimum pension of Rs. 1000/- per month or Rs. 2000/- per month or Rs. 3000/- per | H8: 0 | J8: =INT((ROW()-2)/50)+1 -> 1 | K8: =IF(H8="","Pending",IF(OR(H8="0",H8="1",H8="2",H8="U"),"Complete","Invalid")) -> Complete
A9: v2q-007-candidate-08 | B9: v2q-007 | C9: What is the full form of PMJJBY, and which event does its life insurance cover? | D9: PMJJBY stands for Pradhan Mantri Jeevan Jyoti Bima Yojana and provides life-insurance cover for death due to any reason. | E9: pilot-v2-doc-pmjdy-0001-95c3d046d79a | F9: Pradhan Mantri Jan Dhan Yojana | G9: Basic Savings Bank Deposit Account (BSBDA) Any Indian citizen eligible to open a regular bank account can open a BSBDA. Such an account does not require any minimum balance maintenance. The account holders can use both bank branches, ATMs and Banking Correspondents (BCs) for depositing and withdrawing cash. However, one cannot withdraw cash more than four times a month. Small Account/Chota Khata Under Jan Dhan Yojana, people can open small bank accounts without presenting legal documents. These accounts would be valid normally for a period of twelve months. Thereafter, such accounts would be allowed to a continue for a further period of twelve more months, if the account-holder provides a document showing that he/she has applied for any of the Officially Valid Document, within 12 months of opening the small account. RuPay Debit Card with inbuilt accident insurance Under PMJDY, a free Rupay debit card, with inbuilt accident insurance cover of Rs.2 lakhs (Rs 1 lakh for accounts opened before 28.08.2018), is issued to all beneficiaries. Overdraft Facility Under PMJDY, beneficiaries can avail OD facility upto Rs. 10,000/-. Business Correspondents (BCs)/Bank Mitras BCs/Bank Mitras are retail agents engaged by banks for providing banking services at locations other than a bank branch/ATM. It is mainly meant for the rural areas, where bank branches are far-flung. BCs/Bank Mitras connect with the residents and guide them with banking solutions such as savings accounts, deposits, payments and withdrawals, mini account statements, etc. Banks with their strong network of BCs/Bank Mitras are providing hassle free services to the customers in remote / rural areas.. The applicant should be an Indian National. If minors above ten years apply, they will require support from their legal guardians for administering their PMJDY account.. Step 1- Go to the official portal of PMJDY. Step 2- Under the &quot;e-documents&quot; section, | H9: 0 | J9: =INT((ROW()-2)/50)+1 -> 1 | K9: =IF(H9="","Pending",IF(OR(H9="0",H9="1",H9="2",H9="U"),"Complete","Invalid")) -> Complete
A10: v2q-029-candidate-13 | B10: v2q-029 | C10: What migrant-focused facility distinguishes Ujjwala 2.0, and what clean-cooking transition was established by its predecessor programme? | D10: Ujjwala 2.0 added 1.6 crore LPG connections with a special facility for migrant households. Its predecessor, Pradhan Mantri Ujjwala Yojana, sought to replace traditional cooking fuels with LPG access for rural and deprived households. | E10: pilot-v2-doc-pmay-g-0001-db2db8af1543 | F10: Pradhan Mantri Awaas Yojana - Gramin | G10: years from 2016-17 to 2018-19 and enable construction of quality houses by the beneficiaries using local materials, designs and trained masons. For houses to become homes, adoption of a habitat approach through convergence is proposed.. Launch on 1st April 2016, Pradhan Mantri Awaas Yojana Gramin (PMAY-G) is centre's flagship mission by the Ministry of Rural Development (MoRD), implemented by the Ministry of Housing and Urban Affairs (MoHUA). PMAY-G addresses the rural housing shortage and bridges the housing deficit in rural areas. Financial Assistance of ₹ 1,20,000 per unit for plain areas; and ₹ 1,30,000 per unit for hilly areas, difficult areas, and IAP districts (Himalayan states, North-Eastern states, and Union Territories of Jammu & Kashmir). A willing beneficiary can avail of institutional finance (loan) of up to ₹ 70,000 at 3% lower interest rate, to build a permanent house. The maximum principal amount for which subsidy can be sought is ₹ 2,00,000. The minimum size of the house shall be is 25 sq m including a dedicated area for hygienic cooking. In convergence with Swachh Bharat Mission-Gramin (SBM-G), the beneficiaries get financial assistance of up to ₹ 12,000 for the construction of toilets. In convergence with MGNREGA, the beneficiary is entitled to employment as unskilled labor (Rural Mason Training) at ₹ 90.95 per day for 95 days. In convergence with Pradhan Mantri Ujjwala Yojana, one LPG connection per house is provided. Convergence with different government programmes for piped drinking water, electricity connection, clean & efficient cooking fuel, treatment of social and liquid waste, etc. Payments are made electronically directly to bank accounts or post office accounts that are linked to Aadhaar. Note: Beneficiaries are identified using the "Housing Deprivation Parameters" from the Socio-Economic and Caste Census (SECC) 2011, further verified by the Gram Sabhas.. The universe of eligible beneficiaries under | H10: 0 | J10: =INT((ROW()-2)/50)+1 -> 1 | K10: =IF(H10="","Pending",IF(OR(H10="0",H10="1",H10="2",H10="U"),"Complete","Invalid")) -> Complete
A11: v2q-021-candidate-12 | B11: v2q-021 | C11: How do insurance companies and banks participate in PMFBY? | D11: PMFBY is implemented through a network of insurance companies and banks to provide crop-insurance protection to farmers. | E11: pilot-v2-doc-ab-pmjay-0001-a632a7205efc | F11: Ayushman Bharat - Pradhan Mantri Jan Arogya Yojana | G11: per family per year for secondary and tertiary hospitalization to poor and vulnerable families.. AB PM-JAY is a health insurance scheme for low-income families in rural and urban areas. The scheme aims to provide affordable healthcare facilities to the Poor. It is the largest health assurance scheme in the world which aims at providing a health cover of ₹5,00,000/- per family per year.. Financial Health Insurance Cover: Annual Hospitalization Coverage: Cashless coverage up to ₹5,00,000/- per family per year.- Comprehensive Treatment Costs: Covers consultation, medicines, diagnostics, surgery, ICU, implants, accommodation, and food.- Pre and Post Hospitalization Support: Covers 3 days pre-hospitalization and 15 days post-hospitalization expenses.- Treatment Complication Coverage: Covers complications arising during treatment. Coverage Features: Pre-Existing Disease Coverage: Covers all pre-existing diseases from day one.- No Family Size Limit: No restriction on age, gender, or family size.- Nationwide Portability: Benefits available across India in empanelled hospitals.- Wide Procedure Coverage: Covers approximately 1,929 medical procedures.. Rural Beneficiaries Out of the total seven deprivation criteria for rural areas, PM-JAY covered all such families who fall into at least one of the following six deprivation criteria and automatic inclusion(Destitute/ living on alms, manual scavenger households, primitive tribal group, legally released bonded labour) criteria: Only one room with kucha walls and kucha roof No adult member between ages 16 to 59 Households with no adult male member between ages 16 to 59 Disabled member and no able-bodied adult member SC/ST households Landless households deriving a major part of their income from manual casual labour Automatically includedHouseholds without shelter Destitute/ living on alms, Manual scavenger families, Primitive tribal groups, Legally released bonded labour. Urban Beneficiaries For urban areas, the following 11 occupational categories of workers are eligible for the scheme: Ragpicker Beggar Domestic worker Street vendor/ Cobbler/hawker / other service provider working on streets | H11: 0 | J11: =INT((ROW()-2)/50)+1 -> 1 | K11: =IF(H11="","Pending",IF(OR(H11="0",H11="1",H11="2",H11="U"),"Complete","Invalid")) -> Complete
A12: v2q-002-candidate-07 | B12: v2q-002 | C12: What maximum premium rates can farmers pay under PMFBY for Kharif, Rabi, and annual commercial or horticultural crops? | D12: Farmers pay at most 2% for Kharif food and oilseed crops, 1.5% for Rabi food and oilseed crops, and 5% for annual commercial or horticultural crops. | E12: pilot-v2-doc-pmay-g-0001-db2db8af1543 | F12: Pradhan Mantri Awaas Yojana - Gramin | G12: years from 2016-17 to 2018-19 and enable construction of quality houses by the beneficiaries using local materials, designs and trained masons. For houses to become homes, adoption of a habitat approach through convergence is proposed.. Launch on 1st April 2016, Pradhan Mantri Awaas Yojana Gramin (PMAY-G) is centre's flagship mission by the Ministry of Rural Development (MoRD), implemented by the Ministry of Housing and Urban Affairs (MoHUA). PMAY-G addresses the rural housing shortage and bridges the housing deficit in rural areas. Financial Assistance of ₹ 1,20,000 per unit for plain areas; and ₹ 1,30,000 per unit for hilly areas, difficult areas, and IAP districts (Himalayan states, North-Eastern states, and Union Territories of Jammu & Kashmir). A willing beneficiary can avail of institutional finance (loan) of up to ₹ 70,000 at 3% lower interest rate, to build a permanent house. The maximum principal amount for which subsidy can be sought is ₹ 2,00,000. The minimum size of the house shall be is 25 sq m including a dedicated area for hygienic cooking. In convergence with Swachh Bharat Mission-Gramin (SBM-G), the beneficiaries get financial assistance of up to ₹ 12,000 for the construction of toilets. In convergence with MGNREGA, the beneficiary is entitled to employment as unskilled labor (Rural Mason Training) at ₹ 90.95 per day for 95 days. In convergence with Pradhan Mantri Ujjwala Yojana, one LPG connection per house is provided. Convergence with different government programmes for piped drinking water, electricity connection, clean & efficient cooking fuel, treatment of social and liquid waste, etc. Payments are made electronically directly to bank accounts or post office accounts that are linked to Aadhaar. Note: Beneficiaries are identified using the "Housing Deprivation Parameters" from the Socio-Economic and Caste Census (SECC) 2011, further verified by the Gram Sabhas.. The universe of eligible beneficiaries under | H12: 0 | J12: =INT((ROW()-2)/50)+1 -> 1 | K12: =IF(H12="","Pending",IF(OR(H12="0",H12="1",H12="2",H12="U"),"Complete","Invalid")) -> Complete
A13: v2q-024-candidate-10 | B13: v2q-024 | C13: Which national health-assurance programme does NHA implement under the health ministry? | D13: The National Health Authority implements AB-PMJAY under the Ministry of Health and Family Welfare. | E13: pilot-v2-doc-pm-janman-0002-d0844e3327b6 | F13: PM Janjati Adivasi Nyaya Maha Abhiyan (PM JANMAN) | G13: physical survey conducted by state governments using the mobile application on the PM Gati-shakti Portal. Eligibility Specific to Interventions The applicant household seeking a pucca house must currently reside in a kaccha house. The applicant household seeking solar power solutions must be an unelectrified household not covered under the Revamped Distribution Sector Scheme (RDSS). The applicant household seeking an on-grid electricity connection shall be an identified beneficiary household under PM-JANMAN, irrespective of standard eligibility criteria under the Revamped Distribution Sector Scheme (RDSS) for the State and Electricity distribution company (DISCOM).. Step 1: Initiation of Identification and Physical Survey The State Governments initiates a detailed physical survey of each Particularly Vulnerable Tribal Group habitation to ascertain the gaps regarding the 11 critical interventions covered under the mission. The data gathered during this exhaustive survey is simultaneously updated and cross-verified on a mobile application developed on the PM Gati-shakti Portal. Step 2: Facilitation of Application Filing for Eligible Beneficiaries The Block Level Implementation Team, consisting of officers designated by the District Collector, will be responsible for identifying each beneficiary family who has not yet been saturated with entitlements and will facilitate the necessary application filing for the respective schemes. The District Level Committee is also responsible for the registration and filling of applications of eligible beneficiaries for each scheme covered under the mission. Step 3: Verification and Project Approval Following the application filing and preliminary eligibility checks, certain proposals for infrastructure, such as the sanctioning of Multi-Purpose Centers, must be forwarded by the Secretary/Principal Secretary, State Tribal Welfare Department to the Ministry of Tribal Affairs. These proposals are subsequently examined by the relevant division, approved by the Mission Director of PM-JANMAN, and granted financial concurrence by the Internal Finance Division. | H13: 0 | J13: =INT((ROW()-2)/50)+1 -> 1 | K13: =IF(H13="","Pending",IF(OR(H13="0",H13="1",H13="2",H13="U"),"Complete","Invalid")) -> Complete
... A26: v2q-027-candidate-21 | B26: v2q-027 | C26: What livelihood mechanism does PM SVANidhi offer street vendors, and which other programme from its ministry addresses housing shortages for eligible urban households? | D26: PM SVANidhi offers street vendors collateral-free working-capital loans, interest subsidy, and digital-payment incentives. PMAY-U, under the same Ministry of Housing and Urban Affairs, provides housing support for eligible urban households. | E26: pilot-v2-doc-mgnrega-0001-5203a455caa6 | F26: Mahatma Gandhi National Rural Employment Guarantee Act | G26: entitled to a travel and subsistence allowance (10% of the minimum wage). Wages are paid within a week, or fifteen days at most. Men and Women are paid equally. Shade, drinking water, and first-aid are provided at every worksite. Exclusive measures for the promotion of the participation of the disabled persons: Identification of suitable works Mobilization of disabled persons by focussing on awareness and special provisions Specifically identified works for disabled persons in the case of large GPs Preference to appoint as mates and as workers for providing drinking water, to manage crèches, etc., at the worksites Adoption of tools and equipment/facilities at workplaces Treating persons with disabilities with respect Special drive to ensure 100 days of employment to such households Provide a special job card of a distinct color Specific attention and provisions for Senior Citizens: Exclusive senior citizen groups may be formed and special works which require lesser physical effort are identified and allotted to these groups. Specific attention and provisions for Internally Displaced Persons: A special job card to be provided will be valid till these families are displaced and will lose its validity as soon as they return to their original place of residence.. The applicant must be at least 18 years of age. The applicant must be residing in a Rural Area.. NA. Step 1: The application for registration may be given on plain paper to the local Gram Panchayat. An individual may appear personally before the Panchayat Secretary or Gram Rozgar Sahayak and make an oral request for registration, in which case the particulars required will be noted by the Gram Rojgar Sahayak or the Panchayat Secretary. Application for registration should contain names of those adult members of the household who are willing to do unskilled manual work. Particulars such as age, sex, SC/ST | H26: 0 | J26: =INT((ROW()-2)/50)+1 -> 1 | K26: =IF(H26="","Pending",IF(OR(H26="0",H26="1",H26="2",H26="U"),"Complete","Invalid")) -> Complete
A27: v2q-017-candidate-11 | B27: v2q-017 | C27: Which training route serves people no longer in education or work who need an initial occupational skill? | D27: PMKVY 4.0 Short-Term Training provides fresh skilling, reskilling, or upskilling for groups including school or college dropouts and unemployed youth. | E27: pilot-v2-doc-pmkvy-rpl-0001-9ccf0701dcf9 | F27: Pradhan Mantri Kaushal Vikas Yojana 4.0 - Recognition Of Prior Learning | G27: charged to the candidate for pre-screening. Assessment and Certification, with a payout of ₹600 per candidate per assessment provided to the Sector Skill Councils (SSCs) / Awarding Bodies for overseeing and facilitating final assessments. Accidental Insurance with one year of coverage, paid from the scheme (as per prevailing rates, ₹14.16). A T-shirt is provided to the trainee by the RPL-PIA at its own cost. A graded Skill Certificate and Marksheet on passing, with the grade awarded as Grade A (85% and above) or Grade B (70% to less than 85%). Conditions associated with the benefits: The pass percentage for a Qualification Pack (QP) is 70%; a candidate must achieve marks greater than or equal to 70% to be awarded the Skill Certificate. Marks scored in the Core National Occupational Standards (NOS) of a QP are given 70% weightage, and the remaining 30% weightage is from the Non-Core NOS. Certification is at the same NSQF level as determined during pre-screening. AEBAS-based compulsory attendance is applicable, and more than 70% biometric attendance is required to appear for the assessment. Indicative average unit (per-candidate) cost by RPL type RPL with upskilling (30 hours) at an Accredited and Affiliated Training Centre: ₹3,126.18 per candidate. RPL with upskilling (30 hours) at Industry premises: ₹2,826.18 per candidate. RPL with upskilling (60 hours) at an Accredited and Affiliated Training Centre: ₹3,962.88 per candidate. RPL with upskilling (60 hours) at Industry premises: ₹3,662.88 per candidate. (Note on the base cost: a fixed cost of ₹2,000 per candidate applies for RPL at an Accredited and Affiliated Training Centre and ₹1,700 for RPL at Industry premises for 12 hours of training; the reduction of ₹300 at Industry premises is owing to availability of infrastructure and lower mobilisation cost. Additional hours beyond 12 are paid at the discounted Common Norm of | H27: 0 | I27: RPL sub-scheme chunk for STT question — RPL targets experienced workers, not dropouts/unemployed needing initial skills. | J27: =INT((ROW()-2)/50)+1 -> 1 | K27: =IF(H27="","Pending",IF(OR(H27="0",H27="1",H27="2",H27="U"),"Complete","Invalid")) -> Complete
A28: v2q-009-candidate-09 | B28: v2q-009 | C28: What does APY stand for, and what monthly pension range does it guarantee after age 60? | D28: APY stands for Atal Pension Yojana and offers guaranteed monthly pension options from ₹1,000 to ₹5,000 after age 60. | E28: pilot-v2-doc-pm-kisan-guidelines-0001-5ad8f250b7e2 | F28: PM-KISAN Operational Guidelines | G28: i) Former and present holders of constitutional posts ii) Former and present Ministers / State Ministers and former / present Members of Lok Sabha / Rajya Sabha / State Legislative Assemblies / State Legislative Councils, former and present Mayors of Municipal Corporations, former and present Chairpersons of District Panchayats. iii) All serving or retired officers and employees of Central / State Government Ministries / Offices / Departments and their field units, Central or State PSEs and Attached offices / Autonomous Institutions under Government as well as regular 2 employees of the Local Bodies (Excluding Multi Tasking Staff / Class IV / Group D employees) iv) All superannuated / retired pensioners whose monthly pension is Rs.10,000/- or more (Excluding Multi Tasking Staff / Class IV / Group D employees) v) All Persons who paid Income Tax in last assessment year. vi) Professionals like Doctors, Engineers, Lawyers, Chartered Accountants, and Architects registered with Professional bodies and carrying out profession by undertaking practices. (c) In case of new beneficiaries being uploaded on the PM-KISAN Portal, all land holding farmers’ families who are Non-resident Indians (NRIs) in terms of the provisions of the Income Tax Act, 1961 shall be excluded from any benefit under the Scheme. 4.2 For the purpose of exclusion State / UT Governments can certify the eligibility of the beneficiaries based on self declaration by the beneficiaries. In case beneficiary is not available / does not reside in the village, State / UT Governments may consider certification based on the declaration by other adult member of his / her family. In case of incorrect self declaration, beneficiary shall be liable for recovery of transferred financial benefit and other penal actions as per law. 5. Methodology for calculation of benefit 5.1 The benefit shall be paid to only those farmers’ families whose | H28: 0 | J28: =INT((ROW()-2)/50)+1 -> 1 | K28: =IF(H28="","Pending",IF(OR(H28="0",H28="1",H28="2",H28="U"),"Complete","Invalid")) -> Complete
A29: v2q-001-candidate-06 | B29: v2q-001 | C29: What is the minimum house size specified under PMAY-G? | D29: The minimum house size is 25 square metres, including a dedicated hygienic cooking area. | E29: pilot-v2-doc-pmay-u-0000-0b5e95b2690a | F29: Pradhan Mantri Awas Yojana - Urban | G29: Pradhan Mantri Awas Yojana - Urban. Ministry Of Housing & Urban Affairs. The “Pradhan Mantri Awas Yojana – Urban (PMAY-U)” was launched on 25th June 2015 by the Ministry of Housing &amp; Urban Affairs, Government of India with the vision of “Housing for All” to provide pucca houses to eligible urban households. Implemented by the Ministry of Housing and Urban Affairs, the scheme addresses urban housing shortages, especially for EWS, LIG, and MIG categories, including slum dwellers. It promotes affordable and sustainable housing through components like the Credit Linked Subsidy Scheme (CLSS), offering interest subsidies on housing loans. The mission covers all statutory towns and notified urban areas as per Census 2011. Aadhaar is mandatory for all eligible beneficiaries under the scheme.. Pradhan Mantri Awas Yojana - Urban (PMAY-U) Scheme was launched on 25th June 2015 by the Hon’ble Prime Minister to provide all-weather pucca houses to all eligible urban households across the nation with the vision of ‘Housing for All’.. States/UTsBLC &amp;amp;amp; AHPARHISSAssam, Arunachal Pradesh, Meghalaya, Manipur, Mizoram, Nagaland, Tripura, Sikkim, Himachal Pradesh, Uttarakhand, UTs of Jammu and Kashmir, Puducherry, and DelhiCentral Govt. - ₹2.25 lakh/Unit; State Govt. - Min. ₹0.25 lakh/UnitTechnology Innovation Grant Central Govt. - ₹3,000/sqm per unit State Govt.- ₹2,000/sqm per unit Home Loan Subsidy – up to ₹1.80 lakh (Actual Release) per unit by the Government of India as a Central Sector SchemeAll other UTsCentral Govt. - ₹2.50 lakh/UnitDoDoAll other StatesCentral Govt. - ₹1.5 lakh/Unit; State Govt. - Min. ₹1.00 lakh/UnitDoDo. The family identifies as one of the following - a) Economically Weaker Section (EWS): households with annual income up to ₹3,00,000. b) Low Income Group (LIG): households with annual income between ₹3,00,001 and ₹6,00,000. c) Middle Income Group-1 (MIG-1): households with annual income between ₹6,00,001 and ₹12,00,000. d) Middle Income Group-2 (MIG-2): households with | H29: 0 | J29: =INT((ROW()-2)/50)+1 -> 1 | K29: =IF(H29="","Pending",IF(OR(H29="0",H29="1",H29="2",H29="U"),"Complete","Invalid")) -> Complete
A30: v2q-003-candidate-20 | B30: v2q-003 | C30: What revised overdraft limit and RuPay accidental-insurance cover are stated for PMJDY? | D30: PMJDY states a revised overdraft limit of ₹10,000 and accidental-insurance cover of ₹2 lakh for RuPay cardholders. | E30: pilot-v2-doc-ab-pmjay-0002-58c80bb24a6c | F30: Ayushman Bharat - Pradhan Mantri Jan Arogya Yojana | G30: deriving a major part of their income from manual casual labour Automatically includedHouseholds without shelter Destitute/ living on alms, Manual scavenger families, Primitive tribal groups, Legally released bonded labour. Urban Beneficiaries For urban areas, the following 11 occupational categories of workers are eligible for the scheme: Ragpicker Beggar Domestic worker Street vendor/ Cobbler/hawker / other service provider working on streets Construction worker/ Plumber/ Mason/ Labour/ Painter/ Welder/ Security guard/ Coolie and other head-load worker Sweeper/ Sanitation worker/ Mali Home-based worker/ Artisan/ Handicrafts worker/ Tailor Transport worker/ Driver/ Conductor/ Helper to drivers and conductors/ Cart puller/ Rickshaw puller Shop worker/ Assistant/ Peon in small establishment/ Helper/Delivery assistant / Attendant/ Waiter Electrician/ Mechanic/ Assembler/ Repair worker Washer-man/ Chowkidar. Those who own a two, three, or four-wheeler or a motorized fishing boat. Those who own mechanized farming equipment. Those who have Kisan cards with a credit limit of ₹50,000/-. Those employed by the government. Those who work in government-managed non-agricultural enterprises. Those earning a monthly income above ₹10,000/-. Those owning refrigerators and landlines. Those with decent, solidly built houses. Those owning 5 acres or more of agricultural land.. The Arogya Mitra searches the available list of beneficiaries using details such as name, location, ration card number, mobile number, or the RSBY URN of the beneficiary. After this, the beneficiary is searched for in the BIS. The individual is identified and the scanned valid ID documents are then uploaded. To get a PMJAY e-card for themselves and their family, a potential beneficiary needs to visit either a hospital or a Community Service Centre (CSC) for identification and follow the steps mentioned below: Step 1: Potential AB-PMJAY beneficiaries are to submit the PM letter/ RSBY URN/ RC Number/ Mobile Number - The operator (commonly known as the Arogya Mitra) searches the available list of beneficiaries. | H30: 0 | J30: =INT((ROW()-2)/50)+1 -> 1 | K30: =IF(H30="","Pending",IF(OR(H30="0",H30="1",H30="2",H30="U"),"Complete","Invalid")) -> Complete
A31: v2q-028-candidate-01 | B31: v2q-028 | C31: What does PMKVY Recognition of Prior Learning certify, and which other pathway from its ministry serves candidates seeking fresh short-term skills training? | D31: PMKVY Recognition of Prior Learning certifies candidates’ existing skills. PMKVY Short-Term Training, under the same Ministry of Skill Development and Entrepreneurship, provides fresh skilling, reskilling, or upskilling. | E31: pilot-v2-doc-pmkvy-sp-0002-dc58b95bab9b | F31: Pradhan Mantri Kaushal Vikas Yojana 4.0- Special Projects | G31: Special Areas, and may also be extended for training in Aspirational, Border, Tribal-dominated, and LWE-affected districts. Special Projects may also be taken up with fully residential training.1. Conveyance / Transportation Cost: Permissible for Women and Persons with Disability (PwD) in case of non-residential training, as per Common Norms.1. Additional Support to Persons with Disability (PwD) Candidates: ₹5,000 towards assistive devices, aids, and appliances.1. Accidental Insurance: Every certified candidate is provided with 1-year accidental insurance, as per prevailing rates (₹14.16).1. Aadhaar Enabled Biometric Attendance System (AEBAS) Transaction Fees: Up to ₹10 per user, borne under the scheme.1. Post-Certification Tracking Support: Information Technology (IT)-based tracking for up to 1 year from the date of certification, with an allowance of up to ₹50 per certified candidate.1. Certification: A Quick Response (QR) code-based digital certificate is issued (on DigiLocker, on email/phone number, and on the Skill India Digital profile), and one printed certificate is provided free of cost by the Training Provider.1. Post-Certification Linkages: Certified candidates are linked with Rojgar Melas (including virtual) and Apprenticeship Melas and gain access to jobs, apprenticeship opportunities, and loans for entrepreneurship through Skill India Digital.. The applicant should be of Indian nationality. The applicant should possess a valid Aadhaar. The applicant should fulfil the eligibility criteria of the respective job role. The applicant should be in the age group of 15 to 45 years. The applicant should belong to a marginalised or vulnerable group, or another group requiring special attention, or should be undertaking job roles with a focus on future skills.. The applicant should not be enrolled again in the same job role in which he/she was trained earlier. The applicant, if already certified once under PMKVY, will be discouraged from opting for a lower National Skills Qualification Framework (NSQF) level course in the same sector; however, | H31: 1 | J31: =INT((ROW()-2)/50)+1 -> 1 | K31: =IF(H31="","Pending",IF(OR(H31="0",H31="1",H31="2",H31="U"),"Complete","Invalid")) -> Complete
A32: v2q-023-candidate-24 | B32: v2q-023 | C32: What role does a Gram Panchayat play when a household registers for MGNREGA? | D32: A household may apply through its local Gram Panchayat, which verifies residence, household identity, and adult membership details. | E32: pilot-v2-doc-pm-gkay-0001-ccd31e120258 | F32: Pradhan Mantri Garib Kalyan Anna Yojana | G32: scheme aims to ensure food security for the poor. Through this scheme, free foodgrains are provided to eligible ration card holders under the National Food Security Act, 2013.. Antyodaya Anna Yojana (AAY) families receive 35 kilograms of foodgrains per family per month. Priority Household (PHH) beneficiaries receive 5 kilograms of foodgrains per person per month. The foodgrains are provided as rice or wheat, depending on the state, with fortified rice distributed nationwide. Since January 2023, the foodgrains have been provided completely free of cost (at zero cost) to the beneficiaries. Through One Nation One Ration Card, beneficiaries can collect their ration from any fair price shop anywhere in India.. The applicant should be a household belonging to the Antyodaya Anna Yojana (AAY) category or the Priority Households (PHH) category. Priority Households (PHH) are to be identified by the state governments/union territory administrations as per the criteria evolved by them. Antyodaya Anna Yojana (AAY) families are to be identified by the States / Union Territories as per the criteria prescribed by the Central Government, as listed below. Criteria for Antyodaya Anna Yojana (AAY) Families: The applicant should be a household headed by a widow, a terminally ill person, a disabled person, or a person aged 60 years or more, with no assured means of subsistence or societal support. The applicant should be a widow, a terminally ill person, a disabled person, a person aged 60 years or more, a single woman, or a single man, with no family or societal support, and with no assured means of subsistence. The applicant should belong to a primitive tribal household. The applicant should be a landless agricultural laborer, a marginal farmer, or a rural artisan or craftsman (such as a potter, tanner, weaver, blacksmith, or carpenter); a slum dweller; or a person earning a | H32: 0 | J32: =INT((ROW()-2)/50)+1 -> 1 | K32: =IF(H32="","Pending",IF(OR(H32="0",H32="1",H32="2",H32="U"),"Complete","Invalid")) -> Complete
A33: v2q-004-candidate-01 | B33: v2q-004 | C33: What is the maximum micro-loan amount stated for PMMY? | D33: PMMY facilitates micro-credit loans up to ₹20 lakh for eligible income-generating micro-enterprises. | E33: pilot-v2-doc-pmay-g-0001-db2db8af1543 | F33: Pradhan Mantri Awaas Yojana - Gramin | G33: years from 2016-17 to 2018-19 and enable construction of quality houses by the beneficiaries using local materials, designs and trained masons. For houses to become homes, adoption of a habitat approach through convergence is proposed.. Launch on 1st April 2016, Pradhan Mantri Awaas Yojana Gramin (PMAY-G) is centre's flagship mission by the Ministry of Rural Development (MoRD), implemented by the Ministry of Housing and Urban Affairs (MoHUA). PMAY-G addresses the rural housing shortage and bridges the housing deficit in rural areas. Financial Assistance of ₹ 1,20,000 per unit for plain areas; and ₹ 1,30,000 per unit for hilly areas, difficult areas, and IAP districts (Himalayan states, North-Eastern states, and Union Territories of Jammu & Kashmir). A willing beneficiary can avail of institutional finance (loan) of up to ₹ 70,000 at 3% lower interest rate, to build a permanent house. The maximum principal amount for which subsidy can be sought is ₹ 2,00,000. The minimum size of the house shall be is 25 sq m including a dedicated area for hygienic cooking. In convergence with Swachh Bharat Mission-Gramin (SBM-G), the beneficiaries get financial assistance of up to ₹ 12,000 for the construction of toilets. In convergence with MGNREGA, the beneficiary is entitled to employment as unskilled labor (Rural Mason Training) at ₹ 90.95 per day for 95 days. In convergence with Pradhan Mantri Ujjwala Yojana, one LPG connection per house is provided. Convergence with different government programmes for piped drinking water, electricity connection, clean & efficient cooking fuel, treatment of social and liquid waste, etc. Payments are made electronically directly to bank accounts or post office accounts that are linked to Aadhaar. Note: Beneficiaries are identified using the "Housing Deprivation Parameters" from the Socio-Economic and Caste Census (SECC) 2011, further verified by the Gram Sabhas.. The universe of eligible beneficiaries under | H33: 0 | J33: =INT((ROW()-2)/50)+1 -> 1 | K33: =IF(H33="","Pending",IF(OR(H33="0",H33="1",H33="2",H33="U"),"Complete","Invalid")) -> Complete
A34: v2q-019-candidate-11 | B34: v2q-019 | C34: What role does the Ministry of Petroleum and Natural Gas have in Ujjwala 2.0? | D34: The ministry introduced Ujjwala 2.0 to provide LPG connections and promote clean cooking fuel among poor, rural, and deprived households. | E34: pilot-v2-doc-pmay-g-0001-db2db8af1543 | F34: Pradhan Mantri Awaas Yojana - Gramin | G34: years from 2016-17 to 2018-19 and enable construction of quality houses by the beneficiaries using local materials, designs and trained masons. For houses to become homes, adoption of a habitat approach through convergence is proposed.. Launch on 1st April 2016, Pradhan Mantri Awaas Yojana Gramin (PMAY-G) is centre's flagship mission by the Ministry of Rural Development (MoRD), implemented by the Ministry of Housing and Urban Affairs (MoHUA). PMAY-G addresses the rural housing shortage and bridges the housing deficit in rural areas. Financial Assistance of ₹ 1,20,000 per unit for plain areas; and ₹ 1,30,000 per unit for hilly areas, difficult areas, and IAP districts (Himalayan states, North-Eastern states, and Union Territories of Jammu & Kashmir). A willing beneficiary can avail of institutional finance (loan) of up to ₹ 70,000 at 3% lower interest rate, to build a permanent house. The maximum principal amount for which subsidy can be sought is ₹ 2,00,000. The minimum size of the house shall be is 25 sq m including a dedicated area for hygienic cooking. In convergence with Swachh Bharat Mission-Gramin (SBM-G), the beneficiaries get financial assistance of up to ₹ 12,000 for the construction of toilets. In convergence with MGNREGA, the beneficiary is entitled to employment as unskilled labor (Rural Mason Training) at ₹ 90.95 per day for 95 days. In convergence with Pradhan Mantri Ujjwala Yojana, one LPG connection per house is provided. Convergence with different government programmes for piped drinking water, electricity connection, clean & efficient cooking fuel, treatment of social and liquid waste, etc. Payments are made electronically directly to bank accounts or post office accounts that are linked to Aadhaar. Note: Beneficiaries are identified using the "Housing Deprivation Parameters" from the Socio-Economic and Caste Census (SECC) 2011, further verified by the Gram Sabhas.. The universe of eligible beneficiaries under | H34: 0 | J34: =INT((ROW()-2)/50)+1 -> 1 | K34: =IF(H34="","Pending",IF(OR(H34="0",H34="1",H34="2",H34="U"),"Complete","Invalid")) -> Complete
A35: v2q-029-candidate-04 | B35: v2q-029 | C35: What migrant-focused facility distinguishes Ujjwala 2.0, and what clean-cooking transition was established by its predecessor programme? | D35: Ujjwala 2.0 added 1.6 crore LPG connections with a special facility for migrant households. Its predecessor, Pradhan Mantri Ujjwala Yojana, sought to replace traditional cooking fuels with LPG access for rural and deprived households. | E35: pilot-v2-doc-pmay-g-0002-e08c1e347071 | F35: Pradhan Mantri Awaas Yojana - Gramin | G35: electricity connection, clean & efficient cooking fuel, treatment of social and liquid waste, etc. Payments are made electronically directly to bank accounts or post office accounts that are linked to Aadhaar. Note: Beneficiaries are identified using the "Housing Deprivation Parameters" from the Socio-Economic and Caste Census (SECC) 2011, further verified by the Gram Sabhas.. The universe of eligible beneficiaries under PMAY-G will include all the houseless households living in zero, one, or two-room houses with kutcha walls and kutcha roofs (as per SECC data, and subject to the exclusion process). Criteria for Automatic/Compulsory Inclusion - 1. Households without shelter 2. Destitute/ living on alms 3. Manual scavengers 4. Primitive Tribal Groups 5. Legally released bonded laborer Prioritisation within the Universe i. There will be multilayered prioritization within the universe of eligible PMAY-G beneficiaries. Priority will first be assigned on the basis of parameters reflecting housing deprivation in each category viz., SC/ST, Minorities, and Others. ii. To begin with, households will be prioritized based on houselessness followed by the number of rooms; zero, one, and two rooms, in that order. iii. In a particular social category viz., SC/ST, Minorities, and Others, households that are houseless or living in houses with a lower number of rooms shall not be ranked below households living in houses with a higher number of rooms. Within the above priority groups, households that fulfill the criteria of "compulsory inclusion", will be further elevated. Automatically included households shall not rank lower than other households within a priority group. Inter-se priority within the two subgroups viz. households which are automatically included and otherwise will be determined based on their cumulative deprivation scores. The scores will be calculated from the socio-economic parameters given below with each having equal weight: i. Households with no adult member between ages 16 to 59 | H35: 0 | J35: =INT((ROW()-2)/50)+1 -> 1 | K35: =IF(H35="","Pending",IF(OR(H35="0",H35="1",H35="2",H35="U"),"Complete","Invalid")) -> Complete
A36: v2q-026-candidate-21 | B36: v2q-026 | C36: What employment guarantee does MGNREGA provide, and which other programme from its ministry supplies pucca houses to rural households? | D36: MGNREGA guarantees at least 100 days of wage employment to qualifying rural households. PMAY-G, under the same Ministry of Rural Development, supports pucca houses with basic amenities for eligible rural households. | E36: pilot-v2-doc-pmay-g-0004-f8ee90715c3f | F36: Pradhan Mantri Awaas Yojana - Gramin | G36: such. In case all eligible SC and ST households are covered, the State/ UT targets would be allocated to beneficiaries from the 'Other' categories included in the Permanent Wait List drawn from SECC 2011. For Minorities: Further, as far as possible, 15% of the total fund would be earmarked for Minorities at the National Level for households. The allocation of targets for Minorities among the States/UTs will be on the basis of the proportionate rural population of Minorities in the respective State/UT as per Census 2011 data. Minorities notified under Section 2(c) of the National Commission for Minorities Act, 1992 are to be considered eligible for receiving benefits against Minority earmarks. For PwDs: Accordingly, in the scheme of PMAY-G, while deciding the inter-se priority among the beneficiaries who are to be provided assistance, households with any disabled member and no able-bodied adult member have been accorded additional deprivation score so that such households are given priority while allotting the houses. Keeping in view the provisions of the Persons with Disabilities Act, of 1995, the States to the extent possible, may ensure that 3% of beneficiaries at the State Level are from among persons with disabilities. Tie Breaker In case there is a tie with more than one household within a subgroup having the same deprivation score, the households will be ranked according to priority on the basis of the following parameters: i. Households with widows and next-of-kin of members of defence/paramilitary/police forces killed in action. ii. Households where a member is suffering from leprosy or cancer and People living with HIV (PLHIV). iii. Households with a single girl child. iv. Beneficiary families of the Scheduled Tribes and Other Traditional Forest Dwellers (Recognition of Forest Rights) Act, 2006, commonly known as the Forest Rights Act. v. Transgender persons.. Step 1: Exclusion | H36: 1 | J36: =INT((ROW()-2)/50)+1 -> 1 | K36: =IF(H36="","Pending",IF(OR(H36="0",H36="1",H36="2",H36="U"),"Complete","Invalid")) -> Complete
A37: v2q-034-candidate-04 | B37: v2q-034 | C37: How do three programmes meet distinct household needs for rural housing, clean cooking, and food security? | D37: PMAY-G supports pucca rural housing with basic amenities; PMUY provides LPG access to deprived households replacing traditional cooking fuels; PMGKAY provides free foodgrains to eligible AAY and PHH ration-card holders. | E37: pilot-v2-doc-mgnrega-0001-5203a455caa6 | F37: Mahatma Gandhi National Rural Employment Guarantee Act | G37: entitled to a travel and subsistence allowance (10% of the minimum wage). Wages are paid within a week, or fifteen days at most. Men and Women are paid equally. Shade, drinking water, and first-aid are provided at every worksite. Exclusive measures for the promotion of the participation of the disabled persons: Identification of suitable works Mobilization of disabled persons by focussing on awareness and special provisions Specifically identified works for disabled persons in the case of large GPs Preference to appoint as mates and as workers for providing drinking water, to manage crèches, etc., at the worksites Adoption of tools and equipment/facilities at workplaces Treating persons with disabilities with respect Special drive to ensure 100 days of employment to such households Provide a special job card of a distinct color Specific attention and provisions for Senior Citizens: Exclusive senior citizen groups may be formed and special works which require lesser physical effort are identified and allotted to these groups. Specific attention and provisions for Internally Displaced Persons: A special job card to be provided will be valid till these families are displaced and will lose its validity as soon as they return to their original place of residence.. The applicant must be at least 18 years of age. The applicant must be residing in a Rural Area.. NA. Step 1: The application for registration may be given on plain paper to the local Gram Panchayat. An individual may appear personally before the Panchayat Secretary or Gram Rozgar Sahayak and make an oral request for registration, in which case the particulars required will be noted by the Gram Rojgar Sahayak or the Panchayat Secretary. Application for registration should contain names of those adult members of the household who are willing to do unskilled manual work. Particulars such as age, sex, SC/ST | H37: 0 | J37: =INT((ROW()-2)/50)+1 -> 1 | K37: =IF(H37="","Pending",IF(OR(H37="0",H37="1",H37="2",H37="U"),"Complete","Invalid")) -> Complete
A38: v2q-023-candidate-18 | B38: v2q-023 | C38: What role does a Gram Panchayat play when a household registers for MGNREGA? | D38: A household may apply through its local Gram Panchayat, which verifies residence, household identity, and adult membership details. | E38: pilot-v2-doc-ab-pmjay-0003-1242266bb260 | F38: Ayushman Bharat - Pradhan Mantri Jan Arogya Yojana | G38: for themselves and their family, a potential beneficiary needs to visit either a hospital or a Community Service Centre (CSC) for identification and follow the steps mentioned below: Step 1: Potential AB-PMJAY beneficiaries are to submit the PM letter/ RSBY URN/ RC Number/ Mobile Number - The operator (commonly known as the Arogya Mitra) searches the available list of beneficiaries. The operator does this by entering details such as name, location, Ration Card number, mobile number, or even RSBY URN of the beneficiary. Step 2: Search in the BIS Application - The operator searches for the potential beneficiary in the entitled SECC, RSBY, State Health Scheme, Additional Data Collection Drive databases. Step 3: Individual Identification - The identification process is carried out if the name is found in the list. For this, documents like Aadhaar or any government ID and a Ration Card or an alternative family ID are required to validate against the details available in the system. Scanned documents are then uploaded. Step 4: Family Identification - The Arogya Mitra then identifies the family records through the ration card and the scanned documents are then uploaded. The Arogya Mitra then submits the individual and family records to the trust/insurance company for approval. Step 5: Approval or Rejection - The Health insurance company or trust may then approve or recommend rejection for the submitted beneficiaries. The cases that are recommended for rejection will be finally verified for approval or rejection by the State Health Agency (SHA). Step 6: E-card Issuance - On approval by SHA/insurance company/trust, an e-card will be issued to the beneficiary.. Step 1: Register on the UMANG Portal Visit the official website of UMANG. In the top right corner of the landing page, click "Register." You will be taken to the Registration Page. Step 2: Mobile | H38: 0 | J38: =INT((ROW()-2)/50)+1 -> 1 | K38: =IF(H38="","Pending",IF(OR(H38="0",H38="1",H38="2",H38="U"),"Complete","Invalid")) -> Complete
A39: v2q-015-candidate-11 | B39: v2q-015 | C39: Which initiative helps job-seekers and established craftspeople launch small businesses outside agriculture? | D39: The Prime Minister's Employment Generation Programme supports new micro-enterprises to create self-employment for traditional artisans, unemployed youth, and other eligible beneficiaries. | E39: pilot-v2-doc-pm-kisan-guidelines-0011-06191a382507 | F39: PM-KISAN Operational Guidelines | G39: to be identified by the respective State and Union Territory. The details of farmers are being maintained by the States / UTs either in electronic form or in manual register. To make integrated platform available in the country to assist in benefit transfer, a platform named PM-Kisan Portal available at URL (http://pmkisan.gov.in) has been be launched for uploading the farmers’ details at a single web-portal in a uniform structure. 9.2 The PM-Kisan Portal has been created with the following objectives - i) To provide verified and single source of truth on farmers’ details at the portal. ii) Timely assistance to the farmers in farm operation iii) A unified e-platform for transferring of cash benefits into farmer’s bank account through Public Financial Management System (PFMS) integration. iv) Location wise availability of benefited farmers’ list. v) Ease of monitoring across the country on fund transaction details. 9.3 PM-Kisan Portal : The following farmer attributes need to be entered in the Portal: Farmer Attributes: (Essential): State, District, Sub-District/Block, Village, Farmer Name, Type of Identity – Aadhaar Number and in case Aadhaar not available, Aadhaar enrollment number with any other ID proof like Voter ID etc, Gender, Category, IFSC Code, Bank Account Number. Farmer Attributes (Optional): Father name, Address, Mobile Number, Date of Birth/Age, Farm-Size in Hectare, Survey Number, Khasra Number Optional attributes such as Mobile number can be utilized for SMS alerts. Other optional attributes may be used for purpose of future requirement. However, these attributes are not essential for purpose of transfer of money. These attributes are illustrated on PM-KISAN Portal http://pmkisan.gov.in as follows 8 9.4 There are 3 ways through which a State / UT can onboard on the PM Kisan Portal: (a) If a State / UT has village / district wise list of farmers, they may upload the same | H39: 0 | J39: =INT((ROW()-2)/50)+1 -> 1 | K39: =IF(H39="","Pending",IF(OR(H39="0",H39="1",H39="2",H39="U"),"Complete","Invalid")) -> Complete
... A82: v2q-019-candidate-03 | B82: v2q-019 | C82: What role does the Ministry of Petroleum and Natural Gas have in Ujjwala 2.0? | D82: The ministry introduced Ujjwala 2.0 to provide LPG connections and promote clean cooking fuel among poor, rural, and deprived households. | E82: pilot-v2-doc-pmegp-0003-43256e8e6645 | F82: Prime Minister's Employment Generation Programme | G82: sector and above ₹ 5,00,000 in the Business /Service sector, the beneficiaries should possess at least VIII standard pass educational qualification. Assistance under the scheme is available only for new projects sanctioned specifically under the PMEGP. Existing Units (under PMRY, REGP, or any other scheme of the Government of India or State Government) and the units that have already availed of Government Subsidy under any other scheme of the Government of India or State Government are not eligible. For up-gradation of existing PMEGP / REGP / MUDRA units Margin Money(subsidy)claimed under PMEGP has to be successfully adjusted on the completion of the lock-in period of 3 years. The first loan under PMEGP/REGP/MUDRA has to be successfully repaid in the stipulated time. The unit is profit-making with good turnover and has the potential for further growth in turnover and profit with modernization/upgrading of the technology. Reservation / Preference / Priority Priority will be given to the persons affected by natural calamities/disasters in the areas which are declared as affected by "disaster" as defined under Section 2(d) of the Disaster Management Act, 2005 by the Ministry of Home Affairs.. For PMEGP new enterprises (Units): Existing Units (under PMRY, REGP, or any other scheme of the Government of India or State Government) and the units that have already availed of Government Subsidy under any other scheme of the Government of India or State Government are not eligible. Only one person from one family is eligible for obtaining financial assistance for setting up of projects under PMEGP. The 'family’ includes self and spouse. Negative List of Activities: The following list of activities will not be permitted under PMEGP for setting up of micro enterprises/ projects/units:- Any Industry/ Business connected with Meat(slaughtered), i.e., processing, canning and/or serving items made of it as food, production/Manufacturing or | H82: 0 | J82: =INT((ROW()-2)/50)+1 -> 2 | K82: =IF(H82="","Pending",IF(OR(H82="0",H82="1",H82="2",H82="U"),"Complete","Invalid")) -> Complete
A83: v2q-017-candidate-09 | B83: v2q-017 | C83: Which training route serves people no longer in education or work who need an initial occupational skill? | D83: PMKVY 4.0 Short-Term Training provides fresh skilling, reskilling, or upskilling for groups including school or college dropouts and unemployed youth. | E83: pilot-v2-doc-pmkvy-sp-0002-dc58b95bab9b | F83: Pradhan Mantri Kaushal Vikas Yojana 4.0- Special Projects | G83: Special Areas, and may also be extended for training in Aspirational, Border, Tribal-dominated, and LWE-affected districts. Special Projects may also be taken up with fully residential training.1. Conveyance / Transportation Cost: Permissible for Women and Persons with Disability (PwD) in case of non-residential training, as per Common Norms.1. Additional Support to Persons with Disability (PwD) Candidates: ₹5,000 towards assistive devices, aids, and appliances.1. Accidental Insurance: Every certified candidate is provided with 1-year accidental insurance, as per prevailing rates (₹14.16).1. Aadhaar Enabled Biometric Attendance System (AEBAS) Transaction Fees: Up to ₹10 per user, borne under the scheme.1. Post-Certification Tracking Support: Information Technology (IT)-based tracking for up to 1 year from the date of certification, with an allowance of up to ₹50 per certified candidate.1. Certification: A Quick Response (QR) code-based digital certificate is issued (on DigiLocker, on email/phone number, and on the Skill India Digital profile), and one printed certificate is provided free of cost by the Training Provider.1. Post-Certification Linkages: Certified candidates are linked with Rojgar Melas (including virtual) and Apprenticeship Melas and gain access to jobs, apprenticeship opportunities, and loans for entrepreneurship through Skill India Digital.. The applicant should be of Indian nationality. The applicant should possess a valid Aadhaar. The applicant should fulfil the eligibility criteria of the respective job role. The applicant should be in the age group of 15 to 45 years. The applicant should belong to a marginalised or vulnerable group, or another group requiring special attention, or should be undertaking job roles with a focus on future skills.. The applicant should not be enrolled again in the same job role in which he/she was trained earlier. The applicant, if already certified once under PMKVY, will be discouraged from opting for a lower National Skills Qualification Framework (NSQF) level course in the same sector; however, | H83: 0 | I83: SP sub-scheme chunk for STT question — special-project geographic targeting, not the fresh-skilling STT pathway. | J83: =INT((ROW()-2)/50)+1 -> 2 | K83: =IF(H83="","Pending",IF(OR(H83="0",H83="1",H83="2",H83="U"),"Complete","Invalid")) -> Complete
A84: v2q-009-candidate-17 | B84: v2q-009 | C84: What does APY stand for, and what monthly pension range does it guarantee after age 60? | D84: APY stands for Atal Pension Yojana and offers guaranteed monthly pension options from ₹1,000 to ₹5,000 after age 60. | E84: pilot-v2-doc-pmjdy-0000-8b241ec39723 | F84: Pradhan Mantri Jan Dhan Yojana | G84: Pradhan Mantri Jan Dhan Yojana. Ministry Of Finance. Department of Financial Service. Banks. A National Mission for Financial Inclusion (NMFI), namely, Pradhan Mantri Jan Dhan Yojana (PMJDY) was launched across the Country in August, 2014 by the Prime Minister with the idea to ensure that citizens envisage their financial activities. PMJDY provides universal banking services for every unbanked household, based on the guiding principles of banking the unbanked, securing the unsecured, funding the unfunded and serving unserved and underserved areas. In order to give impetus to financial inclusion initiatives of the Government, PMJDY scheme was extended beyond 14.08.2018 with the focus on opening of accounts shifting from “every household” to “every unbanked adult”. The scheme has been made more attractive with upward revision in (i) OD limit from Rs. 5,000/- to Rs. 10,000/- and (ii) Accidental insurance cover on RuPay card holders from Rs.1 lakh to Rs.2 lakhs. PMJDY has been successful in increasing banking penetration and promoting financial inclusion across the country. The scheme has ensured access to various financial services like availability of basic savings bank account, access to need based credit, remittances facility, insurance and pension to the excluded sections i.e. weaker sections &amp; low-income groups.. A National Mission for Financial Inclusion (NMFI), namely, Pradhan Mantri Jan Dhan Yojana (PMJDY) was launched by the Prime Minister across the country on 28th August, 2014. It envisages to provide universal banking services for every unbanked adult in the country.. Basic Savings Bank Deposit Account (BSBDA) Any Indian citizen eligible to open a regular bank account can open a BSBDA. Such an account does not require any minimum balance maintenance. The account holders can use both bank branches, ATMs and Banking Correspondents (BCs) for depositing and withdrawing cash. However, one cannot withdraw cash more than four times a month. Small | H84: 0 | J84: =INT((ROW()-2)/50)+1 -> 2 | K84: =IF(H84="","Pending",IF(OR(H84="0",H84="1",H84="2",H84="U"),"Complete","Invalid")) -> Complete
A85: v2q-009-candidate-07 | B85: v2q-009 | C85: What does APY stand for, and what monthly pension range does it guarantee after age 60? | D85: APY stands for Atal Pension Yojana and offers guaranteed monthly pension options from ₹1,000 to ₹5,000 after age 60. | E85: pilot-v2-doc-pm-kmy-guidelines-0006-2652020c834e | F85: Pradhan Mantri Kisan Maan Dhan Yojana Operational Guidelines | G85: same day every month as enrolment date. The beneficiaries may also chose an option to pay their contributions on quarterly, 4-monthly or half-yearly basis. Such contributions will fall due on the same day of such period as the date of enrollment; 4 (x) The amount of the monthly contribution shall range between Rs.55 to Rs.200 per month depending upon the age of entry of the farmers into the Scheme, as per the following contribution chart: Superannuation Member's Government’s Total contribution Entry Age Age contribution (Rs.) contribution (Rs.) (Rs.) (1) (2) (3) (4) (5) 18 60 55 55 110 19 60 58 58 116 20 60 61 61 122 21 60 64 64 128 22 60 68 68 136 23 60 72 72 144 24 60 76 76 152 25 60 80 80 160 26 60 85 85 170 27 60 90 90 180 28 60 95 95 190 29 60 100 100 200 30 60 105 105 210 31 60 110 110 220 32 60 120 120 240 33 60 130 130 260 34 60 140 140 280 35 60 150 150 300 36 60 160 160 320 37 60 170 170 340 38 60 180 180 360 39 60 190 190 380 40 60 200 200 400 (xi) In case of death of subscriber before vesting date, the spouse of subscriber shall have an option of continuing the scheme by payment of remaining contributions under the scheme, provided she/he is not already an SMF beneficiary of the Scheme. The rate of contribution and vesting date shall remain the same. Pension accruals will be calculated as if subscriber were to be alive on the vesting date. However, the same pension would be payable to the spouse. Upon death of spouse after vesting date, pension corpus would be transferred back to | H85: 0 | J85: =INT((ROW()-2)/50)+1 -> 2 | K85: =IF(H85="","Pending",IF(OR(H85="0",H85="1",H85="2",H85="U"),"Complete","Invalid")) -> Complete
A86: v2q-014-candidate-21 | B86: v2q-014 | C86: Under the national ration programme, what monthly cereal allocation goes to families in the poorest entitlement tier and to each person in the priority tier? | D86: AAY families receive 35 kilograms per family per month, while PHH beneficiaries receive 5 kilograms per person per month. | E86: pilot-v2-doc-mgnrega-0002-bbbce5f319d4 | F86: Mahatma Gandhi National Rural Employment Guarantee Act | G86: before the Panchayat Secretary or Gram Rozgar Sahayak and make an oral request for registration, in which case the particulars required will be noted by the Gram Rojgar Sahayak or the Panchayat Secretary. Application for registration should contain names of those adult members of the household who are willing to do unskilled manual work. Particulars such as age, sex, SC/ST status, Rashtriya Swastha Bima Yojana (RSBY) number, Aadhar number, Below Poverty Line (BPL) status and bank/post office account number (if s/he has opened one) must be provided in the application. Step 2: The Gram Panchayat (GP) will verify the following details: Whether the household is really an entity as stated in the application. Whether the applicant household are local residents in the Gram Panchayat concerned. Whether applicants are adult members of the household. The process of verification shall be completed as early as possible, and in any case not later than a fortnight after the receipt of the application in the Gram Panchayat. Step 3: All particulars of a household found to be eligible after verification, will be entered in the MIS (NREGASoft) by the Panchayat Secretary or the Gram Rojgar Sahayak (GRS) or a person duly authorized by the State Government. Step 4: If a household is found to be eligible for registration, the GP will, within a fortnight of the application, issue a JC to the household. JC should be handed over to one of the members of the applicant household in the presence of a few other residents of the GP. The format of the Job Card is provided in the Annexure-5 of the scheme guidelines. The detailed format for application for registration is provided in Annexure-3 of the scheme guidelines. Registrations shall be opened throughout the year at the Gram Panchayat (GP) office. Application for registration | H86: 0 | J86: =INT((ROW()-2)/50)+1 -> 2 | K86: =IF(H86="","Pending",IF(OR(H86="0",H86="1",H86="2",H86="U"),"Complete","Invalid")) -> Complete
A87: v2q-025-candidate-14 | B87: v2q-025 | C87: What banking function does PMJDY provide, and which other programme from its ministry finances income-generating micro-enterprises? | D87: PMJDY provides universal banking services for unbanked households. PMMY, under the same Ministry of Finance, provides micro-credit for income-generating micro-enterprises. | E87: pilot-v2-doc-apy-0000-c43dd88d7899 | F87: Atal Pension Yojana | G87: Atal Pension Yojana. Ministry Of Finance. Department of Financial Service. Banks. Atal Pension Yojana (APY) is an old age income security scheme for a savings account holder in the age group of 18-40 years who is not an income tax-payee. The scheme helps in addressing the longevity risks among the workers in the unorganized sector and encourages the workers to voluntarily save for their retirement. Focus of APY The scheme is mainly targeted at the poor, the under-privileged and workers in the unorganized sector. APY Subscriber Contribution Chart - https://www.npscra.nsdl.co.in/nsdl/scheme-details/APYSubscribersContributionChart1.pdf Charges and fees and overdue interest under APY: The charges and fees and the overdue interest for non-payment or delayed payment of prescribed contribution amount shall be levied on the subscribers of APY. These charges and their method of application shall be prescribed by PFRDA from time to time, in consultation with the Central Government. Raising Grievance Under APY A subscriber can raise grievance anytime free of cost from anywhere by visiting: www.npscra.nsdl.co.in &gt;&gt;Home &gt;&gt; select: NPS-Lite or through CGMS Subscriber raising the grievance will be allotted a token number against the grievance raised. Subscriber may check the status of the grievance under “Check the status of Grievance / Enquiry already registered”.. Atal Pension Yojana (APY) is an old age income security scheme for a savings account holder in the age group of 18-40 years, who is not an income tax-payee. It helps to address longevity risks among workers in unorganized sector and encourages the workers to voluntarily save for retirement.. Upon exit on attaining 60 years The subscriber shall receive the following three benefits on attaining the age of 60: (i) Guaranteed minimum pension amount: Each subscriber under APY shall receive a guaranteed minimum pension of Rs. 1000/- per month or Rs. 2000/- per month or Rs. 3000/- per | H87: 0 | J87: =INT((ROW()-2)/50)+1 -> 2 | K87: =IF(H87="","Pending",IF(OR(H87="0",H87="1",H87="2",H87="U"),"Complete","Invalid")) -> Complete
A88: v2q-031-candidate-20 | B88: v2q-031 | C88: How do three finance-sector programmes combine basic banking, life insurance, and accident insurance? | D88: PMJDY provides universal banking and access to financial services; PMJJBY supplies life cover for death from any cause; PMSBY supplies accidental-death and disability cover. | E88: pilot-v2-doc-pmsby-0001-8851a01ce006 | F88: Pradhan Mantri Suraksha Bima Yojana | G88: of one eye or loss of use of one hand or foot –subscriber shall get Rs. 1 Lakh.. Individual bank account holders of participating banks aged between 18 years (completed) and 70 years (age nearer birthday) who give their consent to join / enable auto-debit, will be enrolled into the scheme.. Step 01: In order to enrol in PMSBY offline, one can visit the bank branch where one has a savings account or the candidate can visit the official site: https://jansuraksha.gov.in/Forms-PMSBY.aspx to download the form. Step 02: After downloading the application form , candidate can fill in all the details and submit them to the bank along with the required documents. Step 03: Once it is successfully submitted , subscriber will get an Acknowledgement Slip Cum Certificate of Insurance. Contact: State wise tollfree number - https://jansuraksha.gov.in/files/STATEWISETOLLFREE.pdf National Toll Free Number - 1800-180-1111 / 1800-110-001. One can also avail cover under PMSBY online using their bank's Net banking facility. | H88: 1 | J88: =INT((ROW()-2)/50)+1 -> 2 | K88: =IF(H88="","Pending",IF(OR(H88="0",H88="1",H88="2",H88="U"),"Complete","Invalid")) -> Complete
A89: v2q-018-candidate-10 | B89: v2q-018 | C89: Which initiative helps city households across officially defined lower and middle income bands obtain permanent homes? | D89: Pradhan Mantri Awas Yojana–Urban addresses urban housing shortages and supports eligible EWS, LIG, and MIG households, including slum dwellers. | E89: pilot-v2-doc-pmay-u-0001-b64fadc4bf6b | F89: Pradhan Mantri Awas Yojana - Urban | G89: State Govt. - Min. ₹1.00 lakh/UnitDoDo. The family identifies as one of the following - a) Economically Weaker Section (EWS): households with annual income up to ₹3,00,000. b) Low Income Group (LIG): households with annual income between ₹3,00,001 and ₹6,00,000. c) Middle Income Group-1 (MIG-1): households with annual income between ₹6,00,001 and ₹12,00,000. d) Middle Income Group-2 (MIG-2): households with annual income between ₹12,00,001 and ₹18,00,000. The applicant or his/her family members must not own a pucca house in any part of the country. The family must comprise of husband/wife and unmarried children. The town/city in which the family resides must be covered under the scheme. The family MUST NOT have previously availed the benefits of any housing-related schemes set up by the Government of India.. Step 1: Interested beneficiary who wants to own a house under PMAY-U 2.0 can register herself/himself on the PMAY-U 2.0 website, wherein it is required to click on ‘Apply for PMAY-U 2.0’ tab. Step 2: The User is required to read and understand the instructions carefully, her/his eligibility criteria, the option to choose any one vertical out of the four verticals of PMAY-U 2,0 before availing the benefits. Step 3: After proceeding, the User needs to undergo the eligibility check for the scheme. Step 4: Once the Eligibility check is completed, the user shall give consent for Aadhaar authentication. Step 5: User will then be taken to the Beneficiary Survey Form for all verticals. The survey form has different sections. User Manual: Click here.. Step 1: Visit a Common Service Centre (CSC) near you. Step 2: Purchase the application form by paying ₹ 25 (plus GST) at the counter. Step 3: In the form, fill in all the mandatory details, and attach copies of the required documents. The details to be filled include name, | H89: 2 | J89: =INT((ROW()-2)/50)+1 -> 2 | K89: =IF(H89="","Pending",IF(OR(H89="0",H89="1",H89="2",H89="U"),"Complete","Invalid")) -> Complete
A90: v2q-007-candidate-19 | B90: v2q-007 | C90: What is the full form of PMJJBY, and which event does its life insurance cover? | D90: PMJJBY stands for Pradhan Mantri Jeevan Jyoti Bima Yojana and provides life-insurance cover for death due to any reason. | E90: pilot-v2-doc-pm-kmy-guidelines-0020-27037b9fe8a1 | F90: Pradhan Mantri Kisan Maan Dhan Yojana Operational Guidelines | G90: of such Nominee so long as such minority or disability continues. (e) If more than one Nominee is appointed and in such appointment the Subscriber has failed to specify their respective interest, the Nominees so named shall share equally. If any designated Nominee predeceases the Subscriber the interest of such Nominee shall terminate and his/her share shall be payable equally to such of the remaining Nominees as survive the Subscriber unless the Subscriber has made written request otherwise to the LIC in the prescribed form. 13 18. INTERPRETATION OF GUIDELINES: It shall be a condition of the membership of the Scheme that on any question arising on any point of interpretation of these Guidelines or any point relating to cessation of membership, the decision of the DAC&FW shall be final. 19. COORDINATION AMONG VARIOUS PARTICIPATING AGENCIES The DAC&FW has entered into detailed Memorandum of Understanding (MoUs) with various participating agencies for seamless implementation of the Scheme, namely, the LIC, the CSC-SPV, the NPCI, the IDBI and the IBA. These MoUs contained detailed roles and responsibilities of these agencies among themselves as well as towards smooth implementation of the Scheme. Further, the DAC&FW has also taken the key financial institutions / authorities, namely, the Department of Financial Services (DFS) under the Ministry of Finance, the Reserve Bank of India (RBI) and the Insurance Regulatory & Development Authority of India (IRDAI) on-board for successful operation of the Scheme. 20. REVIEW, MONITORING AND GRIEVANCE REDRESSAL MECHANISM a) An Empowered Committee under the Chairmanship of Cabinet Secretary with Secretaries of Agriculture & Farmers’ Welfare, MeiTY, Department of Expenditure, Department of Financial Services and any other Secretary concerned as members shall review and monitor implementation of the Scheme through appropriate implementation strategies and to approve any modifications in the Scheme within the within the overall | H90: 0 | J90: =INT((ROW()-2)/50)+1 -> 2 | K90: =IF(H90="","Pending",IF(OR(H90="0",H90="1",H90="2",H90="U"),"Complete","Invalid")) -> Complete
A91: v2q-014-candidate-15 | B91: v2q-014 | C91: Under the national ration programme, what monthly cereal allocation goes to families in the poorest entitlement tier and to each person in the priority tier? | D91: AAY families receive 35 kilograms per family per month, while PHH beneficiaries receive 5 kilograms per person per month. | E91: pilot-v2-doc-pmay-g-0004-f8ee90715c3f | F91: Pradhan Mantri Awaas Yojana - Gramin | G91: such. In case all eligible SC and ST households are covered, the State/ UT targets would be allocated to beneficiaries from the 'Other' categories included in the Permanent Wait List drawn from SECC 2011. For Minorities: Further, as far as possible, 15% of the total fund would be earmarked for Minorities at the National Level for households. The allocation of targets for Minorities among the States/UTs will be on the basis of the proportionate rural population of Minorities in the respective State/UT as per Census 2011 data. Minorities notified under Section 2(c) of the National Commission for Minorities Act, 1992 are to be considered eligible for receiving benefits against Minority earmarks. For PwDs: Accordingly, in the scheme of PMAY-G, while deciding the inter-se priority among the beneficiaries who are to be provided assistance, households with any disabled member and no able-bodied adult member have been accorded additional deprivation score so that such households are given priority while allotting the houses. Keeping in view the provisions of the Persons with Disabilities Act, of 1995, the States to the extent possible, may ensure that 3% of beneficiaries at the State Level are from among persons with disabilities. Tie Breaker In case there is a tie with more than one household within a subgroup having the same deprivation score, the households will be ranked according to priority on the basis of the following parameters: i. Households with widows and next-of-kin of members of defence/paramilitary/police forces killed in action. ii. Households where a member is suffering from leprosy or cancer and People living with HIV (PLHIV). iii. Households with a single girl child. iv. Beneficiary families of the Scheduled Tribes and Other Traditional Forest Dwellers (Recognition of Forest Rights) Act, 2006, commonly known as the Forest Rights Act. v. Transgender persons.. Step 1: Exclusion | H91: 0 | J91: =INT((ROW()-2)/50)+1 -> 2 | K91: =IF(H91="","Pending",IF(OR(H91="0",H91="1",H91="2",H91="U"),"Complete","Invalid")) -> Complete
A92: v2q-015-candidate-12 | B92: v2q-015 | C92: Which initiative helps job-seekers and established craftspeople launch small businesses outside agriculture? | D92: The Prime Minister's Employment Generation Programme supports new micro-enterprises to create self-employment for traditional artisans, unemployed youth, and other eligible beneficiaries. | E92: pilot-v2-doc-pm-kisan-guidelines-0005-7d487843ff7f | F92: PM-KISAN Operational Guidelines | G92: Subsequent to inheritance if the families of the inheritors also become freshly eligible under PM-Kisan then all the details of the freshly eligible families have to be incorporated in the database so that benefits start accruing to such families from the date when inheritance became operational. 4 iv) In case of transfer of cultivable land for reasons other than death after 01.02.2019, the officials have to reassess the eligibility of the transferor and decide whether the benefits have to be stopped or not and intimate the authorities so that the PM-KISAN portal can be updated. Transferees are not entitled for any benefits under PM-KISAN in such cases. 5.4 The beneficiaries, whose names are uploaded on PM-Kisan Portal by the State / UT Government in a particular 4-month period / trimester, shall be entitled to receive benefit for that trimester and for further installments pertaining to the subsequent trimesters for that financial year. 5.5 In some of the North Eastern States, the land ownership rights are community based and it might not be possible to assess the quantum of land holder farmers. In such States an alternate implementation mechanism for eligibility of the farmers will be developed and approved by the Committee of Union Ministers of Ministry of Development of North East Region (DoNER), the Ministry of Rural Development (Department of Land Resources), the Union Agriculture Minister and the concerned State Chief Ministers or their Ministerial representatives, based on the proposal by the concerned North Eastern States. 5.5.1 For identification of bona fide beneficiary under PM-Kisan Scheme in Manipur, the following proposal of Government of Manipur was considered and approved by the Committee: “The certificate issued by the Village authority, namely, the Chairman/Chief, authorizing any tribal family to cultivate a piece of land, may be accepted. Such certification of village Chairman/Chief | H92: 0 | J92: =INT((ROW()-2)/50)+1 -> 2 | K92: =IF(H92="","Pending",IF(OR(H92="0",H92="1",H92="2",H92="U"),"Complete","Invalid")) -> Complete
A93: v2q-004-candidate-16 | B93: v2q-004 | C93: What is the maximum micro-loan amount stated for PMMY? | D93: PMMY facilitates micro-credit loans up to ₹20 lakh for eligible income-generating micro-enterprises. | E93: pilot-v2-doc-pm-kmy-guidelines-0022-e87f63954812 | F93: Pradhan Mantri Kisan Maan Dhan Yojana Operational Guidelines | G93: the date of dispute. If the Sponsor Bank fails to respond / resolve the dispute within agreed time line, the disputed amount will be debited to the settlement account of the Sponsor Bank maintained with Reserve Bank of India (RBI). f) Any disputes other than that detailed above shall be resolved by LIC, Sponsor Bank and the Ministry without any liability on the other participating stakeholders. The process to be followed for dispute resolution is provided in the MoUs. g) Any matter related to execution, grievance redressal, dispute resolution etc. shall be referred to the Joint Secretary (Farmers Welfare), Department of Agriculture, Cooperation and Farmers Welfare, Ministry of Agriculture & farmers Welfare, Krishi Bhavan, New Delhi – 110001 for redressal. ****** 15 प्रधानमंत्री किसान मानधन योजना (पीएम-िेएमवाई) प्रचालन संबंधी दिशाननिेश 1. स्िनम सरकार ने देश के सभी भूधारक लघु और सीमाांत ककसानों के ललए "प्रधानमांत्री ककसान मान-धन योजना (पीएम-केएमवाई)", नामक वृद्धावस्था पेंशन योजना शुरू की है जो एक स्वैच्छिक और अांशदायी पेंशन स्कीम है और इसमें शालमल होने की आयु 18 से 40 वर्ष है। यह स्कीम 9 अगस्त, 2019 से प्रभावी है। 2. उद्िेश्य और लाभ सरकार की ओर से ककसानों के ललए आय और मूल्य समथषन के ललए कई योजनाएां चलाई गई हैं। तथापप, ककसानों के ललए एक सामाच्जक सुरक्षा कवच सृच्जत करने की जरूरत महसूस की गई है क्योंकक वृद्धावस्था में अधधकाांश ककसानों की आजीपवका के साधन नह रह जाते। खेती- बाडी के ललए खेतों में कडी मेहनत करनी होती है जो उनकी उम्र की इस अवस्था में कन न होता है। यह समस्या लघु और सीमाांत ककसानों के ललए और भी बडी होती है क्योंकक उनके पास बुढापे में बेहद मामूल या शून्य बचत होती है। प्रधानमांत्री ककसान मान धन योजना (पीएम-केएमवाई) के अांतगषत सभी भूधारक लघु और सीमाांत ककसानों पुरूर् और स्त्री दोनों के ललए | H93: 0 | J93: =INT((ROW()-2)/50)+1 -> 2 | K93: =IF(H93="","Pending",IF(OR(H93="0",H93="1",H93="2",H93="U"),"Complete","Invalid")) -> Complete
A94: v2q-013-candidate-15 | B94: v2q-013 | C94: Which initiative helps women in low-income countryside homes replace smoke-producing solid cooking materials with bottled gas? | D94: Pradhan Mantri Ujjwala Yojana provides LPG access to rural and deprived households that previously relied on traditional cooking fuels. | E94: pilot-v2-doc-ab-pmjay-0001-a632a7205efc | F94: Ayushman Bharat - Pradhan Mantri Jan Arogya Yojana | G94: per family per year for secondary and tertiary hospitalization to poor and vulnerable families.. AB PM-JAY is a health insurance scheme for low-income families in rural and urban areas. The scheme aims to provide affordable healthcare facilities to the Poor. It is the largest health assurance scheme in the world which aims at providing a health cover of ₹5,00,000/- per family per year.. Financial Health Insurance Cover: Annual Hospitalization Coverage: Cashless coverage up to ₹5,00,000/- per family per year.- Comprehensive Treatment Costs: Covers consultation, medicines, diagnostics, surgery, ICU, implants, accommodation, and food.- Pre and Post Hospitalization Support: Covers 3 days pre-hospitalization and 15 days post-hospitalization expenses.- Treatment Complication Coverage: Covers complications arising during treatment. Coverage Features: Pre-Existing Disease Coverage: Covers all pre-existing diseases from day one.- No Family Size Limit: No restriction on age, gender, or family size.- Nationwide Portability: Benefits available across India in empanelled hospitals.- Wide Procedure Coverage: Covers approximately 1,929 medical procedures.. Rural Beneficiaries Out of the total seven deprivation criteria for rural areas, PM-JAY covered all such families who fall into at least one of the following six deprivation criteria and automatic inclusion(Destitute/ living on alms, manual scavenger households, primitive tribal group, legally released bonded labour) criteria: Only one room with kucha walls and kucha roof No adult member between ages 16 to 59 Households with no adult male member between ages 16 to 59 Disabled member and no able-bodied adult member SC/ST households Landless households deriving a major part of their income from manual casual labour Automatically includedHouseholds without shelter Destitute/ living on alms, Manual scavenger families, Primitive tribal groups, Legally released bonded labour. Urban Beneficiaries For urban areas, the following 11 occupational categories of workers are eligible for the scheme: Ragpicker Beggar Domestic worker Street vendor/ Cobbler/hawker / other service provider working on streets | H94: 0 | J94: =INT((ROW()-2)/50)+1 -> 2 | K94: =IF(H94="","Pending",IF(OR(H94="0",H94="1",H94="2",H94="U"),"Complete","Invalid")) -> Complete
A95: v2q-002-candidate-23 | B95: v2q-002 | C95: What maximum premium rates can farmers pay under PMFBY for Kharif, Rabi, and annual commercial or horticultural crops? | D95: Farmers pay at most 2% for Kharif food and oilseed crops, 1.5% for Rabi food and oilseed crops, and 5% for annual commercial or horticultural crops. | E95: pilot-v2-doc-apy-0003-68e7199c9d14 | F95: Atal Pension Yojana | G95: can also open an APY account online using one's Net banking facility. The applicant can login into his/her internet banking account and search for APY on dashboard. Customer has to fill basic and Nominee details. Customer has to give consent for auto debit of premium from the account and submit the form. Process 2: Visit website “https://enps.nsdl.com/eNPS/NationalPensionSystem.html “ and select “Atal Pension Yojana”. Select “APY Registration” Fill the basic details in the form. One can complete KYC through 3 options – Offline KYC – Where one has to upload XML file of Aadhaar Aadhaar – Where KYC is done through OTP verification on Mobile Number register with Aadhaar Virtual ID – Where Aadhaar virtual ID is created for KYC Citizen can select either one of three options. Once the basic details are filled, an acknowledgement number is generated. Citizen then has to fill personal details and decide the pension amount he/she wants after 60 years. The Citizen also has to decide the frequency of contribution for the scheme. Once the citizen “confirms” for personal details, he/she has to then fill nominee details. After submitting the personal and Nominee details, Citizen is redirected to NSDL website for eSign. Once Aadhaar is OTP verified, Citizen gets successfully registered in APY. One can also join digitally through e-APY portal or through web portal of banks providing such facility. Visit website “https://enps.nsdl.com/eNPS/NationalPensionSystem.html “ and select “Atal Pension Yojana”. Helpline Number - - Toll Free Helpline number for APY Scheme is 1800-110-069. One can visit the nearest Bank branch or Post Office where he/ she is having a saving bank account and submit the APY registration form for opening the APY account. | H95: 0 | J95: =INT((ROW()-2)/50)+1 -> 2 | K95: =IF(H95="","Pending",IF(OR(H95="0",H95="1",H95="2",H95="U"),"Complete","Invalid")) -> Complete
... A97: v2q-023-candidate-07 | B97: v2q-023 | C97: What role does a Gram Panchayat play when a household registers for MGNREGA? | D97: A household may apply through its local Gram Panchayat, which verifies residence, household identity, and adult membership details. | E97: pilot-v2-doc-pm-svanidhi-0000-f6024bb09ca5 | F97: PM Street Vendor’s AtmaNirbhar Nidhi (PM SVANidhi) | G97: PM Street Vendor’s AtmaNirbhar Nidhi (PM SVANidhi). Ministry Of Housing & Urban Affairs. Urban Local Bodies (ULBs) And Town Vending Committees (TVCs). The scheme &quot;PM Street Vendor’s AtmaNirbhar Nidhi (PM SVANidhi)&quot; by the Ministry of Housing and Urban Affairs, Government of India aims to formalize street vendors and enhance their economic opportunities through providing collateral-free working capital loans, interest subsidy, and digital transaction incentives to street vendors. It was launched on 1st June 2020 as a central sector scheme. The scheme supports vendors in restarting and expanding their businesses. It also promotes digital payments to increase financial inclusion. Street vendors include hawkers, thelewala, rehriwala, and others engaged in small-scale vending activities. The scheme aims to formalize the street vendors and open up new opportunities for this sector to move up the economic ladder. Street vendors represent a very important constituent of the urban informal economy and play a significant role in ensuring availability of the goods and services at affordable rates at the doorstep of the city dwellers. They are known as vendors, hawkers, thelewala, rehriwala, theliphadwala, etc. in different areas/ contexts. The goods supplied by them include vegetables, fruits, ready-to-eat street food, tea, pakodas, bread, eggs, textile, apparel, footwear, artisan products, books/ stationary, etc. The services include barber shops, cobblers, pan shops, laundry services, etc.. PM SVANidhi is a micro-credit scheme launched on 1st June 2020 by the MoHUA to provide handholding support to street vendors. The scheme facilitates a working capital collateral-free loan of ₹10,000, with subsequent loans of ₹20,000 and ₹50,000 with a 7% interest subsidy.. Working Capital Loan: 1st Tranche: Loan up to ₹15,000/-; repayment within 12 months. - 2nd Tranche: Loan up to ₹25,000/-; repayment within 18 months. - 3rd Tranche: Loan up to ₹50,000/-; repayment within 36 months. - Next tranche available on timely | H97: 0 | J97: =INT((ROW()-2)/50)+1 -> 2 | K97: =IF(H97="","Pending",IF(OR(H97="0",H97="1",H97="2",H97="U"),"Complete","Invalid")) -> Complete
A98: v2q-016-candidate-03 | B98: v2q-016 | C98: How can an experienced worker obtain formal recognition for skills learned outside a training course? | D98: PMKVY 4.0 Recognition of Prior Learning assesses, upskills, and certifies candidates who already possess relevant skills or prior-learning experience. | E98: pilot-v2-doc-pmkvy-sp-0004-57e566374b9c | F98: Pradhan Mantri Kaushal Vikas Yojana 4.0- Special Projects | G98: 6: The applicant selects the nearest Training Centre based on the availability of the preferred job role and the quality of training infrastructure (rating, centre profile), or is mapped automatically through logic-based mapping to the nearest Training Centre. Stage 7: On selection and enrolment, the applicant undergoes training, followed by On-the-Job Training (OJT) in applicable job roles. Stage 8: The applicant appears for assessment by an NCVET-approved Awarding Body / Assessment Agency after completion of On-the-Job Training, requiring more than 70% biometric attendance to be eligible. Stage 9: On successful completion, the applicant is awarded a Quick Response (QR) code-based digital certificate, issued via DigiLocker, an email/phone download link, and the Skill India Digital profile page, along with one printed certificate provided free of cost by the Training Provider. | H98: 0 | I98: STT/SP sub-scheme chunk for RPL question — different pathway, does not help answer how experienced workers get prior-learning recognition. | J98: =INT((ROW()-2)/50)+1 -> 2 | K98: =IF(H98="","Pending",IF(OR(H98="0",H98="1",H98="2",H98="U"),"Complete","Invalid")) -> Complete
A99: v2q-023-candidate-19 | B99: v2q-023 | C99: What role does a Gram Panchayat play when a household registers for MGNREGA? | D99: A household may apply through its local Gram Panchayat, which verifies residence, household identity, and adult membership details. | E99: pilot-v2-doc-pmay-g-0002-e08c1e347071 | F99: Pradhan Mantri Awaas Yojana - Gramin | G99: electricity connection, clean & efficient cooking fuel, treatment of social and liquid waste, etc. Payments are made electronically directly to bank accounts or post office accounts that are linked to Aadhaar. Note: Beneficiaries are identified using the "Housing Deprivation Parameters" from the Socio-Economic and Caste Census (SECC) 2011, further verified by the Gram Sabhas.. The universe of eligible beneficiaries under PMAY-G will include all the houseless households living in zero, one, or two-room houses with kutcha walls and kutcha roofs (as per SECC data, and subject to the exclusion process). Criteria for Automatic/Compulsory Inclusion - 1. Households without shelter 2. Destitute/ living on alms 3. Manual scavengers 4. Primitive Tribal Groups 5. Legally released bonded laborer Prioritisation within the Universe i. There will be multilayered prioritization within the universe of eligible PMAY-G beneficiaries. Priority will first be assigned on the basis of parameters reflecting housing deprivation in each category viz., SC/ST, Minorities, and Others. ii. To begin with, households will be prioritized based on houselessness followed by the number of rooms; zero, one, and two rooms, in that order. iii. In a particular social category viz., SC/ST, Minorities, and Others, households that are houseless or living in houses with a lower number of rooms shall not be ranked below households living in houses with a higher number of rooms. Within the above priority groups, households that fulfill the criteria of "compulsory inclusion", will be further elevated. Automatically included households shall not rank lower than other households within a priority group. Inter-se priority within the two subgroups viz. households which are automatically included and otherwise will be determined based on their cumulative deprivation scores. The scores will be calculated from the socio-economic parameters given below with each having equal weight: i. Households with no adult member between ages 16 to 59 | H99: 0 | J99: =INT((ROW()-2)/50)+1 -> 2 | K99: =IF(H99="","Pending",IF(OR(H99="0",H99="1",H99="2",H99="U"),"Complete","Invalid")) -> Complete
A100: v2q-022-candidate-18 | B100: v2q-022 | C100: Which finance programme relies on Member Lending Institutions to extend assistance to non-corporate micro-enterprises? | D100: Eligible Member Lending Institutions extend PMMY financial assistance and provide the scheme’s micro-loans to qualifying micro and small enterprises. | E100: pilot-v2-doc-pm-gkay-0000-c29b96f46a80 | F100: Pradhan Mantri Garib Kalyan Anna Yojana | G100: Pradhan Mantri Garib Kalyan Anna Yojana. Ministry Of Finance. Department Of Economic Affairs. The scheme "Pradhan Mantri Garib Kalyan Anna Yojana (PMGKAY)" has been launched by the Department of Food and Public Distribution, Ministry of Consumer Affairs, Food and Public Distribution, Government of India, and aims to ensure food security for the poor and vulnerable sections of the country by providing free food foodgrains. It was announced on 26 March 2020 during the COVID-19 pandemic and is operated by the Department of Food and Public Distribution under the Ministry of Consumer Affairs, Food and Public Distribution. Through this scheme, free foodgrains (rice or wheat, depending on the State) are provided to eligible ration card holders covered under the National Food Security Act, 2013, namely Antyodaya Anna Yojana (AAY) households and Priority Households (PHH). From 1 January 2023, the scheme was integrated into the food security framework, and foodgrains earlier given at the highly subsidised rates of ₹1, ₹2, and ₹3 per kilogram for coarse cereals, wheat, and rice, respectively, are now provided free of cost. The scheme has been extended by the Union Cabinet for 5 years starting from 1 January 2024 and is approved for continuation till 31 December 2028, with a total financial outlay of ₹11.80 lakh crore (₹11,80,000 crore). The scheme is implemented through the Targeted Public Distribution System (TPDS) by the state governments and Union Territory Administrations, with foodgrain allocation by the Government of India.. The scheme aims to ensure food security for the poor. Through this scheme, free foodgrains are provided to eligible ration card holders under the National Food Security Act, 2013.. Antyodaya Anna Yojana (AAY) families receive 35 kilograms of foodgrains per family per month. Priority Household (PHH) beneficiaries receive 5 kilograms of foodgrains per person per month. The foodgrains are provided as | H100: 0 | J100: =INT((ROW()-2)/50)+1 -> 2 | K100: =IF(H100="","Pending",IF(OR(H100="0",H100="1",H100="2",H100="U"),"Complete","Invalid")) -> Complete
A101: v2q-003-candidate-24 | B101: v2q-003 | C101: What revised overdraft limit and RuPay accidental-insurance cover are stated for PMJDY? | D101: PMJDY states a revised overdraft limit of ₹10,000 and accidental-insurance cover of ₹2 lakh for RuPay cardholders. | E101: pilot-v2-doc-ab-pmjay-0000-94c82a474579 | F101: Ayushman Bharat - Pradhan Mantri Jan Arogya Yojana | G101: Ayushman Bharat - Pradhan Mantri Jan Arogya Yojana. Ministry Of Health & Family Welfare. Department of Health and Family Welfare. National Health Authority (NHA). The scheme “Ayushman Bharat – Pradhan Mantri Jan Arogya Yojana” implemented by the National Health Authority (NHA) under Ministry of Health and Family Welfare, Government of India, aims to provide cashless hospitalisation coverage of ₹5,00,000 per family per year to poor and vulnerable families for secondary and tertiary healthcare services. It was launched on 23rd September 2018 in Ranchi, Jharkhand, by the Hon’ble Prime Minister of India. &quot;Ayushman Bharat&quot; is an attempt to move from a sectoral and segmented approach to health service delivery to a comprehensive need-based health care service. This scheme aims to undertake path-breaking interventions to holistically address the healthcare system (covering prevention, promotion, and ambulatory care) at the primary, secondary, and tertiary levels. Ayushman Bharat adopts a continuum of care approach, comprising two interrelated components, which are - Health and Wellness Centres (HWCs): The scheme aims to provide comprehensive primary healthcare services, including maternal and child health, non-communicable disease care, free essential drugs, and diagnostics, close to people’s homes. The centres promote preventive healthcare and healthy behaviours to reduce the risk of chronic diseases. Pradhan Mantri Jan Arogya Yojana (PM-JAY): The second component under Ayushman Bharat is the Pradhan Mantri Jan Arogya Yojna or PM-JAY as it is popularly known. It aims to provide cashless health insurance coverage of up to ₹5,00,000 per family per year for secondary and tertiary hospitalization to poor and vulnerable families.. AB PM-JAY is a health insurance scheme for low-income families in rural and urban areas. The scheme aims to provide affordable healthcare facilities to the Poor. It is the largest health assurance scheme in the world which aims at providing a health cover of ₹5,00,000/- per | H101: 0 | J101: =INT((ROW()-2)/50)+1 -> 2 | K101: =IF(H101="","Pending",IF(OR(H101="0",H101="1",H101="2",H101="U"),"Complete","Invalid")) -> Complete
A102: v2q-003-candidate-03 | B102: v2q-003 | C102: What revised overdraft limit and RuPay accidental-insurance cover are stated for PMJDY? | D102: PMJDY states a revised overdraft limit of ₹10,000 and accidental-insurance cover of ₹2 lakh for RuPay cardholders. | E102: pilot-v2-doc-pm-svanidhi-0001-e06d259b429d | F102: PM Street Vendor’s AtmaNirbhar Nidhi (PM SVANidhi) | G102: a working capital collateral-free loan of ₹10,000, with subsequent loans of ₹20,000 and ₹50,000 with a 7% interest subsidy.. Working Capital Loan: 1st Tranche: Loan up to ₹15,000/-; repayment within 12 months. - 2nd Tranche: Loan up to ₹25,000/-; repayment within 18 months. - 3rd Tranche: Loan up to ₹50,000/-; repayment within 36 months. - Next tranche available on timely or early repayment. No prepayment penalty on early repayment. Interest Subsidy: Subsidy at 7% per annum on loan amount. Credited quarterly to beneficiary’s bank account. Applicable only for standard (non-NPA) accounts. Valid up to 31st March 2033. Digital Transaction Cashback: Cashback up to ₹100/- per month for digital transactions. Credit Guarantee Support: 31.87% guarantee cover for 1st tranche loan. 8.25% guarantee cover for 2nd tranche loan. 6% guarantee cover for 3rd tranche loan. No charges for lending institutions. UPI Linked RuPay Credit Card: Initial credit limit of ₹10,000/-; extendable up to ₹30,000/-. Validity of 5 years. Available after successful repayment of 2nd tranche loan.. Street vendors in possession of Certificate of Vending / Identity Card issued by Urban Local Bodies (ULBs). The vendors, who have been identified in the survey but have not been issued Certificate of Vending / Identity Card. Street Vendors left out of the ULB-led identification survey or who have started vending after completion of the survey and have been issued a Letter of Recommendation (LoR) to that effect by the ULB / Town Vending Committee (TVC). The vendors of surrounding development/ peri-urban/rural areas vending in the geographical limits of the ULBs, who have been issued a Letter of Recommendation (LoR) to that effect by the ULB / TVC.. Step 1: Visit https://pmsvanidhi.mohua.gov.in/ and click on the "Log In" button on the homepage. Step 2: Enter Mobile number and captcha. Click request OTP. Step 3: After successful | H102: 0 | J102: =INT((ROW()-2)/50)+1 -> 3 | K102: =IF(H102="","Pending",IF(OR(H102="0",H102="1",H102="2",H102="U"),"Complete","Invalid")) -> Complete
A103: v2q-021-candidate-02 | B103: v2q-021 | C103: How do insurance companies and banks participate in PMFBY? | D103: PMFBY is implemented through a network of insurance companies and banks to provide crop-insurance protection to farmers. | E103: pilot-v2-doc-mgnrega-0000-7e6d80b47566 | F103: Mahatma Gandhi National Rural Employment Guarantee Act | G103: Mahatma Gandhi National Rural Employment Guarantee Act. Ministry Of Rural Development. Department of Rural Development. Gram Panchayats (GPs). An employment scheme by the Ministry of Rural Development, providing provide at least 100 days of guaranteed wage employment in a financial year to every rural household whose adult members volunteer to do unskilled work. Any Indian citizen above the age of 18 years and residing in a rural area can apply to this scheme. The applicant receives guaranteed employment within 15 days from the date of application. The wage is deposited directly in the Bank Account / Post Office Account of the applicant. Wages are paid within a week, or fifteen days at most. Men and Women are paid equally. MGNREGA covers the entire country with the exception of districts that have a hundred percent urban population.. An employment scheme by the MoRD, providing provide at least 100 days of guaranteed wage employment in a financial year to every rural household whose adult members volunteer to do unskilled work. Any Indian citizen above the age of 18 years and residing in a rural area can apply to this scheme.. The applicant receives guaranteed employment within 15 days from the date of application. Work is to be provided within a radius of 5 kilometers of the applicant’s residence if possible, and in any case within the Block. If the applicant lives more than 5 km away from the worksite, he/she will be entitled to a travel and subsistence allowance (10% of the minimum wage). Wages are paid within a week, or fifteen days at most. Men and Women are paid equally. Shade, drinking water, and first-aid are provided at every worksite. Exclusive measures for the promotion of the participation of the disabled persons: Identification of suitable works Mobilization of disabled persons by | H103: 0 | J103: =INT((ROW()-2)/50)+1 -> 3 | K103: =IF(H103="","Pending",IF(OR(H103="0",H103="1",H103="2",H103="U"),"Complete","Invalid")) -> Complete
A104: v2q-020-candidate-18 | B104: v2q-020 | C104: How do NSDC and SPIAs divide responsibility in the Special Projects arm of the national skill mission? | D104: NSDC supports the ministry’s implementation, while Special Projects Implementing Agencies deliver the projects on the ground. | E104: pilot-v2-doc-pm-kisan-guidelines-0007-38a7fcb29c5d | F104: PM-KISAN Operational Guidelines | G104: the District. Provided that the name of the beneficiary is included in the state of Nagaland’s Agriculture Census of 2015-16. This proviso shall not be applicable in cases of succession and family partition. 5 The list of such beneficiaries shall be subject to the exclusions under the operational guidelines. 5.6 For identification of bona fide beneficiary under PM-Kisan Scheme in Jharkhand, the following proposal of Government of Jharkhand was considered and approved by the Committee: “The farmer will be asked to submit ‘Vanshavali (Lineage)’ linked to the entry of land record comprising his \ her ancestor’s name giving a chart of successor. This lineage chart shall be submitted before the Gram Sabha for calling objections. After approval of the Gram Sabha, the village level \ circle level revenue officials will verify and authenticate the Vanshawali and possession of holding. This authenticated list of farmers after due verification of succession chart shall be countersigned by the District level revenue authority. Farmers’ names, subject to the exclusion criterion after following the aforementioned process, shall be uploaded on the PM-Kisan portal along with other required details for this disbursement of benefit under the scheme.” 6. Strategy for Implementation 6.1 The States shall prepare database of eligible beneficiary land holder farmer families in the villages capturing the Name, Age, Gender, Category (SC/ST), Aadhaar Number, Bank Account Number and the Mobile Number of the beneficiaries. Responsibility of identifying the land holder farmer family eligible for benefit under the scheme shall be of the State / UT Government. In case of beneficiaries in States of Assam, Meghalaya, J&K where Aadhaar number has not been issued to most of the citizens, Aadhaar number shall be collected for those beneficiaries where it is available and for others alternate prescribed documents such as Driving Licence, Voters’ ID Card, NREGA | H104: 0 | J104: =INT((ROW()-2)/50)+1 -> 3 | K104: =IF(H104="","Pending",IF(OR(H104="0",H104="1",H104="2",H104="U"),"Complete","Invalid")) -> Complete
A105: v2q-027-candidate-07 | B105: v2q-027 | C105: What livelihood mechanism does PM SVANidhi offer street vendors, and which other programme from its ministry addresses housing shortages for eligible urban households? | D105: PM SVANidhi offers street vendors collateral-free working-capital loans, interest subsidy, and digital-payment incentives. PMAY-U, under the same Ministry of Housing and Urban Affairs, provides housing support for eligible urban households. | E105: pilot-v2-doc-pmay-g-0000-d4162175877d | F105: Pradhan Mantri Awaas Yojana - Gramin | G105: Pradhan Mantri Awaas Yojana - Gramin. Ministry Of Rural Development. Department of Rural Development. Ministry Of Housing And Urban Affairs (MoHUA). Launch on 1st April 2016, Pradhan Mantri Awaas Yojana Gramin (PMAY-G) is centre's flagship mission by the Ministry of Rural Development (MoRD), implemented by the Ministry of Housing and Urban Affairs (MoHUA). PMAY-G aims at providing a pucca house, with basic amenities, to all houseless households and those households living in kutcha and dilapidated house. PMAY-G addresses the rural housing shortage and bridges the housing deficit in rural areas of India, contributing significantly to the mission of "Housing for All". The minimum size of the houses under PMAY-G is 25 sq m including a dedicated area for hygienic cooking. As of 27th Sept 2022, 2.00 crore houses have been constructed out of the total target of 2.72 crores. The beneficiaries are identified using the Socio-Economic and Caste Census (SECC) parameters and verified by the Gram Sabhas. The amount is transferred directly to the Aadhaar-Linked Bank Account / Post-Office Account of the beneficiary. PMAY-G has been extended for another two years, i.e. till 31st March 2024. Aim and Objective: PMAY-G aims to provide a pucca house with basic amenities to all houseless households and households living in kutcha and dilapidated house in rural areas by 2024. The immediate objective is to cover 1.00 Crore households in rural areas, that are houseless or living in kutcha / dilapidated house, in three years from 2016-17 to 2018-19 and enable construction of quality houses by the beneficiaries using local materials, designs and trained masons. For houses to become homes, adoption of a habitat approach through convergence is proposed.. Launch on 1st April 2016, Pradhan Mantri Awaas Yojana Gramin (PMAY-G) is centre's flagship mission by the Ministry of Rural Development (MoRD), implemented by the | H105: 0 | J105: =INT((ROW()-2)/50)+1 -> 3 | K105: =IF(H105="","Pending",IF(OR(H105="0",H105="1",H105="2",H105="U"),"Complete","Invalid")) -> Complete
A106: v2q-021-candidate-09 | B106: v2q-021 | C106: How do insurance companies and banks participate in PMFBY? | D106: PMFBY is implemented through a network of insurance companies and banks to provide crop-insurance protection to farmers. | E106: pilot-v2-doc-pmjdy-0000-8b241ec39723 | F106: Pradhan Mantri Jan Dhan Yojana | G106: Pradhan Mantri Jan Dhan Yojana. Ministry Of Finance. Department of Financial Service. Banks. A National Mission for Financial Inclusion (NMFI), namely, Pradhan Mantri Jan Dhan Yojana (PMJDY) was launched across the Country in August, 2014 by the Prime Minister with the idea to ensure that citizens envisage their financial activities. PMJDY provides universal banking services for every unbanked household, based on the guiding principles of banking the unbanked, securing the unsecured, funding the unfunded and serving unserved and underserved areas. In order to give impetus to financial inclusion initiatives of the Government, PMJDY scheme was extended beyond 14.08.2018 with the focus on opening of accounts shifting from “every household” to “every unbanked adult”. The scheme has been made more attractive with upward revision in (i) OD limit from Rs. 5,000/- to Rs. 10,000/- and (ii) Accidental insurance cover on RuPay card holders from Rs.1 lakh to Rs.2 lakhs. PMJDY has been successful in increasing banking penetration and promoting financial inclusion across the country. The scheme has ensured access to various financial services like availability of basic savings bank account, access to need based credit, remittances facility, insurance and pension to the excluded sections i.e. weaker sections &amp; low-income groups.. A National Mission for Financial Inclusion (NMFI), namely, Pradhan Mantri Jan Dhan Yojana (PMJDY) was launched by the Prime Minister across the country on 28th August, 2014. It envisages to provide universal banking services for every unbanked adult in the country.. Basic Savings Bank Deposit Account (BSBDA) Any Indian citizen eligible to open a regular bank account can open a BSBDA. Such an account does not require any minimum balance maintenance. The account holders can use both bank branches, ATMs and Banking Correspondents (BCs) for depositing and withdrawing cash. However, one cannot withdraw cash more than four times a month. Small | H106: 0 | J106: =INT((ROW()-2)/50)+1 -> 3 | K106: =IF(H106="","Pending",IF(OR(H106="0",H106="1",H106="2",H106="U"),"Complete","Invalid")) -> Complete
A107: v2q-003-candidate-15 | B107: v2q-003 | C107: What revised overdraft limit and RuPay accidental-insurance cover are stated for PMJDY? | D107: PMJDY states a revised overdraft limit of ₹10,000 and accidental-insurance cover of ₹2 lakh for RuPay cardholders. | E107: pilot-v2-doc-apy-0000-c43dd88d7899 | F107: Atal Pension Yojana | G107: Atal Pension Yojana. Ministry Of Finance. Department of Financial Service. Banks. Atal Pension Yojana (APY) is an old age income security scheme for a savings account holder in the age group of 18-40 years who is not an income tax-payee. The scheme helps in addressing the longevity risks among the workers in the unorganized sector and encourages the workers to voluntarily save for their retirement. Focus of APY The scheme is mainly targeted at the poor, the under-privileged and workers in the unorganized sector. APY Subscriber Contribution Chart - https://www.npscra.nsdl.co.in/nsdl/scheme-details/APYSubscribersContributionChart1.pdf Charges and fees and overdue interest under APY: The charges and fees and the overdue interest for non-payment or delayed payment of prescribed contribution amount shall be levied on the subscribers of APY. These charges and their method of application shall be prescribed by PFRDA from time to time, in consultation with the Central Government. Raising Grievance Under APY A subscriber can raise grievance anytime free of cost from anywhere by visiting: www.npscra.nsdl.co.in &gt;&gt;Home &gt;&gt; select: NPS-Lite or through CGMS Subscriber raising the grievance will be allotted a token number against the grievance raised. Subscriber may check the status of the grievance under “Check the status of Grievance / Enquiry already registered”.. Atal Pension Yojana (APY) is an old age income security scheme for a savings account holder in the age group of 18-40 years, who is not an income tax-payee. It helps to address longevity risks among workers in unorganized sector and encourages the workers to voluntarily save for retirement.. Upon exit on attaining 60 years The subscriber shall receive the following three benefits on attaining the age of 60: (i) Guaranteed minimum pension amount: Each subscriber under APY shall receive a guaranteed minimum pension of Rs. 1000/- per month or Rs. 2000/- per month or Rs. 3000/- per | H107: 0 | J107: =INT((ROW()-2)/50)+1 -> 3 | K107: =IF(H107="","Pending",IF(OR(H107="0",H107="1",H107="2",H107="U"),"Complete","Invalid")) -> Complete
A108: v2q-031-candidate-08 | B108: v2q-031 | C108: How do three finance-sector programmes combine basic banking, life insurance, and accident insurance? | D108: PMJDY provides universal banking and access to financial services; PMJJBY supplies life cover for death from any cause; PMSBY supplies accidental-death and disability cover. | E108: pilot-v2-doc-pm-kmy-guidelines-0004-79b3bf95bb65 | F108: Pradhan Mantri Kisan Maan Dhan Yojana Operational Guidelines | G108: Municipal Corporations, former and present Chairpersons of District Panchayats. (d) All serving or retired officers and employees of Central/ State Government Ministries/ Offices/Departments and their field units, Central or State PSEs and Attached offices/ Autonomous Institutions under Government as well as regular employees of the Local Bodies (ExcludingMultiTaskingStaff/ClassIV/GroupD employees) (e) All Persons who paid Income Tax in last assessment year. (f) Professionals like Doctors, Engineers, Lawyers, Chartered Accountants, and Architects registered with Professional bodies and carrying out profession by undertaking practice. 3 5.2 For the purpose of exclusion State/UT Government can certify the eligibility of the beneficiary based on self declaration by the beneficiaries. In case beneficiary is not available /does not reside in the village, State/UT Governments may consider certification based on the declaration by other adult member of his/her family. In case of incorrect self declaration, beneficiary shall not be eligible for financial benefit under the Scheme. 6. Key features of the Scheme (i) The PM-KMY is a Central Sector Scheme, administered by the Department of Agriculture, Cooperation & Farmers Welfare, Ministry of Agriculture & Farmers’ Welfare, Government of India in partnership with the Life Insurance Corporation of India (LIC). (ii) The LIC shall be the Pension Fund Manager and responsible for Pension pay out. (iii) It is a voluntary and periodic contribution based pension system meant for all land holding Small and Marginal Farmers (SMFs) throughout the country, subject to aforesaid exclusion criteria. (iv) The SMFs shall have the option to allow payment of his/her voluntary contribution to the Scheme from the financial benefits received by them from the PM-KISAN Scheme, directly. (v) The eligible SMFs who are desirous of using their PM-Kisan benefit for contributing for PM-KMY, will have to sign and submit an enrolment-cum-auto-debit-mandate form for giving their consent for auto-debiting their bank accounts, in | H108: 0 | J108: =INT((ROW()-2)/50)+1 -> 3 | K108: =IF(H108="","Pending",IF(OR(H108="0",H108="1",H108="2",H108="U"),"Complete","Invalid")) -> Complete
A109: v2q-026-candidate-12 | B109: v2q-026 | C109: What employment guarantee does MGNREGA provide, and which other programme from its ministry supplies pucca houses to rural households? | D109: MGNREGA guarantees at least 100 days of wage employment to qualifying rural households. PMAY-G, under the same Ministry of Rural Development, supports pucca houses with basic amenities for eligible rural households. | E109: pilot-v2-doc-pm-janman-0002-d0844e3327b6 | F109: PM Janjati Adivasi Nyaya Maha Abhiyan (PM JANMAN) | G109: physical survey conducted by state governments using the mobile application on the PM Gati-shakti Portal. Eligibility Specific to Interventions The applicant household seeking a pucca house must currently reside in a kaccha house. The applicant household seeking solar power solutions must be an unelectrified household not covered under the Revamped Distribution Sector Scheme (RDSS). The applicant household seeking an on-grid electricity connection shall be an identified beneficiary household under PM-JANMAN, irrespective of standard eligibility criteria under the Revamped Distribution Sector Scheme (RDSS) for the State and Electricity distribution company (DISCOM).. Step 1: Initiation of Identification and Physical Survey The State Governments initiates a detailed physical survey of each Particularly Vulnerable Tribal Group habitation to ascertain the gaps regarding the 11 critical interventions covered under the mission. The data gathered during this exhaustive survey is simultaneously updated and cross-verified on a mobile application developed on the PM Gati-shakti Portal. Step 2: Facilitation of Application Filing for Eligible Beneficiaries The Block Level Implementation Team, consisting of officers designated by the District Collector, will be responsible for identifying each beneficiary family who has not yet been saturated with entitlements and will facilitate the necessary application filing for the respective schemes. The District Level Committee is also responsible for the registration and filling of applications of eligible beneficiaries for each scheme covered under the mission. Step 3: Verification and Project Approval Following the application filing and preliminary eligibility checks, certain proposals for infrastructure, such as the sanctioning of Multi-Purpose Centers, must be forwarded by the Secretary/Principal Secretary, State Tribal Welfare Department to the Ministry of Tribal Affairs. These proposals are subsequently examined by the relevant division, approved by the Mission Director of PM-JANMAN, and granted financial concurrence by the Internal Finance Division. | H109: 0 | J109: =INT((ROW()-2)/50)+1 -> 3 | K109: =IF(H109="","Pending",IF(OR(H109="0",H109="1",H109="2",H109="U"),"Complete","Invalid")) -> Complete
A110: v2q-005-candidate-04 | B110: v2q-005 | C110: How many days of wage employment does MGNREGA guarantee a rural household in a financial year? | D110: MGNREGA guarantees at least 100 days of wage employment per financial year to a rural household whose adult members volunteer for unskilled work. | E110: pilot-v2-doc-mgnrega-0001-5203a455caa6 | F110: Mahatma Gandhi National Rural Employment Guarantee Act | G110: entitled to a travel and subsistence allowance (10% of the minimum wage). Wages are paid within a week, or fifteen days at most. Men and Women are paid equally. Shade, drinking water, and first-aid are provided at every worksite. Exclusive measures for the promotion of the participation of the disabled persons: Identification of suitable works Mobilization of disabled persons by focussing on awareness and special provisions Specifically identified works for disabled persons in the case of large GPs Preference to appoint as mates and as workers for providing drinking water, to manage crèches, etc., at the worksites Adoption of tools and equipment/facilities at workplaces Treating persons with disabilities with respect Special drive to ensure 100 days of employment to such households Provide a special job card of a distinct color Specific attention and provisions for Senior Citizens: Exclusive senior citizen groups may be formed and special works which require lesser physical effort are identified and allotted to these groups. Specific attention and provisions for Internally Displaced Persons: A special job card to be provided will be valid till these families are displaced and will lose its validity as soon as they return to their original place of residence.. The applicant must be at least 18 years of age. The applicant must be residing in a Rural Area.. NA. Step 1: The application for registration may be given on plain paper to the local Gram Panchayat. An individual may appear personally before the Panchayat Secretary or Gram Rozgar Sahayak and make an oral request for registration, in which case the particulars required will be noted by the Gram Rojgar Sahayak or the Panchayat Secretary. Application for registration should contain names of those adult members of the household who are willing to do unskilled manual work. Particulars such as age, sex, SC/ST | H110: 2 | J110: =INT((ROW()-2)/50)+1 -> 3 | K110: =IF(H110="","Pending",IF(OR(H110="0",H110="1",H110="2",H110="U"),"Complete","Invalid")) -> Complete
... A128: v2q-006-candidate-17 | B128: v2q-006 | C128: What annual hospitalisation cover does AB-PMJAY provide per eligible family? | D128: AB-PMJAY provides cashless hospitalisation cover of ₹5 lakh per family per year for secondary and tertiary healthcare. | E128: pilot-v2-doc-mgnrega-0002-bbbce5f319d4 | F128: Mahatma Gandhi National Rural Employment Guarantee Act | G128: before the Panchayat Secretary or Gram Rozgar Sahayak and make an oral request for registration, in which case the particulars required will be noted by the Gram Rojgar Sahayak or the Panchayat Secretary. Application for registration should contain names of those adult members of the household who are willing to do unskilled manual work. Particulars such as age, sex, SC/ST status, Rashtriya Swastha Bima Yojana (RSBY) number, Aadhar number, Below Poverty Line (BPL) status and bank/post office account number (if s/he has opened one) must be provided in the application. Step 2: The Gram Panchayat (GP) will verify the following details: Whether the household is really an entity as stated in the application. Whether the applicant household are local residents in the Gram Panchayat concerned. Whether applicants are adult members of the household. The process of verification shall be completed as early as possible, and in any case not later than a fortnight after the receipt of the application in the Gram Panchayat. Step 3: All particulars of a household found to be eligible after verification, will be entered in the MIS (NREGASoft) by the Panchayat Secretary or the Gram Rojgar Sahayak (GRS) or a person duly authorized by the State Government. Step 4: If a household is found to be eligible for registration, the GP will, within a fortnight of the application, issue a JC to the household. JC should be handed over to one of the members of the applicant household in the presence of a few other residents of the GP. The format of the Job Card is provided in the Annexure-5 of the scheme guidelines. The detailed format for application for registration is provided in Annexure-3 of the scheme guidelines. Registrations shall be opened throughout the year at the Gram Panchayat (GP) office. Application for registration | H128: 0 | J128: =INT((ROW()-2)/50)+1 -> 3 | K128: =IF(H128="","Pending",IF(OR(H128="0",H128="1",H128="2",H128="U"),"Complete","Invalid")) -> Complete
A129: v2q-028-candidate-06 | B129: v2q-028 | C129: What does PMKVY Recognition of Prior Learning certify, and which other pathway from its ministry serves candidates seeking fresh short-term skills training? | D129: PMKVY Recognition of Prior Learning certifies candidates’ existing skills. PMKVY Short-Term Training, under the same Ministry of Skill Development and Entrepreneurship, provides fresh skilling, reskilling, or upskilling. | E129: pilot-v2-doc-pmkvy-rpl-0003-9425f5b8529a | F129: Pradhan Mantri Kaushal Vikas Yojana 4.0 - Recognition Of Prior Learning | G129: in the same sector, shall be discouraged; however, a higher job role in the same sector is permitted. The applicant may enrol not more than twice in the same sector, with a six-month gap between the certification date of the first course and the batch start date of the subsequent course.. The interested candidate can contact the nearest Training Center to apply. Training Center: https://www.pmkvyofficial.org/trainingcenter. The applicant first registers on the Skill India Digital (SID) platform or the mobile application developed for the purpose; profile verification is completed through mobile-based OTP / eKYC, and a de-duplication check is carried out. The applicant is counselled by the PIA/trainer on areas including a brief about MSDE, the Skill India programme, and RPL processes; eligibility for RPL certification; benefits and how to avail them; possible career progression (vertical and horizontal); and employment opportunities. The Induction Video on RPL is also shown at this stage. Stage 1: The applicant is pre-screened by the Awarding Body through a robust process to ascertain the existing level of prior learning. This includes Part 1 (collection of supporting documentation and evidence from the candidate) and Part 2 (assessment of the candidate's previous knowledge). No payment is charged for pre-screening. Stage 2: The candidate's experiential learning outcomes are categorised as equal to or more than 70% of the qualification learning outcomes, or as less than 70%. Stage 3: The applicant undergoes a minimum of 30 hours of classroom orientation, either General Orientation (with modules for Employability Skills, Career Progression, Opportunities for formal education, etc.) or Orientation with NOS (with modules for NOS, Employability Skills, Career Progression, etc.). The maximum duration of RPL is 132 hours. Stage 4: The applicant undergoes assessment (Theory and Practical), conducted by the Awarding Bodies, equivalent to STT assessment, with AEBAS-based compulsory attendance. Stage 5: | H129: 1 | I129: RPL enrollment-frequency restriction — correct sub-scheme, does not state what RPL certifies. | J129: =INT((ROW()-2)/50)+1 -> 3 | K129: =IF(H129="","Pending",IF(OR(H129="0",H129="1",H129="2",H129="U"),"Complete","Invalid")) -> Complete
A130: v2q-030-candidate-20 | B130: v2q-030 | C130: What retirement benefit does APY offer, and which life-insurance programme administered through the same department covers death from any cause? | D130: APY offers guaranteed monthly pension options after age 60. PMJJBY, associated with the same Department of Financial Services, provides life cover for death due to any reason. | E130: pilot-v2-doc-pmmy-0000-70a89ee32765 | F130: Pradhan Mantri Mudra Yojana | G130: Pradhan Mantri Mudra Yojana. Ministry Of Finance. Department of Financial Service. Member Lending Institutions - Bank Or A Micro Finance Institution (MFI) / Non-Banking Finance Company (NBFC) / Other Financial Intermediary. Pradhan Mantri Mudra Yojana (PMMY) is a flagship scheme of Government of India. The scheme facilitates micro credit/Loan up to Rs. 20 lakhs to income generating micro enterprises engaged in the non farm sector in manufacturing, trading or service sectors including activities allied to agriculture such as poultry, dairy, beekeeping, etc. The Scheme provides financial assistance extended by Member Lending Institutions to the non-corporate, non-farm sector income generating activities of micro and small entities. These micro and small entities comprise of millions of proprietorship / partnership firms running as small manufacturing units, service sector units, shopkeepers, fruits / vegetable vendors, truck operators, food-service units, repair shops, machine operators, small industries, artisans, food processors and others. The loans under Pradhan Mantri Mudra Yojana can be availed through eligible Member Lending Institutions (MLIs), which include: Public Sector Banks Private Sector Banks State operated cooperative banks Rural banks from regional sector Micro Finance Institution (MFI) Non-Banking Finance Company (NBFC) Small Finance Banks (SFBs) Other financial intermediary approved by Mudra Ltd. as member financial institutions Interest rate The interest rates are declared by Member Lending Institutions from time to time as per Reserve Bank of India guidelines based on which applicable interest rate is determined. Upfront fee/Processing charges Banks may consider charging of upfront fee as per their internal guidelines. The upfront fee/processing charges for Shishu loans (Covering loans upto Rs. 50,000/-) are waived by most Banks. Note : There are no agents or middleman engaged by MUDRA for availing of Mudra Loans. The borrowers are advised to keep away from persons posing as Agents/ facilitators of MUDRA/PMMY.. Pradhan Mantri Mudra Yojana (PMMY) | H130: 0 | J130: =INT((ROW()-2)/50)+1 -> 3 | K130: =IF(H130="","Pending",IF(OR(H130="0",H130="1",H130="2",H130="U"),"Complete","Invalid")) -> Complete
A131: v2q-006-candidate-24 | B131: v2q-006 | C131: What annual hospitalisation cover does AB-PMJAY provide per eligible family? | D131: AB-PMJAY provides cashless hospitalisation cover of ₹5 lakh per family per year for secondary and tertiary healthcare. | E131: pilot-v2-doc-mgnrega-0000-7e6d80b47566 | F131: Mahatma Gandhi National Rural Employment Guarantee Act | G131: Mahatma Gandhi National Rural Employment Guarantee Act. Ministry Of Rural Development. Department of Rural Development. Gram Panchayats (GPs). An employment scheme by the Ministry of Rural Development, providing provide at least 100 days of guaranteed wage employment in a financial year to every rural household whose adult members volunteer to do unskilled work. Any Indian citizen above the age of 18 years and residing in a rural area can apply to this scheme. The applicant receives guaranteed employment within 15 days from the date of application. The wage is deposited directly in the Bank Account / Post Office Account of the applicant. Wages are paid within a week, or fifteen days at most. Men and Women are paid equally. MGNREGA covers the entire country with the exception of districts that have a hundred percent urban population.. An employment scheme by the MoRD, providing provide at least 100 days of guaranteed wage employment in a financial year to every rural household whose adult members volunteer to do unskilled work. Any Indian citizen above the age of 18 years and residing in a rural area can apply to this scheme.. The applicant receives guaranteed employment within 15 days from the date of application. Work is to be provided within a radius of 5 kilometers of the applicant’s residence if possible, and in any case within the Block. If the applicant lives more than 5 km away from the worksite, he/she will be entitled to a travel and subsistence allowance (10% of the minimum wage). Wages are paid within a week, or fifteen days at most. Men and Women are paid equally. Shade, drinking water, and first-aid are provided at every worksite. Exclusive measures for the promotion of the participation of the disabled persons: Identification of suitable works Mobilization of disabled persons by | H131: 0 | J131: =INT((ROW()-2)/50)+1 -> 3 | K131: =IF(H131="","Pending",IF(OR(H131="0",H131="1",H131="2",H131="U"),"Complete","Invalid")) -> Complete
A132: v2q-007-candidate-03 | B132: v2q-007 | C132: What is the full form of PMJJBY, and which event does its life insurance cover? | D132: PMJJBY stands for Pradhan Mantri Jeevan Jyoti Bima Yojana and provides life-insurance cover for death due to any reason. | E132: pilot-v2-doc-pmsby-0000-0f297846df39 | F132: Pradhan Mantri Suraksha Bima Yojana | G132: Pradhan Mantri Suraksha Bima Yojana. Ministry Of Finance. Department of Financial Service. Banks. An Accident Insurance Scheme offering accidental death and disability cover for death or disability on account of an accident. Premium: Rs.20/- per annum per member. The premium will be deducted from the account holder’s bank / Post office account through ‘auto debit’ facility on or before 1st June of each annual coverage period under the scheme. Coverage Duration: Coverage under PMJJBY is valid for one year from 1st June to 31st May on payment of annual premium. Accident cover assurance termination: The accident cover of the member shall terminate / be restricted accordingly on any of the following events: • On attaining age 70 years (age nearer birth day). • Closure of account with the Bank or insufficiency of balance to keep the insurance in force. In case a member is covered under PMSBY through more than one account and premium is received by insurance company inadvertently, insurance cover will be restricted to Rs. 2 lakh.. An Accident Insurance Scheme offering accidental death and disability cover for death or disability on account of an accident.. On Death- the Nominee shall get Rs. 2 Lakhs. Total and irrecoverable loss of both eyes or loss of use of both hands or feet or loss of sight of one eye and loss of use of hand or foot- Subscriber shall get Rs. 2 Lakhs. Total and irrecoverable loss of sight of one eye or loss of use of one hand or foot –subscriber shall get Rs. 1 Lakh.. Individual bank account holders of participating banks aged between 18 years (completed) and 70 years (age nearer birthday) who give their consent to join / enable auto-debit, will be enrolled into the scheme.. Step 01: In order to enrol in PMSBY offline, | H132: 1 | J132: =INT((ROW()-2)/50)+1 -> 3 | K132: =IF(H132="","Pending",IF(OR(H132="0",H132="1",H132="2",H132="U"),"Complete","Invalid")) -> Complete
A133: v2q-014-candidate-16 | B133: v2q-014 | C133: Under the national ration programme, what monthly cereal allocation goes to families in the poorest entitlement tier and to each person in the priority tier? | D133: AAY families receive 35 kilograms per family per month, while PHH beneficiaries receive 5 kilograms per person per month. | E133: pilot-v2-doc-pm-kmy-guidelines-0000-0582a8323d67 | F133: Pradhan Mantri Kisan Maan Dhan Yojana Operational Guidelines | G133: Pradhan Mantri Kisan Maan Dhan Yojana (PM-KMY) OPERATIONAL GUIDELINES 1. Scheme The Government of India has introduced an old age pension scheme for all land holding Small and Marginal Farmers (SMFs) in the country, namely, the “Pradhan Mantri Kisan Maan-Dhan Yojana (PM-KMY)”, as a voluntary and contributory pension scheme for the entry age group of 18 to 40 years. The Scheme is effective from the 9th August, 2019. 2. Objective and Benefits There have been a series of interventions for income and price support by the Government for farmers. However, there is a felt need to create a social security net for the farmers as old age may result in loss of livelihood for many of them. Farming requires hard work in fields which becomes difficult at an advanced age. The problem is compounded in respect of small and marginal farmers as they have minimal or no savings to provide for old age. The Pradhan Mantri Kisan Maan-Dhan Yojana (PM-KMY) provides for an assured monthly pension of Rs. 3000/- to all land holding Small and Marginal Farmers (SMFs), whether male or female, on their attaining the age of 60 years. Farmers falling within the purview of the exclusion criteria (as defined in Para 5 of these guidelines) are, however, not eligible for the benefit. The key features and other consequential benefits accruing to the subscribers of the Scheme are detailed further in these guidelines. 3. Definitions : (a) “BENEFICIARY” shall mean the subscriber and in case of his/her death his/her spouse; (b) “Contribution” means the amount specified in the contribution chart appended with this Scheme as modified by the Government from time to time, to be payable monthly or periodically by an eligible subscriber to the scheme; (c) “CSC” means “Common Service Centre e-Governance Services India Limited – Special Purpose | H133: 0 | J133: =INT((ROW()-2)/50)+1 -> 3 | K133: =IF(H133="","Pending",IF(OR(H133="0",H133="1",H133="2",H133="U"),"Complete","Invalid")) -> Complete
A134: v2q-001-candidate-09 | B134: v2q-001 | C134: What is the minimum house size specified under PMAY-G? | D134: The minimum house size is 25 square metres, including a dedicated hygienic cooking area. | E134: pilot-v2-doc-pmay-g-0005-c6e2fcfefcd0 | F134: Pradhan Mantri Awaas Yojana - Gramin | G134: defence/paramilitary/police forces killed in action. ii. Households where a member is suffering from leprosy or cancer and People living with HIV (PLHIV). iii. Households with a single girl child. iv. Beneficiary families of the Scheduled Tribes and Other Traditional Forest Dwellers (Recognition of Forest Rights) Act, 2006, commonly known as the Forest Rights Act. v. Transgender persons.. Step 1: Exclusion of pucca houses All households living in houses with pucca roofs and/or pucca walls and households living in houses with more than 2 rooms are filtered out. Step 2: Automatic Exclusion From the remaining set of households, all households fulfilling any one of the 13 parameters listed below are automatically excluded:- 1. Motorised two/three/four wheeler/ fishing boat 2. Mechanised three/four-wheeler agricultural equipment 3. Kisan Credit Card with a credit limit of Rs.50,000 or above 4. Household with any member as a Government employee 5. Households with non-agricultural enterprises registered with the Government 6. Any member of the family earning more than Rs.10,000 per month 7. Paying income tax 8. Paying professional tax 9. Own a refrigerator 10. Own a landline phone 11. Own 2.5 acres or more of irrigated land with at least one irrigation equipment 12. 5 acres or more of irrigated land for two or more crop seasons 13. Owning at least 7.5 acres of land or more with at least one irrigation equipment. Beneficiary Registration Manual - https://pmayg.nic.in/netiayHome/Document/Document-PMAYG-Registratio-Manual.pdf There are four sections to the beneficiary registration process: Personal details, Bank account details, Convergence details, and Details from the concerned office. To successfully register or add the beneficiary, follow the steps given below: Visit the official website for login PMAY-G. Fill in the details required in the personal details section (such as gender, mobile number, Aadhaar number, etc.) Upload the consent form required to use the Aadhaar number. | H134: 1 | J134: =INT((ROW()-2)/50)+1 -> 3 | K134: =IF(H134="","Pending",IF(OR(H134="0",H134="1",H134="2",H134="U"),"Complete","Invalid")) -> Complete
A135: v2q-004-candidate-06 | B135: v2q-004 | C135: What is the maximum micro-loan amount stated for PMMY? | D135: PMMY facilitates micro-credit loans up to ₹20 lakh for eligible income-generating micro-enterprises. | E135: pilot-v2-doc-mgnrega-0002-bbbce5f319d4 | F135: Mahatma Gandhi National Rural Employment Guarantee Act | G135: before the Panchayat Secretary or Gram Rozgar Sahayak and make an oral request for registration, in which case the particulars required will be noted by the Gram Rojgar Sahayak or the Panchayat Secretary. Application for registration should contain names of those adult members of the household who are willing to do unskilled manual work. Particulars such as age, sex, SC/ST status, Rashtriya Swastha Bima Yojana (RSBY) number, Aadhar number, Below Poverty Line (BPL) status and bank/post office account number (if s/he has opened one) must be provided in the application. Step 2: The Gram Panchayat (GP) will verify the following details: Whether the household is really an entity as stated in the application. Whether the applicant household are local residents in the Gram Panchayat concerned. Whether applicants are adult members of the household. The process of verification shall be completed as early as possible, and in any case not later than a fortnight after the receipt of the application in the Gram Panchayat. Step 3: All particulars of a household found to be eligible after verification, will be entered in the MIS (NREGASoft) by the Panchayat Secretary or the Gram Rojgar Sahayak (GRS) or a person duly authorized by the State Government. Step 4: If a household is found to be eligible for registration, the GP will, within a fortnight of the application, issue a JC to the household. JC should be handed over to one of the members of the applicant household in the presence of a few other residents of the GP. The format of the Job Card is provided in the Annexure-5 of the scheme guidelines. The detailed format for application for registration is provided in Annexure-3 of the scheme guidelines. Registrations shall be opened throughout the year at the Gram Panchayat (GP) office. Application for registration | H135: 0 | J135: =INT((ROW()-2)/50)+1 -> 3 | K135: =IF(H135="","Pending",IF(OR(H135="0",H135="1",H135="2",H135="U"),"Complete","Invalid")) -> Complete
A136: v2q-019-candidate-12 | B136: v2q-019 | C136: What role does the Ministry of Petroleum and Natural Gas have in Ujjwala 2.0? | D136: The ministry introduced Ujjwala 2.0 to provide LPG connections and promote clean cooking fuel among poor, rural, and deprived households. | E136: pilot-v2-doc-pm-svanidhi-0000-f6024bb09ca5 | F136: PM Street Vendor’s AtmaNirbhar Nidhi (PM SVANidhi) | G136: PM Street Vendor’s AtmaNirbhar Nidhi (PM SVANidhi). Ministry Of Housing & Urban Affairs. Urban Local Bodies (ULBs) And Town Vending Committees (TVCs). The scheme &quot;PM Street Vendor’s AtmaNirbhar Nidhi (PM SVANidhi)&quot; by the Ministry of Housing and Urban Affairs, Government of India aims to formalize street vendors and enhance their economic opportunities through providing collateral-free working capital loans, interest subsidy, and digital transaction incentives to street vendors. It was launched on 1st June 2020 as a central sector scheme. The scheme supports vendors in restarting and expanding their businesses. It also promotes digital payments to increase financial inclusion. Street vendors include hawkers, thelewala, rehriwala, and others engaged in small-scale vending activities. The scheme aims to formalize the street vendors and open up new opportunities for this sector to move up the economic ladder. Street vendors represent a very important constituent of the urban informal economy and play a significant role in ensuring availability of the goods and services at affordable rates at the doorstep of the city dwellers. They are known as vendors, hawkers, thelewala, rehriwala, theliphadwala, etc. in different areas/ contexts. The goods supplied by them include vegetables, fruits, ready-to-eat street food, tea, pakodas, bread, eggs, textile, apparel, footwear, artisan products, books/ stationary, etc. The services include barber shops, cobblers, pan shops, laundry services, etc.. PM SVANidhi is a micro-credit scheme launched on 1st June 2020 by the MoHUA to provide handholding support to street vendors. The scheme facilitates a working capital collateral-free loan of ₹10,000, with subsequent loans of ₹20,000 and ₹50,000 with a 7% interest subsidy.. Working Capital Loan: 1st Tranche: Loan up to ₹15,000/-; repayment within 12 months. - 2nd Tranche: Loan up to ₹25,000/-; repayment within 18 months. - 3rd Tranche: Loan up to ₹50,000/-; repayment within 36 months. - Next tranche available on timely | H136: 0 | J136: =INT((ROW()-2)/50)+1 -> 3 | K136: =IF(H136="","Pending",IF(OR(H136="0",H136="1",H136="2",H136="U"),"Complete","Invalid")) -> Complete
A137: v2q-009-candidate-15 | B137: v2q-009 | C137: What does APY stand for, and what monthly pension range does it guarantee after age 60? | D137: APY stands for Atal Pension Yojana and offers guaranteed monthly pension options from ₹1,000 to ₹5,000 after age 60. | E137: pilot-v2-doc-pm-kmy-guidelines-0020-27037b9fe8a1 | F137: Pradhan Mantri Kisan Maan Dhan Yojana Operational Guidelines | G137: of such Nominee so long as such minority or disability continues. (e) If more than one Nominee is appointed and in such appointment the Subscriber has failed to specify their respective interest, the Nominees so named shall share equally. If any designated Nominee predeceases the Subscriber the interest of such Nominee shall terminate and his/her share shall be payable equally to such of the remaining Nominees as survive the Subscriber unless the Subscriber has made written request otherwise to the LIC in the prescribed form. 13 18. INTERPRETATION OF GUIDELINES: It shall be a condition of the membership of the Scheme that on any question arising on any point of interpretation of these Guidelines or any point relating to cessation of membership, the decision of the DAC&FW shall be final. 19. COORDINATION AMONG VARIOUS PARTICIPATING AGENCIES The DAC&FW has entered into detailed Memorandum of Understanding (MoUs) with various participating agencies for seamless implementation of the Scheme, namely, the LIC, the CSC-SPV, the NPCI, the IDBI and the IBA. These MoUs contained detailed roles and responsibilities of these agencies among themselves as well as towards smooth implementation of the Scheme. Further, the DAC&FW has also taken the key financial institutions / authorities, namely, the Department of Financial Services (DFS) under the Ministry of Finance, the Reserve Bank of India (RBI) and the Insurance Regulatory & Development Authority of India (IRDAI) on-board for successful operation of the Scheme. 20. REVIEW, MONITORING AND GRIEVANCE REDRESSAL MECHANISM a) An Empowered Committee under the Chairmanship of Cabinet Secretary with Secretaries of Agriculture & Farmers’ Welfare, MeiTY, Department of Expenditure, Department of Financial Services and any other Secretary concerned as members shall review and monitor implementation of the Scheme through appropriate implementation strategies and to approve any modifications in the Scheme within the within the overall | H137: 0 | J137: =INT((ROW()-2)/50)+1 -> 3 | K137: =IF(H137="","Pending",IF(OR(H137="0",H137="1",H137="2",H137="U"),"Complete","Invalid")) -> Complete
A138: v2q-022-candidate-10 | B138: v2q-022 | C138: Which finance programme relies on Member Lending Institutions to extend assistance to non-corporate micro-enterprises? | D138: Eligible Member Lending Institutions extend PMMY financial assistance and provide the scheme’s micro-loans to qualifying micro and small enterprises. | E138: pilot-v2-doc-pmegp-0000-7b958e1ec4b0 | F138: Prime Minister's Employment Generation Programme | G138: Prime Minister's Employment Generation Programme. Ministry Of Micro, Small and Medium Enterprises. Khadi And Village Industries Commission (KVIC). The &quot;Prime Minister’s Employment Generation Programme (PMEGP)&quot; is a credit-linked subsidy scheme launched in 2008 by the Ministry of Micro, Small, and Medium Enterprises (MSME). The scheme aims to generate employment opportunities by supporting the establishment of new micro-enterprises in both rural and urban areas. It promotes self-employment among traditional artisans, unemployed youth, and other eligible beneficiaries in the non-farm sector. PMEGP is being implemented by the Khadi and Village Industries Commission (KVIC) along with KVIBs, DICs, Coir Board, and banks. The scheme has been continued for the period 2021-22 to 2025-26 to support enterprise creation and sustainable livelihood generation across the country.. Launched in August 2008, Prime Minister's Employment Generation Programme (PMEGP) is a credit-linked subsidy scheme, administered by the Ministry of Micro, Small and Medium Enterprises (MSME). PMEGP aims to generate employment opportunities through the establishment of micro-enterprises in. Funds under PMEGP Scheme will be available under two major heads: 1. Margin Money Subsidy a) Funds will be allocated under annual Budget Estimates toward disbursement of Margin Money (subsidy) for setting up new micro-enterprises/units; and b) From the funds allocated under BE for the Margin Money subsidy, ₹ 100 Crores or as approved by the competent authority will be earmarked for each FY towards disbursement of Margin Money (subsidy) for the upgradation of existing PMEGP/REGP/MUDRA units. 2. Backward and Forward Linkages 5% of the total allocation under BE for a Financial Year against PMEGP, or as approved by the competent authority, shall be earmarked as funds under Backward and Forward Linkages and will be utilized for arranging awareness camps, State/District level monitoring meetings, Workshops, Exhibitions, Bankers meetings, TNDA, Publicity, Entrepreneurship Development Programme (EDP) training, Physical verification & Geo-tagging, Evaluation & | H138: 0 | J138: =INT((ROW()-2)/50)+1 -> 3 | K138: =IF(H138="","Pending",IF(OR(H138="0",H138="1",H138="2",H138="U"),"Complete","Invalid")) -> Complete
A139: v2q-018-candidate-16 | B139: v2q-018 | C139: Which initiative helps city households across officially defined lower and middle income bands obtain permanent homes? | D139: Pradhan Mantri Awas Yojana–Urban addresses urban housing shortages and supports eligible EWS, LIG, and MIG households, including slum dwellers. | E139: pilot-v2-doc-mgnrega-0001-5203a455caa6 | F139: Mahatma Gandhi National Rural Employment Guarantee Act | G139: entitled to a travel and subsistence allowance (10% of the minimum wage). Wages are paid within a week, or fifteen days at most. Men and Women are paid equally. Shade, drinking water, and first-aid are provided at every worksite. Exclusive measures for the promotion of the participation of the disabled persons: Identification of suitable works Mobilization of disabled persons by focussing on awareness and special provisions Specifically identified works for disabled persons in the case of large GPs Preference to appoint as mates and as workers for providing drinking water, to manage crèches, etc., at the worksites Adoption of tools and equipment/facilities at workplaces Treating persons with disabilities with respect Special drive to ensure 100 days of employment to such households Provide a special job card of a distinct color Specific attention and provisions for Senior Citizens: Exclusive senior citizen groups may be formed and special works which require lesser physical effort are identified and allotted to these groups. Specific attention and provisions for Internally Displaced Persons: A special job card to be provided will be valid till these families are displaced and will lose its validity as soon as they return to their original place of residence.. The applicant must be at least 18 years of age. The applicant must be residing in a Rural Area.. NA. Step 1: The application for registration may be given on plain paper to the local Gram Panchayat. An individual may appear personally before the Panchayat Secretary or Gram Rozgar Sahayak and make an oral request for registration, in which case the particulars required will be noted by the Gram Rojgar Sahayak or the Panchayat Secretary. Application for registration should contain names of those adult members of the household who are willing to do unskilled manual work. Particulars such as age, sex, SC/ST | H139: 0 | J139: =INT((ROW()-2)/50)+1 -> 3 | K139: =IF(H139="","Pending",IF(OR(H139="0",H139="1",H139="2",H139="U"),"Complete","Invalid")) -> Complete
A140: v2q-034-candidate-17 | B140: v2q-034 | C140: How do three programmes meet distinct household needs for rural housing, clean cooking, and food security? | D140: PMAY-G supports pucca rural housing with basic amenities; PMUY provides LPG access to deprived households replacing traditional cooking fuels; PMGKAY provides free foodgrains to eligible AAY and PHH ration-card holders. | E140: pilot-v2-doc-pmay-g-0000-d4162175877d | F140: Pradhan Mantri Awaas Yojana - Gramin | G140: Pradhan Mantri Awaas Yojana - Gramin. Ministry Of Rural Development. Department of Rural Development. Ministry Of Housing And Urban Affairs (MoHUA). Launch on 1st April 2016, Pradhan Mantri Awaas Yojana Gramin (PMAY-G) is centre's flagship mission by the Ministry of Rural Development (MoRD), implemented by the Ministry of Housing and Urban Affairs (MoHUA). PMAY-G aims at providing a pucca house, with basic amenities, to all houseless households and those households living in kutcha and dilapidated house. PMAY-G addresses the rural housing shortage and bridges the housing deficit in rural areas of India, contributing significantly to the mission of "Housing for All". The minimum size of the houses under PMAY-G is 25 sq m including a dedicated area for hygienic cooking. As of 27th Sept 2022, 2.00 crore houses have been constructed out of the total target of 2.72 crores. The beneficiaries are identified using the Socio-Economic and Caste Census (SECC) parameters and verified by the Gram Sabhas. The amount is transferred directly to the Aadhaar-Linked Bank Account / Post-Office Account of the beneficiary. PMAY-G has been extended for another two years, i.e. till 31st March 2024. Aim and Objective: PMAY-G aims to provide a pucca house with basic amenities to all houseless households and households living in kutcha and dilapidated house in rural areas by 2024. The immediate objective is to cover 1.00 Crore households in rural areas, that are houseless or living in kutcha / dilapidated house, in three years from 2016-17 to 2018-19 and enable construction of quality houses by the beneficiaries using local materials, designs and trained masons. For houses to become homes, adoption of a habitat approach through convergence is proposed.. Launch on 1st April 2016, Pradhan Mantri Awaas Yojana Gramin (PMAY-G) is centre's flagship mission by the Ministry of Rural Development (MoRD), implemented by the | H140: 2 | J140: =INT((ROW()-2)/50)+1 -> 3 | K140: =IF(H140="","Pending",IF(OR(H140="0",H140="1",H140="2",H140="U"),"Complete","Invalid")) -> Complete
A141: v2q-007-candidate-23 | B141: v2q-007 | C141: What is the full form of PMJJBY, and which event does its life insurance cover? | D141: PMJJBY stands for Pradhan Mantri Jeevan Jyoti Bima Yojana and provides life-insurance cover for death due to any reason. | E141: pilot-v2-doc-apy-0003-68e7199c9d14 | F141: Atal Pension Yojana | G141: can also open an APY account online using one's Net banking facility. The applicant can login into his/her internet banking account and search for APY on dashboard. Customer has to fill basic and Nominee details. Customer has to give consent for auto debit of premium from the account and submit the form. Process 2: Visit website “https://enps.nsdl.com/eNPS/NationalPensionSystem.html “ and select “Atal Pension Yojana”. Select “APY Registration” Fill the basic details in the form. One can complete KYC through 3 options – Offline KYC – Where one has to upload XML file of Aadhaar Aadhaar – Where KYC is done through OTP verification on Mobile Number register with Aadhaar Virtual ID – Where Aadhaar virtual ID is created for KYC Citizen can select either one of three options. Once the basic details are filled, an acknowledgement number is generated. Citizen then has to fill personal details and decide the pension amount he/she wants after 60 years. The Citizen also has to decide the frequency of contribution for the scheme. Once the citizen “confirms” for personal details, he/she has to then fill nominee details. After submitting the personal and Nominee details, Citizen is redirected to NSDL website for eSign. Once Aadhaar is OTP verified, Citizen gets successfully registered in APY. One can also join digitally through e-APY portal or through web portal of banks providing such facility. Visit website “https://enps.nsdl.com/eNPS/NationalPensionSystem.html “ and select “Atal Pension Yojana”. Helpline Number - - Toll Free Helpline number for APY Scheme is 1800-110-069. One can visit the nearest Bank branch or Post Office where he/ she is having a saving bank account and submit the APY registration form for opening the APY account. | H141: 0 | J141: =INT((ROW()-2)/50)+1 -> 3 | K141: =IF(H141="","Pending",IF(OR(H141="0",H141="1",H141="2",H141="U"),"Complete","Invalid")) -> Complete
... A156: v2q-020-candidate-02 | B156: v2q-020 | C156: How do NSDC and SPIAs divide responsibility in the Special Projects arm of the national skill mission? | D156: NSDC supports the ministry’s implementation, while Special Projects Implementing Agencies deliver the projects on the ground. | E156: pilot-v2-doc-pm-janman-0002-d0844e3327b6 | F156: PM Janjati Adivasi Nyaya Maha Abhiyan (PM JANMAN) | G156: physical survey conducted by state governments using the mobile application on the PM Gati-shakti Portal. Eligibility Specific to Interventions The applicant household seeking a pucca house must currently reside in a kaccha house. The applicant household seeking solar power solutions must be an unelectrified household not covered under the Revamped Distribution Sector Scheme (RDSS). The applicant household seeking an on-grid electricity connection shall be an identified beneficiary household under PM-JANMAN, irrespective of standard eligibility criteria under the Revamped Distribution Sector Scheme (RDSS) for the State and Electricity distribution company (DISCOM).. Step 1: Initiation of Identification and Physical Survey The State Governments initiates a detailed physical survey of each Particularly Vulnerable Tribal Group habitation to ascertain the gaps regarding the 11 critical interventions covered under the mission. The data gathered during this exhaustive survey is simultaneously updated and cross-verified on a mobile application developed on the PM Gati-shakti Portal. Step 2: Facilitation of Application Filing for Eligible Beneficiaries The Block Level Implementation Team, consisting of officers designated by the District Collector, will be responsible for identifying each beneficiary family who has not yet been saturated with entitlements and will facilitate the necessary application filing for the respective schemes. The District Level Committee is also responsible for the registration and filling of applications of eligible beneficiaries for each scheme covered under the mission. Step 3: Verification and Project Approval Following the application filing and preliminary eligibility checks, certain proposals for infrastructure, such as the sanctioning of Multi-Purpose Centers, must be forwarded by the Secretary/Principal Secretary, State Tribal Welfare Department to the Ministry of Tribal Affairs. These proposals are subsequently examined by the relevant division, approved by the Mission Director of PM-JANMAN, and granted financial concurrence by the Internal Finance Division. | H156: 0 | J156: =INT((ROW()-2)/50)+1 -> 4 | K156: =IF(H156="","Pending",IF(OR(H156="0",H156="1",H156="2",H156="U"),"Complete","Invalid")) -> Complete
A157: v2q-033-candidate-07 | B157: v2q-033 | C157: How do three programmes support micro-enterprises, new enterprise creation, and street-vendor livelihoods through different financial mechanisms? | D157: PMMY provides micro-credit to eligible micro-enterprises; PMEGP uses a credit-linked subsidy to establish new micro-enterprises; PM SVANidhi provides street vendors collateral-free working-capital loans, interest subsidy, and digital-payment incentives. | E157: pilot-v2-doc-pmegp-0001-f900b4f4f97a | F157: Prime Minister's Employment Generation Programme | G157: Linkages 5% of the total allocation under BE for a Financial Year against PMEGP, or as approved by the competent authority, shall be earmarked as funds under Backward and Forward Linkages and will be utilized for arranging awareness camps, State/District level monitoring meetings, Workshops, Exhibitions, Bankers meetings, TNDA, Publicity, Entrepreneurship Development Programme (EDP) training, Physical verification & Geo-tagging, Evaluation & impacts Assessment study, Setting of Entrepreneurship Facilitation Centre (EFC), Center of Excellence (CoE), Engagement of Field Experts and Data Entry Operators (DEOs), Creation and Upgradation of IT infrastructure, Awards, Call Centre facility, PMU, and other related activities and settlement of other residual liabilities by the KVIC. Levels of support under PMEGP 1. For setting up new micro-enterprise (units) a) Categories of beneficiaries under PMEGP (for setting up of new enterprises): General Category Beneficiary's contribution (of project cost): 10% Rate of Subsidy (of project cost): 15% for Urban Areas, 25% for Rural Areas. b) Categories of beneficiaries under PMEGP (for setting up of new enterprises): Special Category (including SC, ST, OBC, Minorities, Women, Ex-Servicemen, Transgenders, Differently abled, NER, Aspirational Districts, Hill and Border areas(as notified by the Government), etc. (i) Beneficiary's contribution (of project cost): 05% (ii) Rate of Subsidy (of project cost): 25% for Urban Areas, 35% for Rural Areas. Note: The maximum cost of the project/unit admissible for Margin Money subsidy under the Manufacturing sector is ₹50,00,000. The maximum cost of the project/unit admissible for the Margin Money subsidy under the Business/Service sector is ₹20,00,000. The balance amount (excluding the own contribution)of the total project cost will be provided by Banks. If the total project cost exceeds ₹50,00,000 or ₹20,00,000 for Manufacturing and Service/Business sector respectively, the balance amount may be provided by Banks without any Government subsidy. 2. 2nd Loan for Upgradation of Existing PMEGP / REGP / | H157: 1 | I157: PMEGP linkage funds for awareness/monitoring — correct scheme but not credit-linked subsidy mechanism. | J157: =INT((ROW()-2)/50)+1 -> 4 | K157: =IF(H157="","Pending",IF(OR(H157="0",H157="1",H157="2",H157="U"),"Complete","Invalid")) -> Complete
A158: v2q-001-candidate-12 | B158: v2q-001 | C158: What is the minimum house size specified under PMAY-G? | D158: The minimum house size is 25 square metres, including a dedicated hygienic cooking area. | E158: pilot-v2-doc-apy-0000-c43dd88d7899 | F158: Atal Pension Yojana | G158: Atal Pension Yojana. Ministry Of Finance. Department of Financial Service. Banks. Atal Pension Yojana (APY) is an old age income security scheme for a savings account holder in the age group of 18-40 years who is not an income tax-payee. The scheme helps in addressing the longevity risks among the workers in the unorganized sector and encourages the workers to voluntarily save for their retirement. Focus of APY The scheme is mainly targeted at the poor, the under-privileged and workers in the unorganized sector. APY Subscriber Contribution Chart - https://www.npscra.nsdl.co.in/nsdl/scheme-details/APYSubscribersContributionChart1.pdf Charges and fees and overdue interest under APY: The charges and fees and the overdue interest for non-payment or delayed payment of prescribed contribution amount shall be levied on the subscribers of APY. These charges and their method of application shall be prescribed by PFRDA from time to time, in consultation with the Central Government. Raising Grievance Under APY A subscriber can raise grievance anytime free of cost from anywhere by visiting: www.npscra.nsdl.co.in &gt;&gt;Home &gt;&gt; select: NPS-Lite or through CGMS Subscriber raising the grievance will be allotted a token number against the grievance raised. Subscriber may check the status of the grievance under “Check the status of Grievance / Enquiry already registered”.. Atal Pension Yojana (APY) is an old age income security scheme for a savings account holder in the age group of 18-40 years, who is not an income tax-payee. It helps to address longevity risks among workers in unorganized sector and encourages the workers to voluntarily save for retirement.. Upon exit on attaining 60 years The subscriber shall receive the following three benefits on attaining the age of 60: (i) Guaranteed minimum pension amount: Each subscriber under APY shall receive a guaranteed minimum pension of Rs. 1000/- per month or Rs. 2000/- per month or Rs. 3000/- per | H158: 0 | J158: =INT((ROW()-2)/50)+1 -> 4 | K158: =IF(H158="","Pending",IF(OR(H158="0",H158="1",H158="2",H158="U"),"Complete","Invalid")) -> Complete
A159: v2q-004-candidate-21 | B159: v2q-004 | C159: What is the maximum micro-loan amount stated for PMMY? | D159: PMMY facilitates micro-credit loans up to ₹20 lakh for eligible income-generating micro-enterprises. | E159: pilot-v2-doc-pmmy-0002-526833661bcb | F159: Pradhan Mantri Mudra Yojana | G159: need for educational qualification, if any, is assessed based on the nature of the proposed activity and its requirement.. The following are the pre-requisites for the enrolment process: ID Proof Address Proof Passport size photograph Applicant Signature Proof of Identity / Address of Business Enterprises Step 01: Go to PM MUDRA official website and after that select the Udyamimitra portal Step 02: Click on Mudra loan "Apply Now" Step 03: Select one of the following : New entrepreneur/ Existing Entrepreneur/Self-employed professional Step 04: Then fill in the name of the applicant, email and Mobile number and Generate OTP After Successful Registration Step 01: Fill in Personal Details and Professional Details. Step 02: Select hand-holding agencies if any help is required for preparing project proposals etc., otherwise click &quot;Loan Application Center&quot; and apply. Step 03: Select the category of loan required - Mudra Shishu / Mudra Kishore/ Mudra Tarun. Step 04: The applicant then needs to fill in the Business Information like business name, business activity, etc. and select industry type like Manufacturing, Service, Trading or activities allied to agriculture. Step 05: Fill in other information like owner details, existing Banking/ Credit facilities, proposed credit facilities, future estimates and preferred lender. Step 06: Attach all required Documents i.e. ID proof, Address proof, Applicant photo, Applicant Signature, Proof of Identity/ Address of Business Enterprise, etc. Step 07: Once the application is submitted, an Application Number gets generated which needs to be kept for future reference. | H159: 1 | J159: =INT((ROW()-2)/50)+1 -> 4 | K159: =IF(H159="","Pending",IF(OR(H159="0",H159="1",H159="2",H159="U"),"Complete","Invalid")) -> Complete
A160: v2q-029-candidate-07 | B160: v2q-029 | C160: What migrant-focused facility distinguishes Ujjwala 2.0, and what clean-cooking transition was established by its predecessor programme? | D160: Ujjwala 2.0 added 1.6 crore LPG connections with a special facility for migrant households. Its predecessor, Pradhan Mantri Ujjwala Yojana, sought to replace traditional cooking fuels with LPG access for rural and deprived households. | E160: pilot-v2-doc-pmuy2-0002-61d762b2cd43 | F160: Pradhan Mantri Ujjwala Yojana 2.0 | G160: account information, and LPG distributor preference. Step 3: Attach the necessary documents along with the application form. The documents typically include proof of identity, proof of address, and proof of BPL category. Step 4: Submit the completed application form along with the supporting documents to the nearest LPG distributor.. Step 1: Apply online for Pradhan Mantri Ujjwala Yojana 2.0 from the official website. Step 2: Select the option Apply for the New Ujjwala 2.0 Connection. Step 3: Scroll down to and click on Online Portal. and Select the LPG distribution company name example Indane / Bharatgas / HP Gas. Step 4: Click on Register Now on the selected LPG distribution company. Step 5: Select a type of Connection like Ujjwala 2.0 New Connection. Step 6: Choose the State, District, Pin Code, and Name of the Distributor. Then Enter your Mobile Number, Captcha, and OTP. Step 7: Select the type of KYC New KYC and Normal KYC. Step 8: Select Migrant Family status in YES or NO Step 9: For the family Identifier in NO fill in Annexure 1 Step 10: For family Identifier in Yes fill in Ration Card Step 11: Fill in all Family Details, Personal details, address details, bank details, Choose Cylinder Types, Select rural or urban and select the declaration and submit. Step 12: Generate the Reference number and Print your applied form attach all the documents you submitted online and visit the selected Gas agency. | H160: 1 | I160: PMUY-2 application steps (document submission) — correct scheme, no migrant facility or predecessor LPG transition. | J160: =INT((ROW()-2)/50)+1 -> 4 | K160: =IF(H160="","Pending",IF(OR(H160="0",H160="1",H160="2",H160="U"),"Complete","Invalid")) -> Complete
A161: v2q-015-candidate-15 | B161: v2q-015 | C161: Which initiative helps job-seekers and established craftspeople launch small businesses outside agriculture? | D161: The Prime Minister's Employment Generation Programme supports new micro-enterprises to create self-employment for traditional artisans, unemployed youth, and other eligible beneficiaries. | E161: pilot-v2-doc-pmmy-0000-70a89ee32765 | F161: Pradhan Mantri Mudra Yojana | G161: Pradhan Mantri Mudra Yojana. Ministry Of Finance. Department of Financial Service. Member Lending Institutions - Bank Or A Micro Finance Institution (MFI) / Non-Banking Finance Company (NBFC) / Other Financial Intermediary. Pradhan Mantri Mudra Yojana (PMMY) is a flagship scheme of Government of India. The scheme facilitates micro credit/Loan up to Rs. 20 lakhs to income generating micro enterprises engaged in the non farm sector in manufacturing, trading or service sectors including activities allied to agriculture such as poultry, dairy, beekeeping, etc. The Scheme provides financial assistance extended by Member Lending Institutions to the non-corporate, non-farm sector income generating activities of micro and small entities. These micro and small entities comprise of millions of proprietorship / partnership firms running as small manufacturing units, service sector units, shopkeepers, fruits / vegetable vendors, truck operators, food-service units, repair shops, machine operators, small industries, artisans, food processors and others. The loans under Pradhan Mantri Mudra Yojana can be availed through eligible Member Lending Institutions (MLIs), which include: Public Sector Banks Private Sector Banks State operated cooperative banks Rural banks from regional sector Micro Finance Institution (MFI) Non-Banking Finance Company (NBFC) Small Finance Banks (SFBs) Other financial intermediary approved by Mudra Ltd. as member financial institutions Interest rate The interest rates are declared by Member Lending Institutions from time to time as per Reserve Bank of India guidelines based on which applicable interest rate is determined. Upfront fee/Processing charges Banks may consider charging of upfront fee as per their internal guidelines. The upfront fee/processing charges for Shishu loans (Covering loans upto Rs. 50,000/-) are waived by most Banks. Note : There are no agents or middleman engaged by MUDRA for availing of Mudra Loans. The borrowers are advised to keep away from persons posing as Agents/ facilitators of MUDRA/PMMY.. Pradhan Mantri Mudra Yojana (PMMY) | H161: 0 | J161: =INT((ROW()-2)/50)+1 -> 4 | K161: =IF(H161="","Pending",IF(OR(H161="0",H161="1",H161="2",H161="U"),"Complete","Invalid")) -> Complete
A162: v2q-006-candidate-07 | B162: v2q-006 | C162: What annual hospitalisation cover does AB-PMJAY provide per eligible family? | D162: AB-PMJAY provides cashless hospitalisation cover of ₹5 lakh per family per year for secondary and tertiary healthcare. | E162: pilot-v2-doc-pmegp-0003-43256e8e6645 | F162: Prime Minister's Employment Generation Programme | G162: sector and above ₹ 5,00,000 in the Business /Service sector, the beneficiaries should possess at least VIII standard pass educational qualification. Assistance under the scheme is available only for new projects sanctioned specifically under the PMEGP. Existing Units (under PMRY, REGP, or any other scheme of the Government of India or State Government) and the units that have already availed of Government Subsidy under any other scheme of the Government of India or State Government are not eligible. For up-gradation of existing PMEGP / REGP / MUDRA units Margin Money(subsidy)claimed under PMEGP has to be successfully adjusted on the completion of the lock-in period of 3 years. The first loan under PMEGP/REGP/MUDRA has to be successfully repaid in the stipulated time. The unit is profit-making with good turnover and has the potential for further growth in turnover and profit with modernization/upgrading of the technology. Reservation / Preference / Priority Priority will be given to the persons affected by natural calamities/disasters in the areas which are declared as affected by "disaster" as defined under Section 2(d) of the Disaster Management Act, 2005 by the Ministry of Home Affairs.. For PMEGP new enterprises (Units): Existing Units (under PMRY, REGP, or any other scheme of the Government of India or State Government) and the units that have already availed of Government Subsidy under any other scheme of the Government of India or State Government are not eligible. Only one person from one family is eligible for obtaining financial assistance for setting up of projects under PMEGP. The 'family’ includes self and spouse. Negative List of Activities: The following list of activities will not be permitted under PMEGP for setting up of micro enterprises/ projects/units:- Any Industry/ Business connected with Meat(slaughtered), i.e., processing, canning and/or serving items made of it as food, production/Manufacturing or | H162: 0 | J162: =INT((ROW()-2)/50)+1 -> 4 | K162: =IF(H162="","Pending",IF(OR(H162="0",H162="1",H162="2",H162="U"),"Complete","Invalid")) -> Complete
A163: v2q-006-candidate-21 | B163: v2q-006 | C163: What annual hospitalisation cover does AB-PMJAY provide per eligible family? | D163: AB-PMJAY provides cashless hospitalisation cover of ₹5 lakh per family per year for secondary and tertiary healthcare. | E163: pilot-v2-doc-pmuy-0001-5fd4d0cd2135 | F163: Pradhan Mantri Ujjwala Yojana | G163: Rs. 1150 for a 5 kg cylinder. Additionally, All PMUY beneficiaries will be provided with first LPG refill and Stove (hot plate) both free of cost along with their deposit free connection. Note: Priority would be given to the states which have lower LPG coverage (Compared to the national average) as on 1st Jan 2016.. An adult woman belonging to a poor household and not having an LPG connection in her household will be eligible under UJJWALA 2.0. The beneficiaries should belong to any of the following categories: Eligible as per SECC 2011 list Belongs to SC/ST households, be a beneficiary of Pradhan Mantri Awas Yojana (PMAY), Antyodaya Anna Yojana (AAY), Forest dwellers, Most Backward Classes (MBC), Tea and Ex-Tea Garden Tribes, People residing in river islands (Beneficiary will submit supporting document) If she is not falling in the above 2 categories, then she can stake her claim to be a beneficiary under Poor household by submitting 14-point declaration (as per prescribed format). Male Member from a household cannot apply for the scheme.. Following are the prerequisites for the enrollment process: Aadhar Card Ration card Address Proof Passport size photograph Bank Details Apply the application form through online official website. 1. Select the oil company name example Indane / Bharatgas / HP Gas Select Type of Connection like Ujjwala 2.0 New Connection Choose State, District and Name of Distributor. Enter Mobile Number, Captcha and OTP. Select Migrant Family status in YES or NO For family Identifier in NO fill Annexure 1 For family Identifier in Yes fill Ration Card Select Category. Fill all Family Details, Personal details, address details, bank details, Choose Cylinder Types, Select rural or urban and select declaration and submit. Generate Reference number and visit Gas agency. | H163: 0 | J163: =INT((ROW()-2)/50)+1 -> 4 | K163: =IF(H163="","Pending",IF(OR(H163="0",H163="1",H163="2",H163="U"),"Complete","Invalid")) -> Complete
A164: v2q-029-candidate-01 | B164: v2q-029 | C164: What migrant-focused facility distinguishes Ujjwala 2.0, and what clean-cooking transition was established by its predecessor programme? | D164: Ujjwala 2.0 added 1.6 crore LPG connections with a special facility for migrant households. Its predecessor, Pradhan Mantri Ujjwala Yojana, sought to replace traditional cooking fuels with LPG access for rural and deprived households. | E164: pilot-v2-doc-pmuy2-0000-95fa2d4e3b3f | F164: Pradhan Mantri Ujjwala Yojana 2.0 | G164: Pradhan Mantri Ujjwala Yojana 2.0. Ministry Of Petroleum and Natural Gas. The Pradhan Mantri Ujjwala Yojana 2.0 (PMUY) was launched in May 2016 by the Ministry of Petroleum and Natural Gas to provide free LPG connections to women from poor households. Its main objective is to promote clean cooking fuel like LPG among rural and deprived families who traditionally rely on firewood, coal, or cow-dung cakes. This shift helps reduce health risks for women and minimizes environmental pollution. Under PMUY 2.0, the scheme was further expanded to reach more beneficiaries across India. The target under the scheme was to release 8 Crore LPG Connections to the deprived households by March 2020. On 7th September 2019, the Hon’ble Prime Minister of India handed over the 8th Crore LPG connection in Aurangabad, Maharashtra. The release of 8 Crore LPG connections under the scheme has also helped in increasing the LPG coverage from 62% on 1st May 2016 to 99.8% on 1st April 2021. Ujjwala 2.0: Additional allocation of 1.6 Crore LPG Connections under PMUY Scheme with special facility to migrant households. The scheme was launched in Mahoba, Uttar Pradesh by the Hon’ble Prime Minister of India, Shri. Narendra Modi.. Ministry of Petroleum and Natural Gas (MOPNG), introduced the ‘"Pradhan Mantri Ujjawala Yojana 2.0" in India. The Pradhan Mantri Ujjawala Yojana (PMUY) is a scheme launched by the Government of India in 2016 to provide free LPG (liquefied petroleum gas) connections to women from below-poverty-line.. Cash assistance for PMUY connections is provided by the Government of India - ₹1600 (for a connection 14.2kg cylinder/ ₹1150 for a 5 kg cylinder). The cash assistance covers: Security Deposit of Cylinder – ₹1250 for 14.2 kg cylinder/ ₹ 800 for 5 kg cylinder. Pressure Regulator – ₹150. LPG Hose – ₹100. Domestic Gas Consumer Card – | H164: 2 | J164: =INT((ROW()-2)/50)+1 -> 4 | K164: =IF(H164="","Pending",IF(OR(H164="0",H164="1",H164="2",H164="U"),"Complete","Invalid")) -> Complete
A165: v2q-024-candidate-09 | B165: v2q-024 | C165: Which national health-assurance programme does NHA implement under the health ministry? | D165: The National Health Authority implements AB-PMJAY under the Ministry of Health and Family Welfare. | E165: pilot-v2-doc-pm-janman-0000-69ac65d10edc | F165: PM Janjati Adivasi Nyaya Maha Abhiyan (PM JANMAN) | G165: PM Janjati Adivasi Nyaya Maha Abhiyan (PM JANMAN). Ministry Of Tribal Affairs. The scheme “PM- Janjati Adivasi Nyaya Maha Abhiyan (PM JANMAN)” was launched by the Ministry of Tribal Affairs, Government of India, aims to improve the socio-economic status of Particularly Vulnerable Tribal Groups (PVTGs) by bridging gaps in health, education, and livelihoods, and by saturating PVTG communities and families with basic facilities and services. The scheme provides 11 critical interventions through nine line Ministries/Departments, focusing on ensuring access to pucca houses, safe drinking water, road and mobile connectivity, electricity, and vocational education for individual households and habitations. A unique aspect is the inter-ministerial convergence, with the Ministry of Tribal Affairs serving as the nodal ministry while each participating ministry implements its respective Central Sector and Centrally Sponsored schemes.. The scheme aims to improve the socio-economic status of PVTGs by saturating families and habitations with basic facilities and services. It provides 11 critical infrastructure and welfare interventions, including housing, water, electricity, and connectivity.. Housing Provision of pucca houses to all eligible Particularly Vulnerable Tribal Group households having kaccha houses (Target: 4,90,000 households). The basic unit cost of the house is enhanced to ₹2,00,000/-, with additional facilities raising it to ₹2,39,000/-. Road Connectivity Construction of connecting roads (Target: 8,000 KM) linking approximately 6,500 Particularly Vulnerable Tribal Group villages. The construction cost per Kilometer would be ₹1,00,00,000/-. Drinking Water Provision of piped water supply/Functional Household Tap Connection (FHTC) to all Particularly Vulnerable Tribal Group households. Community water supply will be provided to villages/habitations with a population of less than 20 households. Health Deployment of Mobile Medical Units (MMUs) (Target: 1,000 MMUs) in Particularly Vulnerable Tribal Group habitations/villages. The cost is ₹33,88,000/- per MMU per annum, with Operational Expenditure (Op Ex) as per norms. Education Hostels Construction of residential hostels (Target: 500 hostels) | H165: 0 | J165: =INT((ROW()-2)/50)+1 -> 4 | K165: =IF(H165="","Pending",IF(OR(H165="0",H165="1",H165="2",H165="U"),"Complete","Invalid")) -> Complete
A166: v2q-029-candidate-05 | B166: v2q-029 | C166: What migrant-focused facility distinguishes Ujjwala 2.0, and what clean-cooking transition was established by its predecessor programme? | D166: Ujjwala 2.0 added 1.6 crore LPG connections with a special facility for migrant households. Its predecessor, Pradhan Mantri Ujjwala Yojana, sought to replace traditional cooking fuels with LPG access for rural and deprived households. | E166: pilot-v2-doc-pm-janman-0000-69ac65d10edc | F166: PM Janjati Adivasi Nyaya Maha Abhiyan (PM JANMAN) | G166: PM Janjati Adivasi Nyaya Maha Abhiyan (PM JANMAN). Ministry Of Tribal Affairs. The scheme “PM- Janjati Adivasi Nyaya Maha Abhiyan (PM JANMAN)” was launched by the Ministry of Tribal Affairs, Government of India, aims to improve the socio-economic status of Particularly Vulnerable Tribal Groups (PVTGs) by bridging gaps in health, education, and livelihoods, and by saturating PVTG communities and families with basic facilities and services. The scheme provides 11 critical interventions through nine line Ministries/Departments, focusing on ensuring access to pucca houses, safe drinking water, road and mobile connectivity, electricity, and vocational education for individual households and habitations. A unique aspect is the inter-ministerial convergence, with the Ministry of Tribal Affairs serving as the nodal ministry while each participating ministry implements its respective Central Sector and Centrally Sponsored schemes.. The scheme aims to improve the socio-economic status of PVTGs by saturating families and habitations with basic facilities and services. It provides 11 critical infrastructure and welfare interventions, including housing, water, electricity, and connectivity.. Housing Provision of pucca houses to all eligible Particularly Vulnerable Tribal Group households having kaccha houses (Target: 4,90,000 households). The basic unit cost of the house is enhanced to ₹2,00,000/-, with additional facilities raising it to ₹2,39,000/-. Road Connectivity Construction of connecting roads (Target: 8,000 KM) linking approximately 6,500 Particularly Vulnerable Tribal Group villages. The construction cost per Kilometer would be ₹1,00,00,000/-. Drinking Water Provision of piped water supply/Functional Household Tap Connection (FHTC) to all Particularly Vulnerable Tribal Group households. Community water supply will be provided to villages/habitations with a population of less than 20 households. Health Deployment of Mobile Medical Units (MMUs) (Target: 1,000 MMUs) in Particularly Vulnerable Tribal Group habitations/villages. The cost is ₹33,88,000/- per MMU per annum, with Operational Expenditure (Op Ex) as per norms. Education Hostels Construction of residential hostels (Target: 500 hostels) | H166: 0 | J166: =INT((ROW()-2)/50)+1 -> 4 | K166: =IF(H166="","Pending",IF(OR(H166="0",H166="1",H166="2",H166="U"),"Complete","Invalid")) -> Complete
A167: v2q-018-candidate-05 | B167: v2q-018 | C167: Which initiative helps city households across officially defined lower and middle income bands obtain permanent homes? | D167: Pradhan Mantri Awas Yojana–Urban addresses urban housing shortages and supports eligible EWS, LIG, and MIG households, including slum dwellers. | E167: pilot-v2-doc-ab-pmjay-0001-a632a7205efc | F167: Ayushman Bharat - Pradhan Mantri Jan Arogya Yojana | G167: per family per year for secondary and tertiary hospitalization to poor and vulnerable families.. AB PM-JAY is a health insurance scheme for low-income families in rural and urban areas. The scheme aims to provide affordable healthcare facilities to the Poor. It is the largest health assurance scheme in the world which aims at providing a health cover of ₹5,00,000/- per family per year.. Financial Health Insurance Cover: Annual Hospitalization Coverage: Cashless coverage up to ₹5,00,000/- per family per year.- Comprehensive Treatment Costs: Covers consultation, medicines, diagnostics, surgery, ICU, implants, accommodation, and food.- Pre and Post Hospitalization Support: Covers 3 days pre-hospitalization and 15 days post-hospitalization expenses.- Treatment Complication Coverage: Covers complications arising during treatment. Coverage Features: Pre-Existing Disease Coverage: Covers all pre-existing diseases from day one.- No Family Size Limit: No restriction on age, gender, or family size.- Nationwide Portability: Benefits available across India in empanelled hospitals.- Wide Procedure Coverage: Covers approximately 1,929 medical procedures.. Rural Beneficiaries Out of the total seven deprivation criteria for rural areas, PM-JAY covered all such families who fall into at least one of the following six deprivation criteria and automatic inclusion(Destitute/ living on alms, manual scavenger households, primitive tribal group, legally released bonded labour) criteria: Only one room with kucha walls and kucha roof No adult member between ages 16 to 59 Households with no adult male member between ages 16 to 59 Disabled member and no able-bodied adult member SC/ST households Landless households deriving a major part of their income from manual casual labour Automatically includedHouseholds without shelter Destitute/ living on alms, Manual scavenger families, Primitive tribal groups, Legally released bonded labour. Urban Beneficiaries For urban areas, the following 11 occupational categories of workers are eligible for the scheme: Ragpicker Beggar Domestic worker Street vendor/ Cobbler/hawker / other service provider working on streets | H167: 0 | J167: =INT((ROW()-2)/50)+1 -> 4 | K167: =IF(H167="","Pending",IF(OR(H167="0",H167="1",H167="2",H167="U"),"Complete","Invalid")) -> Complete
