Workbook

Sheet Judging
A1: display_id | B1: query_id | C1: question | D1: reference_answer | E1: chunk_id | F1: source_document_title | G1: candidate_chunk | H1: relevance_grade | I1: rationale | J1: batch | K1: status
A2: v2q-001-candidate-19 | B2: v2q-001 | C2: What is the minimum house size specified under PMAY-G? | D2: The minimum house size is 25 square metres, including a dedicated hygienic cooking area. | E2: pilot-v2-doc-pm-gkay-0000-c29b96f46a80 | F2: Pradhan Mantri Garib Kalyan Anna Yojana | G2: Pradhan Mantri Garib Kalyan Anna Yojana. Ministry Of Finance. Department Of Economic Affairs. The scheme "Pradhan Mantri Garib Kalyan Anna Yojana (PMGKAY)" has been launched by the Department of Food and Public Distribution, Ministry of Consumer Affairs, Food and Public Distribution, Government of India, and aims to ensure food security for the poor and vulnerable sections of the country by providing free food foodgrains. It was announced on 26 March 2020 during the COVID-19 pandemic and is operated by the Department of Food and Public Distribution under the Ministry of Consumer Affairs, Food and Public Distribution. Through this scheme, free foodgrains (rice or wheat, depending on the State) are provided to eligible ration card holders covered under the National Food Security Act, 2013, namely Antyodaya Anna Yojana (AAY) households and Priority Households (PHH). From 1 January 2023, the scheme was integrated into the food security framework, and foodgrains earlier given at the highly subsidised rates of ₹1, ₹2, and ₹3 per kilogram for coarse cereals, wheat, and rice, respectively, are now provided free of cost. The scheme has been extended by the Union Cabinet for 5 years starting from 1 January 2024 and is approved for continuation till 31 December 2028, with a total financial outlay of ₹11.80 lakh crore (₹11,80,000 crore). The scheme is implemented through the Targeted Public Distribution System (TPDS) by the state governments and Union Territory Administrations, with foodgrain allocation by the Government of India.. The scheme aims to ensure food security for the poor. Through this scheme, free foodgrains are provided to eligible ration card holders under the National Food Security Act, 2013.. Antyodaya Anna Yojana (AAY) families receive 35 kilograms of foodgrains per family per month. Priority Household (PHH) beneficiaries receive 5 kilograms of foodgrains per person per month. The foodgrains are provided as | H2: 0 | J2: =INT((ROW()-2)/50)+1 | K2: =IF(H2="","Pending",IF(OR(H2="0",H2="1",H2="2",H2="U"),"Complete","Invalid"))
A3: v2q-004-candidate-10 | B3: v2q-004 | C3: What is the maximum micro-loan amount stated for PMMY? | D3: PMMY facilitates micro-credit loans up to ₹20 lakh for eligible income-generating micro-enterprises. | E3: pilot-v2-doc-pmegp-0002-f67d4c730011 | F3: Prime Minister's Employment Generation Programme | G3: under the Business/Service sector is ₹20,00,000. The balance amount (excluding the own contribution)of the total project cost will be provided by Banks. If the total project cost exceeds ₹50,00,000 or ₹20,00,000 for Manufacturing and Service/Business sector respectively, the balance amount may be provided by Banks without any Government subsidy. 2. 2nd Loan for Upgradation of Existing PMEGP / REGP / MUDRA Units a) Categories of beneficiaries under PMEGP (for upgradation of existing units): All Categories b) Beneficiary's contribution (of project cost): 10% c) Rate of Subsidy (of project cost): 15% (20% in NER and Hill States). Note: The maximum cost of the project/unit admissible for Margin Money subsidy under the Manufacturing sector for upgradation is ₹10,00,00,000. The maximum subsidy would be ₹15,00,000 (₹20,00,000 for NER and Hill States). The maximum cost of the project/unit admissible for Margin Money subsidy under the Business/Service sector for upgradation is ₹25,00,000. The maximum subsidy would be ₹3,75,000 (₹5,00,000 for NER and Hill States). The balance amount (excluding the own contribution)of the total project cost will be provided by Banks. If the total project cost exceeds ₹10,00,00,000 or ₹25,00,000 for Manufacturing and Service/Business sector respectively, the balance amount may be provided by banks without any Government subsidy.. For PMEGP new enterprises (Units) Any individual, above 18 years of age. There will be no income ceiling for assistance in setting up projects under PMEGP. For setting up of project costing above Rs.10 lakh in the Manufacturing sector and above ₹ 5,00,000 in the Business /Service sector, the beneficiaries should possess at least VIII standard pass educational qualification. Assistance under the scheme is available only for new projects sanctioned specifically under the PMEGP. Existing Units (under PMRY, REGP, or any other scheme of the Government of India or State Government) and the units that have already availed | H3: 0 | J3: =INT((ROW()-2)/50)+1 | K3: =IF(H3="","Pending",IF(OR(H3="0",H3="1",H3="2",H3="U"),"Complete","Invalid"))
A4: v2q-005-candidate-12 | B4: v2q-005 | C4: How many days of wage employment does MGNREGA guarantee a rural household in a financial year? | D4: MGNREGA guarantees at least 100 days of wage employment per financial year to a rural household whose adult members volunteer for unskilled work. | E4: pilot-v2-doc-pm-kmy-guidelines-0006-2652020c834e | F4: Pradhan Mantri Kisan Maan Dhan Yojana Operational Guidelines | G4: same day every month as enrolment date. The beneficiaries may also chose an option to pay their contributions on quarterly, 4-monthly or half-yearly basis. Such contributions will fall due on the same day of such period as the date of enrollment; 4 (x) The amount of the monthly contribution shall range between Rs.55 to Rs.200 per month depending upon the age of entry of the farmers into the Scheme, as per the following contribution chart: Superannuation Member's Government’s Total contribution Entry Age Age contribution (Rs.) contribution (Rs.) (Rs.) (1) (2) (3) (4) (5) 18 60 55 55 110 19 60 58 58 116 20 60 61 61 122 21 60 64 64 128 22 60 68 68 136 23 60 72 72 144 24 60 76 76 152 25 60 80 80 160 26 60 85 85 170 27 60 90 90 180 28 60 95 95 190 29 60 100 100 200 30 60 105 105 210 31 60 110 110 220 32 60 120 120 240 33 60 130 130 260 34 60 140 140 280 35 60 150 150 300 36 60 160 160 320 37 60 170 170 340 38 60 180 180 360 39 60 190 190 380 40 60 200 200 400 (xi) In case of death of subscriber before vesting date, the spouse of subscriber shall have an option of continuing the scheme by payment of remaining contributions under the scheme, provided she/he is not already an SMF beneficiary of the Scheme. The rate of contribution and vesting date shall remain the same. Pension accruals will be calculated as if subscriber were to be alive on the vesting date. However, the same pension would be payable to the spouse. Upon death of spouse after vesting date, pension corpus would be transferred back to | H4: 0 | J4: =INT((ROW()-2)/50)+1 | K4: =IF(H4="","Pending",IF(OR(H4="0",H4="1",H4="2",H4="U"),"Complete","Invalid"))
A5: v2q-027-candidate-14 | B5: v2q-027 | C5: What livelihood mechanism does PM SVANidhi offer street vendors, and which other programme from its ministry addresses housing shortages for eligible urban households? | D5: PM SVANidhi offers street vendors collateral-free working-capital loans, interest subsidy, and digital-payment incentives. PMAY-U, under the same Ministry of Housing and Urban Affairs, provides housing support for eligible urban households. | E5: pilot-v2-doc-pm-kisan-guidelines-0000-bbe94f08550e | F5: PM-KISAN Operational Guidelines | G5: PRADHAN MANTRI KISAN SAMMAN NIDHI SCHEME (PM-KISAN SCHEME) OPERATIONAL GUIDELINES (REVISED AS ON 29.03.2020) MINISTRY OF AGRICULTURE & FARMERS’ WELFARE DEPARTMENT OF AGRICULTURE, COOPERATION & FARMERS’ WELFARE (DAC&FW) 1 PRADHAN MANTRI KISAN SAMMAN NIDHI (PM-KISAN) SCHEME OPERATIONAL GUIDELINES 1. Scheme With a view to provide income support to all landholding farmers’ families in the country, having cultivable land, the Central Government has implemented a Central Sector Scheme, namely, “Pradhan Mantri Kisan Samman Nidhi (PM-KISAN)”. 2. Objective and Benefits The scheme aims to supplement the financial needs of all landholding farmers’ families in procuring various inputs to ensure proper crop health and appropriate yields, commensurate with the anticipated farm income as well as for domestic needs. Under the Scheme an amount of Rs.6000/- per year is released by the Central Government online directly into the bank accounts of the eligible farmers under Direct Benefit Transfer mode, subject to certain exclusions. 3. Definition of farmer’s family A landholder farmer’s family is defined as “a family comprising of husband, wife and minor children who owns cultivable land as per land records of the concerned State/UT”. The existing land-ownership system will be used for identification of beneficiaries for calculation of benefit. 4 Exclusions 4.1 The following categories of beneficiaries of higher economic status shall not be eligible for benefit under the scheme: (a) All Institutional Land holders; and (b) Farmer families in which one or more of its members belong to following categories : i) Former and present holders of constitutional posts ii) Former and present Ministers / State Ministers and former / present Members of Lok Sabha / Rajya Sabha / State Legislative Assemblies / State Legislative Councils, former and present Mayors of Municipal Corporations, former and present Chairpersons of District Panchayats. iii) All serving or retired officers and employees of Central / | H5: 0 | J5: =INT((ROW()-2)/50)+1 | K5: =IF(H5="","Pending",IF(OR(H5="0",H5="1",H5="2",H5="U"),"Complete","Invalid"))
A6: v2q-029-candidate-19 | B6: v2q-029 | C6: What migrant-focused facility distinguishes Ujjwala 2.0, and what clean-cooking transition was established by its predecessor programme? | D6: Ujjwala 2.0 added 1.6 crore LPG connections with a special facility for migrant households. Its predecessor, Pradhan Mantri Ujjwala Yojana, sought to replace traditional cooking fuels with LPG access for rural and deprived households. | E6: pilot-v2-doc-pm-gkay-0000-c29b96f46a80 | F6: Pradhan Mantri Garib Kalyan Anna Yojana | G6: Pradhan Mantri Garib Kalyan Anna Yojana. Ministry Of Finance. Department Of Economic Affairs. The scheme "Pradhan Mantri Garib Kalyan Anna Yojana (PMGKAY)" has been launched by the Department of Food and Public Distribution, Ministry of Consumer Affairs, Food and Public Distribution, Government of India, and aims to ensure food security for the poor and vulnerable sections of the country by providing free food foodgrains. It was announced on 26 March 2020 during the COVID-19 pandemic and is operated by the Department of Food and Public Distribution under the Ministry of Consumer Affairs, Food and Public Distribution. Through this scheme, free foodgrains (rice or wheat, depending on the State) are provided to eligible ration card holders covered under the National Food Security Act, 2013, namely Antyodaya Anna Yojana (AAY) households and Priority Households (PHH). From 1 January 2023, the scheme was integrated into the food security framework, and foodgrains earlier given at the highly subsidised rates of ₹1, ₹2, and ₹3 per kilogram for coarse cereals, wheat, and rice, respectively, are now provided free of cost. The scheme has been extended by the Union Cabinet for 5 years starting from 1 January 2024 and is approved for continuation till 31 December 2028, with a total financial outlay of ₹11.80 lakh crore (₹11,80,000 crore). The scheme is implemented through the Targeted Public Distribution System (TPDS) by the state governments and Union Territory Administrations, with foodgrain allocation by the Government of India.. The scheme aims to ensure food security for the poor. Through this scheme, free foodgrains are provided to eligible ration card holders under the National Food Security Act, 2013.. Antyodaya Anna Yojana (AAY) families receive 35 kilograms of foodgrains per family per month. Priority Household (PHH) beneficiaries receive 5 kilograms of foodgrains per person per month. The foodgrains are provided as | H6: 0 | J6: =INT((ROW()-2)/50)+1 | K6: =IF(H6="","Pending",IF(OR(H6="0",H6="1",H6="2",H6="U"),"Complete","Invalid"))
A7: v2q-034-candidate-08 | B7: v2q-034 | C7: How do three programmes meet distinct household needs for rural housing, clean cooking, and food security? | D7: PMAY-G supports pucca rural housing with basic amenities; PMUY provides LPG access to deprived households replacing traditional cooking fuels; PMGKAY provides free foodgrains to eligible AAY and PHH ration-card holders. | E7: pilot-v2-doc-pmegp-0003-43256e8e6645 | F7: Prime Minister's Employment Generation Programme | G7: sector and above ₹ 5,00,000 in the Business /Service sector, the beneficiaries should possess at least VIII standard pass educational qualification. Assistance under the scheme is available only for new projects sanctioned specifically under the PMEGP. Existing Units (under PMRY, REGP, or any other scheme of the Government of India or State Government) and the units that have already availed of Government Subsidy under any other scheme of the Government of India or State Government are not eligible. For up-gradation of existing PMEGP / REGP / MUDRA units Margin Money(subsidy)claimed under PMEGP has to be successfully adjusted on the completion of the lock-in period of 3 years. The first loan under PMEGP/REGP/MUDRA has to be successfully repaid in the stipulated time. The unit is profit-making with good turnover and has the potential for further growth in turnover and profit with modernization/upgrading of the technology. Reservation / Preference / Priority Priority will be given to the persons affected by natural calamities/disasters in the areas which are declared as affected by "disaster" as defined under Section 2(d) of the Disaster Management Act, 2005 by the Ministry of Home Affairs.. For PMEGP new enterprises (Units): Existing Units (under PMRY, REGP, or any other scheme of the Government of India or State Government) and the units that have already availed of Government Subsidy under any other scheme of the Government of India or State Government are not eligible. Only one person from one family is eligible for obtaining financial assistance for setting up of projects under PMEGP. The 'family’ includes self and spouse. Negative List of Activities: The following list of activities will not be permitted under PMEGP for setting up of micro enterprises/ projects/units:- Any Industry/ Business connected with Meat(slaughtered), i.e., processing, canning and/or serving items made of it as food, production/Manufacturing or | H7: 0 | J7: =INT((ROW()-2)/50)+1 | K7: =IF(H7="","Pending",IF(OR(H7="0",H7="1",H7="2",H7="U"),"Complete","Invalid"))
A8: v2q-019-candidate-22 | B8: v2q-019 | C8: What role does the Ministry of Petroleum and Natural Gas have in Ujjwala 2.0? | D8: The ministry introduced Ujjwala 2.0 to provide LPG connections and promote clean cooking fuel among poor, rural, and deprived households. | E8: pilot-v2-doc-apy-0000-c43dd88d7899 | F8: Atal Pension Yojana | G8: Atal Pension Yojana. Ministry Of Finance. Department of Financial Service. Banks. Atal Pension Yojana (APY) is an old age income security scheme for a savings account holder in the age group of 18-40 years who is not an income tax-payee. The scheme helps in addressing the longevity risks among the workers in the unorganized sector and encourages the workers to voluntarily save for their retirement. Focus of APY The scheme is mainly targeted at the poor, the under-privileged and workers in the unorganized sector. APY Subscriber Contribution Chart - https://www.npscra.nsdl.co.in/nsdl/scheme-details/APYSubscribersContributionChart1.pdf Charges and fees and overdue interest under APY: The charges and fees and the overdue interest for non-payment or delayed payment of prescribed contribution amount shall be levied on the subscribers of APY. These charges and their method of application shall be prescribed by PFRDA from time to time, in consultation with the Central Government. Raising Grievance Under APY A subscriber can raise grievance anytime free of cost from anywhere by visiting: www.npscra.nsdl.co.in &gt;&gt;Home &gt;&gt; select: NPS-Lite or through CGMS Subscriber raising the grievance will be allotted a token number against the grievance raised. Subscriber may check the status of the grievance under “Check the status of Grievance / Enquiry already registered”.. Atal Pension Yojana (APY) is an old age income security scheme for a savings account holder in the age group of 18-40 years, who is not an income tax-payee. It helps to address longevity risks among workers in unorganized sector and encourages the workers to voluntarily save for retirement.. Upon exit on attaining 60 years The subscriber shall receive the following three benefits on attaining the age of 60: (i) Guaranteed minimum pension amount: Each subscriber under APY shall receive a guaranteed minimum pension of Rs. 1000/- per month or Rs. 2000/- per month or Rs. 3000/- per | H8: 0 | J8: =INT((ROW()-2)/50)+1 | K8: =IF(H8="","Pending",IF(OR(H8="0",H8="1",H8="2",H8="U"),"Complete","Invalid"))
A9: v2q-007-candidate-08 | B9: v2q-007 | C9: What is the full form of PMJJBY, and which event does its life insurance cover? | D9: PMJJBY stands for Pradhan Mantri Jeevan Jyoti Bima Yojana and provides life-insurance cover for death due to any reason. | E9: pilot-v2-doc-pmjdy-0001-95c3d046d79a | F9: Pradhan Mantri Jan Dhan Yojana | G9: Basic Savings Bank Deposit Account (BSBDA) Any Indian citizen eligible to open a regular bank account can open a BSBDA. Such an account does not require any minimum balance maintenance. The account holders can use both bank branches, ATMs and Banking Correspondents (BCs) for depositing and withdrawing cash. However, one cannot withdraw cash more than four times a month. Small Account/Chota Khata Under Jan Dhan Yojana, people can open small bank accounts without presenting legal documents. These accounts would be valid normally for a period of twelve months. Thereafter, such accounts would be allowed to a continue for a further period of twelve more months, if the account-holder provides a document showing that he/she has applied for any of the Officially Valid Document, within 12 months of opening the small account. RuPay Debit Card with inbuilt accident insurance Under PMJDY, a free Rupay debit card, with inbuilt accident insurance cover of Rs.2 lakhs (Rs 1 lakh for accounts opened before 28.08.2018), is issued to all beneficiaries. Overdraft Facility Under PMJDY, beneficiaries can avail OD facility upto Rs. 10,000/-. Business Correspondents (BCs)/Bank Mitras BCs/Bank Mitras are retail agents engaged by banks for providing banking services at locations other than a bank branch/ATM. It is mainly meant for the rural areas, where bank branches are far-flung. BCs/Bank Mitras connect with the residents and guide them with banking solutions such as savings accounts, deposits, payments and withdrawals, mini account statements, etc. Banks with their strong network of BCs/Bank Mitras are providing hassle free services to the customers in remote / rural areas.. The applicant should be an Indian National. If minors above ten years apply, they will require support from their legal guardians for administering their PMJDY account.. Step 1- Go to the official portal of PMJDY. Step 2- Under the &quot;e-documents&quot; section, | H9: 0 | J9: =INT((ROW()-2)/50)+1 | K9: =IF(H9="","Pending",IF(OR(H9="0",H9="1",H9="2",H9="U"),"Complete","Invalid"))
A10: v2q-029-candidate-13 | B10: v2q-029 | C10: What migrant-focused facility distinguishes Ujjwala 2.0, and what clean-cooking transition was established by its predecessor programme? | D10: Ujjwala 2.0 added 1.6 crore LPG connections with a special facility for migrant households. Its predecessor, Pradhan Mantri Ujjwala Yojana, sought to replace traditional cooking fuels with LPG access for rural and deprived households. | E10: pilot-v2-doc-pmay-g-0001-db2db8af1543 | F10: Pradhan Mantri Awaas Yojana - Gramin | G10: years from 2016-17 to 2018-19 and enable construction of quality houses by the beneficiaries using local materials, designs and trained masons. For houses to become homes, adoption of a habitat approach through convergence is proposed.. Launch on 1st April 2016, Pradhan Mantri Awaas Yojana Gramin (PMAY-G) is centre's flagship mission by the Ministry of Rural Development (MoRD), implemented by the Ministry of Housing and Urban Affairs (MoHUA). PMAY-G addresses the rural housing shortage and bridges the housing deficit in rural areas. Financial Assistance of ₹ 1,20,000 per unit for plain areas; and ₹ 1,30,000 per unit for hilly areas, difficult areas, and IAP districts (Himalayan states, North-Eastern states, and Union Territories of Jammu & Kashmir). A willing beneficiary can avail of institutional finance (loan) of up to ₹ 70,000 at 3% lower interest rate, to build a permanent house. The maximum principal amount for which subsidy can be sought is ₹ 2,00,000. The minimum size of the house shall be is 25 sq m including a dedicated area for hygienic cooking. In convergence with Swachh Bharat Mission-Gramin (SBM-G), the beneficiaries get financial assistance of up to ₹ 12,000 for the construction of toilets. In convergence with MGNREGA, the beneficiary is entitled to employment as unskilled labor (Rural Mason Training) at ₹ 90.95 per day for 95 days. In convergence with Pradhan Mantri Ujjwala Yojana, one LPG connection per house is provided. Convergence with different government programmes for piped drinking water, electricity connection, clean & efficient cooking fuel, treatment of social and liquid waste, etc. Payments are made electronically directly to bank accounts or post office accounts that are linked to Aadhaar. Note: Beneficiaries are identified using the "Housing Deprivation Parameters" from the Socio-Economic and Caste Census (SECC) 2011, further verified by the Gram Sabhas.. The universe of eligible beneficiaries under | H10: 0 | J10: =INT((ROW()-2)/50)+1 | K10: =IF(H10="","Pending",IF(OR(H10="0",H10="1",H10="2",H10="U"),"Complete","Invalid"))
A11: v2q-021-candidate-12 | B11: v2q-021 | C11: How do insurance companies and banks participate in PMFBY? | D11: PMFBY is implemented through a network of insurance companies and banks to provide crop-insurance protection to farmers. | E11: pilot-v2-doc-ab-pmjay-0001-a632a7205efc | F11: Ayushman Bharat - Pradhan Mantri Jan Arogya Yojana | G11: per family per year for secondary and tertiary hospitalization to poor and vulnerable families.. AB PM-JAY is a health insurance scheme for low-income families in rural and urban areas. The scheme aims to provide affordable healthcare facilities to the Poor. It is the largest health assurance scheme in the world which aims at providing a health cover of ₹5,00,000/- per family per year.. Financial Health Insurance Cover: Annual Hospitalization Coverage: Cashless coverage up to ₹5,00,000/- per family per year.- Comprehensive Treatment Costs: Covers consultation, medicines, diagnostics, surgery, ICU, implants, accommodation, and food.- Pre and Post Hospitalization Support: Covers 3 days pre-hospitalization and 15 days post-hospitalization expenses.- Treatment Complication Coverage: Covers complications arising during treatment. Coverage Features: Pre-Existing Disease Coverage: Covers all pre-existing diseases from day one.- No Family Size Limit: No restriction on age, gender, or family size.- Nationwide Portability: Benefits available across India in empanelled hospitals.- Wide Procedure Coverage: Covers approximately 1,929 medical procedures.. Rural Beneficiaries Out of the total seven deprivation criteria for rural areas, PM-JAY covered all such families who fall into at least one of the following six deprivation criteria and automatic inclusion(Destitute/ living on alms, manual scavenger households, primitive tribal group, legally released bonded labour) criteria: Only one room with kucha walls and kucha roof No adult member between ages 16 to 59 Households with no adult male member between ages 16 to 59 Disabled member and no able-bodied adult member SC/ST households Landless households deriving a major part of their income from manual casual labour Automatically includedHouseholds without shelter Destitute/ living on alms, Manual scavenger families, Primitive tribal groups, Legally released bonded labour. Urban Beneficiaries For urban areas, the following 11 occupational categories of workers are eligible for the scheme: Ragpicker Beggar Domestic worker Street vendor/ Cobbler/hawker / other service provider working on streets | H11: 0 | J11: =INT((ROW()-2)/50)+1 | K11: =IF(H11="","Pending",IF(OR(H11="0",H11="1",H11="2",H11="U"),"Complete","Invalid"))
A12: v2q-002-candidate-07 | B12: v2q-002 | C12: What maximum premium rates can farmers pay under PMFBY for Kharif, Rabi, and annual commercial or horticultural crops? | D12: Farmers pay at most 2% for Kharif food and oilseed crops, 1.5% for Rabi food and oilseed crops, and 5% for annual commercial or horticultural crops. | E12: pilot-v2-doc-pmay-g-0001-db2db8af1543 | F12: Pradhan Mantri Awaas Yojana - Gramin | G12: years from 2016-17 to 2018-19 and enable construction of quality houses by the beneficiaries using local materials, designs and trained masons. For houses to become homes, adoption of a habitat approach through convergence is proposed.. Launch on 1st April 2016, Pradhan Mantri Awaas Yojana Gramin (PMAY-G) is centre's flagship mission by the Ministry of Rural Development (MoRD), implemented by the Ministry of Housing and Urban Affairs (MoHUA). PMAY-G addresses the rural housing shortage and bridges the housing deficit in rural areas. Financial Assistance of ₹ 1,20,000 per unit for plain areas; and ₹ 1,30,000 per unit for hilly areas, difficult areas, and IAP districts (Himalayan states, North-Eastern states, and Union Territories of Jammu & Kashmir). A willing beneficiary can avail of institutional finance (loan) of up to ₹ 70,000 at 3% lower interest rate, to build a permanent house. The maximum principal amount for which subsidy can be sought is ₹ 2,00,000. The minimum size of the house shall be is 25 sq m including a dedicated area for hygienic cooking. In convergence with Swachh Bharat Mission-Gramin (SBM-G), the beneficiaries get financial assistance of up to ₹ 12,000 for the construction of toilets. In convergence with MGNREGA, the beneficiary is entitled to employment as unskilled labor (Rural Mason Training) at ₹ 90.95 per day for 95 days. In convergence with Pradhan Mantri Ujjwala Yojana, one LPG connection per house is provided. Convergence with different government programmes for piped drinking water, electricity connection, clean & efficient cooking fuel, treatment of social and liquid waste, etc. Payments are made electronically directly to bank accounts or post office accounts that are linked to Aadhaar. Note: Beneficiaries are identified using the "Housing Deprivation Parameters" from the Socio-Economic and Caste Census (SECC) 2011, further verified by the Gram Sabhas.. The universe of eligible beneficiaries under | H12: 0 | J12: =INT((ROW()-2)/50)+1 | K12: =IF(H12="","Pending",IF(OR(H12="0",H12="1",H12="2",H12="U"),"Complete","Invalid"))
A13: v2q-024-candidate-10 | B13: v2q-024 | C13: Which national health-assurance programme does NHA implement under the health ministry? | D13: The National Health Authority implements AB-PMJAY under the Ministry of Health and Family Welfare. | E13: pilot-v2-doc-pm-janman-0002-d0844e3327b6 | F13: PM Janjati Adivasi Nyaya Maha Abhiyan (PM JANMAN) | G13: physical survey conducted by state governments using the mobile application on the PM Gati-shakti Portal. Eligibility Specific to Interventions The applicant household seeking a pucca house must currently reside in a kaccha house. The applicant household seeking solar power solutions must be an unelectrified household not covered under the Revamped Distribution Sector Scheme (RDSS). The applicant household seeking an on-grid electricity connection shall be an identified beneficiary household under PM-JANMAN, irrespective of standard eligibility criteria under the Revamped Distribution Sector Scheme (RDSS) for the State and Electricity distribution company (DISCOM).. Step 1: Initiation of Identification and Physical Survey The State Governments initiates a detailed physical survey of each Particularly Vulnerable Tribal Group habitation to ascertain the gaps regarding the 11 critical interventions covered under the mission. The data gathered during this exhaustive survey is simultaneously updated and cross-verified on a mobile application developed on the PM Gati-shakti Portal. Step 2: Facilitation of Application Filing for Eligible Beneficiaries The Block Level Implementation Team, consisting of officers designated by the District Collector, will be responsible for identifying each beneficiary family who has not yet been saturated with entitlements and will facilitate the necessary application filing for the respective schemes. The District Level Committee is also responsible for the registration and filling of applications of eligible beneficiaries for each scheme covered under the mission. Step 3: Verification and Project Approval Following the application filing and preliminary eligibility checks, certain proposals for infrastructure, such as the sanctioning of Multi-Purpose Centers, must be forwarded by the Secretary/Principal Secretary, State Tribal Welfare Department to the Ministry of Tribal Affairs. These proposals are subsequently examined by the relevant division, approved by the Mission Director of PM-JANMAN, and granted financial concurrence by the Internal Finance Division. | H13: 0 | J13: =INT((ROW()-2)/50)+1 | K13: =IF(H13="","Pending",IF(OR(H13="0",H13="1",H13="2",H13="U"),"Complete","Invalid"))
... A756: v2q-004-candidate-19 | B756: v2q-004 | C756: What is the maximum micro-loan amount stated for PMMY? | D756: PMMY facilitates micro-credit loans up to ₹20 lakh for eligible income-generating micro-enterprises. | E756: pilot-v2-doc-apy-0001-add48d27a4a2 | F756: Atal Pension Yojana | G756: unorganized sector and encourages the workers to voluntarily save for retirement.. Upon exit on attaining 60 years The subscriber shall receive the following three benefits on attaining the age of 60: (i) Guaranteed minimum pension amount: Each subscriber under APY shall receive a guaranteed minimum pension of Rs. 1000/- per month or Rs. 2000/- per month or Rs. 3000/- per month or Rs. 4000/- per month or Rs. 5000/- per month, after the age of 60 years until death. (ii) Guaranteed minimum pension amount to the spouse: After the subscriber’s demise, the spouse of the subscriber shall be entitled to receive the same pension amount as that of the subscriber,until death. (iii) Return of the pension wealth to the nominee of the subscriber: After the demise of both the subscriber and the spouse, the nominee of the subscriber shall be entitled to receive the pension wealth, as accumulated till the subscriber&#39;s age of 60 years. Contributions to the Atal Pension Yojana (APY) are eligible for tax benefits similar to the National Pension System (NPS) under section 80CCD(1). Voluntary exit (Exit before 60 Years of age): The subscriber shall be refunded only the contributions made by him to APY alongwith the net actual accrued income earned on his contributions (after deducting the account maintenance charges). However, in case of subscribers who joined the scheme before 31st March 2016 and have received the Government Co-Contribution, shall not receive the same including the accrued income earned thereon. For death before 60 years Option 1: In case of death of the subscriber before 60 years, option will be available to the spouse of the subscriber to continue contribution in the APY account of the subscriber, which can be maintained in the spouse’s name, for the remaining vesting period, till the original subscriber would have | H756: 0 | J756: =INT((ROW()-2)/50)+1 | K756: =IF(H756="","Pending",IF(OR(H756="0",H756="1",H756="2",H756="U"),"Complete","Invalid"))

Sheet Instructions
A1: Phase 6 Blind Relevance Judging
A3: Purpose | B3: Human relevance grading of 755 blinded query–chunk pairs.
A4: Grade 2 | B4: Candidate directly supports reference answer.
A5: Grade 1 | B5: Candidate gives useful context but is insufficient alone.
A6: Grade 0 | B6: Candidate is irrelevant or misleading for question.
A7: Grade U | B7: Unclear; requires later adjudication.
A8: Rationale | B8: Required for U and recommended for difficult or borderline cases.
A9: Workflow | B9: Complete one numbered batch at a time. Use Progress sheet to track completion.
A10: Boundary | B10: Do not inspect sealed provenance, system identity, rank, score, qrels, or metrics while judging.

Sheet Progress
A1: Judging Progress
A3: Total pairs | B3: 755
A4: Completed | B4: =COUNTIF('Judging'!$K$2:$K$756,"Complete")
A5: Pending | B5: =COUNTIF('Judging'!$K$2:$K$756,"Pending")
A6: Invalid | B6: =COUNTIF('Judging'!$K$2:$K$756,"Invalid")
A7: Completion | B7: =B4/B3
A10: Batch | B10: Rows | C10: Completed | D10: Remaining
A11: 1 | B11: 50 | C11: =COUNTIFS('Judging'!$J$2:$J$756,A11,'Judging'!$K$2:$K$756,"Complete") | D11: =B11-C11
A12: 2 | B12: 50 | C12: =COUNTIFS('Judging'!$J$2:$J$756,A12,'Judging'!$K$2:$K$756,"Complete") | D12: =B12-C12
A13: 3 | B13: 50 | C13: =COUNTIFS('Judging'!$J$2:$J$756,A13,'Judging'!$K$2:$K$756,"Complete") | D13: =B13-C13
A14: 4 | B14: 50 | C14: =COUNTIFS('Judging'!$J$2:$J$756,A14,'Judging'!$K$2:$K$756,"Complete") | D14: =B14-C14
A15: 5 | B15: 50 | C15: =COUNTIFS('Judging'!$J$2:$J$756,A15,'Judging'!$K$2:$K$756,"Complete") | D15: =B15-C15
A16: 6 | B16: 50 | C16: =COUNTIFS('Judging'!$J$2:$J$756,A16,'Judging'!$K$2:$K$756,"Complete") | D16: =B16-C16
A17: 7 | B17: 50 | C17: =COUNTIFS('Judging'!$J$2:$J$756,A17,'Judging'!$K$2:$K$756,"Complete") | D17: =B17-C17
A18: 8 | B18: 50 | C18: =COUNTIFS('Judging'!$J$2:$J$756,A18,'Judging'!$K$2:$K$756,"Complete") | D18: =B18-C18
A19: 9 | B19: 50 | C19: =COUNTIFS('Judging'!$J$2:$J$756,A19,'Judging'!$K$2:$K$756,"Complete") | D19: =B19-C19
A20: 10 | B20: 50 | C20: =COUNTIFS('Judging'!$J$2:$J$756,A20,'Judging'!$K$2:$K$756,"Complete") | D20: =B20-C20
A21: 11 | B21: 50 | C21: =COUNTIFS('Judging'!$J$2:$J$756,A21,'Judging'!$K$2:$K$756,"Complete") | D21: =B21-C21
A22: 12 | B22: 50 | C22: =COUNTIFS('Judging'!$J$2:$J$756,A22,'Judging'!$K$2:$K$756,"Complete") | D22: =B22-C22
... A26: 16 | B26: 5 | C26: =COUNTIFS('Judging'!$J$2:$J$756,A26,'Judging'!$K$2:$K$756,"Complete") | D26: =B26-C26
